Workbook

Sheet Dashboard
A1: Herbal Monograph Control Center
A2: Use this sheet to monitor monograph completeness, citation health, total scoring, and editorial review priority before publishing. | B2: Use this sheet to monitor monograph completeness, citation health, total scoring, and editorial review priority before publishing. | C2: Use this sheet to monitor monograph completeness, citation health, total scoring, and editorial review priority before publishing. | D2: Use this sheet to monitor monograph completeness, citation health, total scoring, and editorial review priority before publishing. | E2: Use this sheet to monitor monograph completeness, citation health, total scoring, and editorial review priority before publishing. | F2: Use this sheet to monitor monograph completeness, citation health, total scoring, and editorial review priority before publishing. | G2: Use this sheet to monitor monograph completeness, citation health, total scoring, and editorial review priority before publishing. | H2: Use this sheet to monitor monograph completeness, citation health, total scoring, and editorial review priority before publishing. | J2: Next Upgrade Panel
A3: KPI | B3: Value | D3: Score band | E3: Count | G3: Citation health | H3: Count | J3: Mechanism tags tracked | K3: 13
A4: Total monographs | B4: 17 | D4: 8+ | E4: 6 | G4: Present | H4: 11 | J4: Rows needing source normalization | K4: 6
A5: Schema-upgraded rows | B5: 17 | D5: 7 | E5: 4 | G5: Needs normalization | H5: 6 | J5: Rows with missing dosage | K5: 0
A6: High-confidence rows | B6: 4 | D6: 6 | E6: 7 | G6: Partial/missing | H6: 0 | J6: Rows marked Ready | K6: 0
A7: Citation present | B7: 11 | D7: <=5 | E7: 0
A8: Needs normalization | B8: 6
A9: Average total score | B9: 6.9
A10: Immediate actions | B10: Count | D10: Publishing readiness | E10: Count | G10: Review priority | H10: Count
A11: Missing dosage | B11: 10 | D11: Ready | E11: 6 | G11: High | H11: 6
A12: Missing standardization | B12: 8 | D12: Near ready | E12: 11 | G12: Medium | H12: 11
A13: Missing marker compounds | B13: 5 | D13: Needs work | E13: 0 | G13: Low | H13: 0
A14: Low or medium confidence | B14: 13
A16: Monograph workflow rules
A17: High review priority | B17: Citation normalization missing or citation status is missing.
A18: Medium review priority | B18: Core monograph fields missing such as dosage, standardization, or marker compounds.
A19: Ready | B19: High field coverage with present citations; suitable for editorial polishing and publication prep.

Sheet Herb Monographs
A1: name | B1: slug | C1: scientificName | D1: monographType | E1: category | F1: plantPartUsed | G1: commonNames | H1: region | I1: summary | J1: description | K1: activeCompounds | L1: markerCompounds | M1: mechanism | N1: mechanismTags | O1: evidenceLevel | P1: safetyNotes | Q1: interactions | R1: contraindications | S1: preparation | T1: dosage | U1: standardization | V1: qualityConcerns | W1: confidence | X1: status | Y1: sources | Z1: citationStatus | AA1: sourceAuthority | AB1: summaryCitations | AC1: mechanismCitations | AD1: safetyCitations | AE1: interactionCitations | AF1: notesForCodex | AG1: score_confidence | AH1: score_evidence | AI1: score_citation | AJ1: totalScore | AK1: reviewPriority | AL1: dosageStatus | AM1: sourceTier | AN1: completenessPct | AO1: readinessFlag | AP1: editorialOwner | AQ1: reviewDate | AR1: publishStatus | AS1: qaStatus | AT1: sourceLockFlag | AU1: frontendReadyFlag | AV1: webCopyReadyFlag | AW1: publishBlocker | AX1: reviewRound | AY1: reviewerName | AZ1: reviewerRole | BA1: reviewStage | BB1: reviewStatus | BC1: reviewerNotes | BD1: approvalTimestamp | BE1: lastModifiedTimestamp | BF1: changeSummary | BG1: rowReviewKey | BH1: historyEntries
A2: Ashwagandha | B2: ashwagandha | C2: Withania somnifera | D2: herb | E2: shrub | F2: root | G2: ashwagandha; Indian ginseng; winter cherry | H2: Native to India, the Middle East and parts of Africa and Asia. | I2: Ashwagandha (Withania somnifera) is a shrub monograph focused on the root used in herbal preparations. It is associated with Native to India, the Middle East and parts of Africa and Asia. Withanolides are thought to mediate adaptogenic and neuroprotective effects by modulating HPA-axis signaling, NF-κB, Nrf2 and GABAergic pathways. Short-term use appears safe; side effects include drowsiness and GI upset. | J2: Ashwagandha is represented here as a monograph-style entry centered on the root. Key reported compounds include withaferin A; withanolide D; withanolide A; withanoside IV; sitoindosides; alkaloids. Typical preparation forms: Root powders and standardized extracts. Withanolides are thought to mediate adaptogenic and neuroprotective effects by modulating HPA-axis signaling, NF-κB, Nrf2 and GABAergic pathways. Interaction profile: May potentiate sedatives, antihypertensives, antidiabetics, thyroid hormones, and immunosuppressants. Use caution or avoid in: Pregnancy, breastfeeding, autoimmune disease, thyroid disorders, liver disease. | K2: withaferin A; withanolide D; withanolide A; withanoside IV; sitoindosides; alkaloids | L2: withanolides | M2: Withanolides are thought to mediate adaptogenic and neuroprotective effects by modulating HPA-axis signaling, NF-κB, Nrf2 and GABAergic pathways. | N2: adaptogen; anti-inflammatory; antioxidant; gabaergic | O2: human + preclinical | P2: Short-term use appears safe; side effects include drowsiness and GI upset. Rare liver injury has been reported. | Q2: May potentiate sedatives, antihypertensives, antidiabetics, thyroid hormones, and immunosuppressants. | R2: Pregnancy, breastfeeding, autoimmune disease, thyroid disorders, liver disease. | S2: Root powders and standardized extracts. | T2: 300–500 mg root extract twice daily | U2: Often standardized to withanolides. | W2: medium | X2: schema-upgraded | Y2: Recovered from prior batch output in this conversation | Z2: needs-source-normalization | AA2: conversation-recovered | AB2: Recovered from prior batch output in this conversation | AC2: Recovered from prior batch output in this conversation | AD2: Recovered from prior batch output in this conversation | AE2: Recovered from prior batch output in this conversation | AF2: Separate root-based products from leaf-heavy extracts. | AG2: 2 | AH2: 3 | AI2: 1 | AJ2: 6 | AK2: High | AL2: Present | AM2: Conversation-recovered | AN2: 1 | AO2: Near ready | AP2: Research | AR2: Source review | AS2: Not started | AT2: No | AU2: No | AV2: Yes | AW2: Normalize source record | AX2: 1 | BA2: =IF($AR2="Published","Published",IF($AS2="Passed","Approved",IF($AR2="Ready for QA","QA review",IF($AR2="Source review","Source review",IF($AR2="Editorial polish","Editorial review","Review pending"))))) | BB2: =IF(OR($AR2="Published",$AS2="Passed",AND($AY2<>"",$BD2<>"")),"Approved",IF(OR($AY2<>"",$BC2<>"",$BF2<>""),"In review","Pending")) | BE2: =IF(OR($AY2<>"",$AZ2<>"",$BC2<>"",$BF2<>""),TODAY(),"") | BG2: =$B2&"-R"&$AX2 | BH2: =COUNTIF('Change History'!$C:$C,$B2)
A3: Black Cohosh | B3: black-cohosh | C3: Actaea racemosa | D3: herb | E3: rhizome | F3: root; rhizome | G3: black cohosh; black snakeroot; Actaea racemosa | H3: Native to North America, especially the eastern United States. | I3: Black Cohosh (Actaea racemosa) is a rhizome monograph focused on the root; rhizome used in herbal preparations. It is associated with Native to North America, especially the eastern United States. Proposed mechanism based on preclinical and limited clinical data: black cohosh may act through serotonergic pathways, selective estrogen receptor modulation, and anti-inflammatory signaling rather than as a classical estrogen. Generally well tolerated in short-term studies, but rare cases of liver injury have been reported. | J3: Black Cohosh is represented here as a monograph-style entry centered on the root; rhizome. Key reported compounds include triterpene glycosides (actein, 23-epi-26-deoxyactein); cimifugoside; caffeic acid derivatives; fukinolic acid. Typical preparation forms: Root and rhizome used in standardized extracts, capsules, tablets, and tinctures. Proposed mechanism based on preclinical and limited clinical data: black cohosh may act through serotonergic pathways, selective estrogen receptor modulation, and anti-inflammatory signaling rather than as a classical estrogen. Interaction profile: Potential interactions with hepatotoxic drugs and with medications affecting estrogen or serotonergic pathways. Use caution or avoid in: Avoid in pregnancy and breastfeeding. Use caution in liver disease or hormone-sensitive conditions. | K3: triterpene glycosides (actein, 23-epi-26-deoxyactein); cimifugoside; caffeic acid derivatives; fukinolic acid | L3: actein; 23-epi-26-deoxyactein | M3: Proposed mechanism based on preclinical and limited clinical data: black cohosh may act through serotonergic pathways, selective estrogen receptor modulation, and anti-inflammatory signaling rather than as a classical estrogen. | N3: serotonergic; anti-inflammatory; hormonal | O3: preclinical + limited human | P3: Generally well tolerated in short-term studies, but rare cases of liver injury have been reported. Product contamination or misidentification is a known issue. | Q3: Potential interactions with hepatotoxic drugs and with medications affecting estrogen or serotonergic pathways. | R3: Avoid in pregnancy and breastfeeding. Use caution in liver disease or hormone-sensitive conditions. | S3: Root and rhizome used in standardized extracts, capsules, tablets, and tinctures. | V3: Adulteration/misidentification risk in commercial products. | W3: medium | X3: schema-upgraded | Y3: NCCIH; NIH ODS; PubMed mechanism review PMC3046019 | Z3: present | AA3: NCCIH; NIH/ODS; PubMed/PMC | AB3: NCCIH; NIH ODS; PubMed mechanism review PMC3046019 | AC3: NCCIH; NIH ODS; PubMed mechanism review PMC3046019 | AD3: NCCIH; NIH ODS; PubMed mechanism review PMC3046019 | AE3: NCCIH; NIH ODS; PubMed mechanism review PMC3046019 | AF3: Treat menopausal mechanism claims as mixed evidence, not established estrogenic action. | AG3: 2 | AH3: 3 | AI3: 3 | AJ3: 8 | AK3: Medium | AL3: Missing | AM3: Linked primary/secondary | AN3: 0.85714286 | AO3: Ready | AP3: Editorial | AR3: Ready for QA | AS3: Not started | AT3: Yes | AU3: Yes | AV3: Yes | AX3: 1 | BA3: =IF($AR3="Published","Published",IF($AS3="Passed","Approved",IF($AR3="Ready for QA","QA review",IF($AR3="Source review","Source review",IF($AR3="Editorial polish","Editorial review","Review pending"))))) | BB3: =IF(OR($AR3="Published",$AS3="Passed",AND($AY3<>"",$BD3<>"")),"Approved",IF(OR($AY3<>"",$BC3<>"",$BF3<>""),"In review","Pending")) | BE3: =IF(OR($AY3<>"",$AZ3<>"",$BC3<>"",$BF3<>""),TODAY(),"") | BG3: =$B3&"-R"&$AX3 | BH3: =COUNTIF('Change History'!$C:$C,$B3)
A4: Echinacea Purpurea | B4: echinacea-purpurea | C4: Echinacea purpurea | D4: herb | E4: herb | F4: unspecified | G4: echinacea; purple coneflower | H4: Native to the central and eastern United States; now cultivated and introduced in Europe and other temperate regions【55003496660111†L75-L130】. | I4: Echinacea Purpurea (Echinacea purpurea) is a herb monograph focused on the unspecified used in herbal preparations. It is associated with Native to the central and eastern United States; now cultivated and introduced in Europe and other temperate regions【55003496660111†L75-L130】. Roots, leaves and flowers of Echinacea purpurea contain mixtures of lipophilic alkamides and hydrophilic caffeic acid derivatives such as chicoric acid and echinacoside, along with polysaccharides and glycoproteins【880087072039746†L166-L200】【840476591578855†L240-L305】. Short‑term use of echinacea extracts appears safe for most adults. | J4: Echinacea Purpurea is represented here as a monograph-style entry centered on the unspecified. Key reported compounds include alkamides; chicoric acid; echinacoside; caffeic acid; cynarin. Typical preparation forms: Medicinal products use the roots and aerial parts in teas, juices, tinctures and standardized extracts. Roots, leaves and flowers of Echinacea purpurea contain mixtures of lipophilic alkamides and hydrophilic caffeic acid derivatives such as chicoric acid and echinacoside, along with polysaccharides and glycoproteins【880087072039746†L166-L200】【840476591578855†L240-L305】. These constituents stimulate immune function by enhancing phagocytosis, activating fibroblasts and respiratory burst activity, and modulating nitric‑oxide and cytokine production via cannabinoid type‑2 receptors【880087072039746†L215-L243】. They also inhibit cyclo‑oxygenase and lipoxygenase enzymes. Most mechanistic data are from cell and animal studies; human evidence is limited. Interaction profile: Echinacea may interact with immunosuppressant drugs by stimulating immune activity and could affect the pharmacokinetics of drugs metabolised by cytochrome P450 enzymes; caution is advised when taken with hepatic substrates or caffeine. Use caution or avoid in: Individuals with autoimmune disorders or allergies to ragweed and other Asteraceae plants should avoid echinacea. Use during pregnancy or breastfeeding is not recommended. People taking immunosuppressant drugs should avoid echinacea due to potential antagonism. | K4: alkamides; chicoric acid; echinacoside; caffeic acid; cynarin | M4: Roots, leaves and flowers of Echinacea purpurea contain mixtures of lipophilic alkamides and hydrophilic caffeic acid derivatives such as chicoric acid and echinacoside, along with polysaccharides and glycoproteins【880087072039746†L166-L200】【840476591578855†L240-L305】. These constituents stimulate immune function by enhancing phagocytosis, activating fibroblasts and respiratory burst activity, and modulating nitric‑oxide and cytokine production via cannabinoid type‑2 receptors【880087072039746†L215-L243】. They also inhibit cyclo‑oxygenase and lipoxygenase enzymes. Most mechanistic data are from cell and animal studies; human evidence is limited. | N4: immunomodulatory | P4: Short‑term use of echinacea extracts appears safe for most adults. Reported side effects include digestive upset and rash; allergic reactions can occur, especially in individuals sensitive to plants in the Asteraceae family. Some children have developed rashes after echinacea use. Safety during pregnancy or breastfeeding is not established. There is conflicting evidence about whether echinacea alters the metabolism of drugs processed by the liver; theoretical interactions with immunosuppressants or caffeine have been proposed【246299874455786†L194-L213】. | Q4: Echinacea may interact with immunosuppressant drugs by stimulating immune activity and could affect the pharmacokinetics of drugs metabolised by cytochrome P450 enzymes; caution is advised when taken with hepatic substrates or caffeine. | R4: Individuals with autoimmune disorders or allergies to ragweed and other Asteraceae plants should avoid echinacea. Use during pregnancy or breastfeeding is not recommended. People taking immunosuppressant drugs should avoid echinacea due to potential antagonism. | S4: Medicinal products use the roots and aerial parts in teas, juices, tinctures and standardized extracts. | W4: medium | X4: schema-upgraded | Y4: 【880087072039746†L166-L200】; 【880087072039746†L215-L243】; 【840476591578855†L240-L305】; 【246299874455786†L194-L213】; 【55003496660111†L75-L130】 | Z4: present | AA4: PubMed/PMC | AB4: 【880087072039746†L166-L200】; 【880087072039746†L215-L243】; 【840476591578855†L240-L305】; 【246299874455786†L194-L213】; 【55003496660111†L75-L130】 | AC4: 【880087072039746†L166-L200】; 【880087072039746†L215-L243】; 【840476591578855†L240-L305】; 【246299874455786†L194-L213】; 【55003496660111†L75-L130】 | AD4: 【880087072039746†L166-L200】; 【880087072039746†L215-L243】; 【840476591578855†L240-L305】; 【246299874455786†L194-L213】; 【55003496660111†L75-L130】 | AE4: 【880087072039746†L166-L200】; 【880087072039746†L215-L243】; 【840476591578855†L240-L305】; 【246299874455786†L194-L213】; 【55003496660111†L75-L130】 | AF4: Mechanism preserved as qualified language where evidence is preclinical. | AG4: 2 | AH4: 1 | AI4: 3 | AJ4: 6 | AK4: Medium | AL4: Missing | AM4: Linked primary/secondary | AN4: 0.71428571 | AO4: Near ready | AP4: Editorial | AR4: Editorial polish | AS4: Not started | AT4: Yes | AU4: No | AV4: Yes | AW4: Finalize remaining content gaps | AX4: 1 | BA4: =IF($AR4="Published","Published",IF($AS4="Passed","Approved",IF($AR4="Ready for QA","QA review",IF($AR4="Source review","Source review",IF($AR4="Editorial polish","Editorial review","Review pending"))))) | BB4: =IF(OR($AR4="Published",$AS4="Passed",AND($AY4<>"",$BD4<>"")),"Approved",IF(OR($AY4<>"",$BC4<>"",$BF4<>""),"In review","Pending")) | BE4: =IF(OR($AY4<>"",$AZ4<>"",$BC4<>"",$BF4<>""),TODAY(),"") | BG4: =$B4&"-R"&$AX4 | BH4: =COUNTIF('Change History'!$C:$C,$B4)
A5: Garlic | B5: garlic | C5: Allium sativum | D5: herb | E5: bulb | F5: unspecified | G5: garlic; Allium sativum | H5: Native to parts of Central Asia including Iran, Kazakhstan, Kyrgyzstan, Tajikistan, Turkmenistan and Uzbekistan, but now cultivated worldwide【387438139344369†L214-L229】. | I5: Garlic (Allium sativum) is a bulb monograph focused on the unspecified used in herbal preparations. It is associated with Native to parts of Central Asia including Iran, Kazakhstan, Kyrgyzstan, Tajikistan, Turkmenistan and Uzbekistan, but now cultivated worldwide【387438139344369†L214-L229】. Garlic bulbs contain organosulfur compounds such as diallyl sulfide, diallyl disulfide, diallyl trisulfide, ajoene and S‑allyl‑cysteine. Oral garlic preparations are generally safe when used for up to seven years; side effects include breath and body odour, abdominal pain, flatulence and nausea. | J5: Garlic is represented here as a monograph-style entry centered on the unspecified. Key reported compounds include diallyl sulfide; diallyl disulfide; diallyl trisulfide; ajoene; S‑allyl‑cysteine. Typical preparation forms: Fresh or dried bulbs are used as food and in remedies. Commercial supplements include aged garlic extracts, oils and powders standardized for organosulfur content. Garlic bulbs contain organosulfur compounds such as diallyl sulfide, diallyl disulfide, diallyl trisulfide, ajoene and S‑allyl‑cysteine. These constituents exert antioxidant, anti‑inflammatory and immunomodulatory effects in vitro and in animal models by scavenging free radicals and modulating inflammatory pathways. Human evidence is limited, so this should be regarded as a proposed mechanism based on preclinical data. Interaction profile: Garlic may potentiate the effects of anticoagulant and antiplatelet drugs (e.g., warfarin, aspirin) and should be discontinued before surgery. It may also enhance the effects of antihypertensive or antidiabetic medicines. Use caution or avoid in: People with bleeding disorders, those taking anticoagulant or antiplatelet drugs and individuals scheduled for surgery should avoid high‑dose garlic supplements. Because safety during pregnancy and breastfeeding has not been established, garlic supplements are not recommended in these populations. | K5: diallyl sulfide; diallyl disulfide; diallyl trisulfide; ajoene; S‑allyl‑cysteine | M5: Garlic bulbs contain organosulfur compounds such as diallyl sulfide, diallyl disulfide, diallyl trisulfide, ajoene and S‑allyl‑cysteine. These constituents exert antioxidant, anti‑inflammatory and immunomodulatory effects in vitro and in animal models by scavenging free radicals and modulating inflammatory pathways. Human evidence is limited, so this should be regarded as a proposed mechanism based on preclinical data. | N5: anti-inflammatory; antioxidant; immunomodulatory | P5: Oral garlic preparations are generally safe when used for up to seven years; side effects include breath and body odour, abdominal pain, flatulence and nausea. Because garlic can inhibit platelet aggregation it may increase the risk of bleeding, especially when combined with anticoagulants or antiplatelet drugs. Raw garlic applied to the skin can cause severe irritation or burns. The safety of garlic supplements during pregnancy or breastfeeding is uncertain【945608786527328†L190-L207】. | Q5: Garlic may potentiate the effects of anticoagulant and antiplatelet drugs (e.g., warfarin, aspirin) and should be discontinued before surgery. It may also enhance the effects of antihypertensive or antidiabetic medicines. | R5: People with bleeding disorders, those taking anticoagulant or antiplatelet drugs and individuals scheduled for surgery should avoid high‑dose garlic supplements. Because safety during pregnancy and breastfeeding has not been established, garlic supplements are not recommended in these populations. | S5: Fresh or dried bulbs are used as food and in remedies. Commercial supplements include aged garlic extracts, oils and powders standardized for organosulfur content. | W5: medium | X5: schema-upgraded | Y5: 【170738571486764†L1208-L1216】; 【945608786527328†L190-L207】; 【387438139344369†L214-L229】 | Z5: present | AA5: PubMed/PMC | AB5: 【170738571486764†L1208-L1216】; 【945608786527328†L190-L207】; 【387438139344369†L214-L229】 | AC5: 【170738571486764†L1208-L1216】; 【945608786527328†L190-L207】; 【387438139344369†L214-L229】 | AD5: 【170738571486764†L1208-L1216】; 【945608786527328†L190-L207】; 【387438139344369†L214-L229】 | AE5: 【170738571486764†L1208-L1216】; 【945608786527328†L190-L207】; 【387438139344369†L214-L229】 | AF5: Mechanism preserved as qualified language where evidence is preclinical. | AG5: 2 | AH5: 1 | AI5: 3 | AJ5: 6 | AK5: Medium | AL5: Missing | AM5: Linked primary/secondary | AN5: 0.71428571 | AO5: Near ready | AP5: Editorial | AR5: Editorial polish | AS5: Not started | AT5: Yes | AU5: No | AV5: Yes | AW5: Finalize remaining content gaps | AX5: 1 | BA5: =IF($AR5="Published","Published",IF($AS5="Passed","Approved",IF($AR5="Ready for QA","QA review",IF($AR5="Source review","Source review",IF($AR5="Editorial polish","Editorial review","Review pending"))))) | BB5: =IF(OR($AR5="Published",$AS5="Passed",AND($AY5<>"",$BD5<>"")),"Approved",IF(OR($AY5<>"",$BC5<>"",$BF5<>""),"In review","Pending")) | BE5: =IF(OR($AY5<>"",$AZ5<>"",$BC5<>"",$BF5<>""),TODAY(),"") | BG5: =$B5&"-R"&$AX5 | BH5: =COUNTIF('Change History'!$C:$C,$B5)
A6: Ginger | B6: ginger | C6: Zingiber officinale | D6: herb | E6: rhizome | F6: unspecified | G6: ginger; Zingiber officinale | H6: Ginger does not occur in the wild; it is believed to have originated in Southeast Asia and is now cultivated across the humid tropics with India as the largest producer【418916103730052†L148-L163】. | I6: Ginger (Zingiber officinale) is a rhizome monograph focused on the unspecified used in herbal preparations. It is associated with Ginger does not occur in the wild; it is believed to have originated in Southeast Asia and is now cultivated across the humid tropics with India as the largest producer【418916103730052†L148-L163】. Ginger rhizomes contain phenolic constituents such as gingerols, shogaols, zingerone and paradols. Ginger is widely consumed as a food and supplement and is generally regarded as safe. | J6: Ginger is represented here as a monograph-style entry centered on the unspecified. Key reported compounds include [6]-gingerol; shogaols; zingerone; paradols. Typical preparation forms: The rhizome is used fresh, dried, pickled, preserved, candied or powdered. Supplements include encapsulated dried powders and extracts【418916103730052†L176-L189】. Ginger rhizomes contain phenolic constituents such as gingerols, shogaols, zingerone and paradols. These compounds modulate immune‑cell function and regulate signalling pathways including nuclear factor‑κB, MAPK and PI3K/Akt/mTOR, and they can activate AMP‑activated protein kinase (AMPK), NRF2, HO‑1 and PPARγ【69571933386645†L153-L169】【69571933386645†L240-L249】. Through these mechanisms ginger exhibits anti‑inflammatory, antioxidant and neuroprotective effects. Interaction profile: Ginger may increase the risk of bleeding when taken with anticoagulant or antiplatelet drugs and could lower blood glucose or blood pressure, potentiating antidiabetic or antihypertensive medications. Use caution or avoid in: Use cautiously in pregnancy, gallstone disease or bleeding disorders. Discontinue before surgery and avoid high‑dose supplements when taking anticoagulants. | K6: [6]-gingerol; shogaols; zingerone; paradols | M6: Ginger rhizomes contain phenolic constituents such as gingerols, shogaols, zingerone and paradols. These compounds modulate immune‑cell function and regulate signalling pathways including nuclear factor‑κB, MAPK and PI3K/Akt/mTOR, and they can activate AMP‑activated protein kinase (AMPK), NRF2, HO‑1 and PPARγ【69571933386645†L153-L169】【69571933386645†L240-L249】. Through these mechanisms ginger exhibits anti‑inflammatory, antioxidant and neuroprotective effects. | N6: anti-inflammatory; antioxidant; immunomodulatory | P6: Ginger is widely consumed as a food and supplement and is generally regarded as safe. Research suggests it may help with mild nausea and menstrual cramps. Reported side effects at high doses include abdominal discomfort, heartburn, diarrhoea and irritation of the mouth or throat【799387966105800†L29-L56】. Clinical studies using up to 1 000 mg/day of dried powdered extract report adverse event rates similar to placebo【739669106228210†L96-L133】. The safety of high‑dose ginger during pregnancy has not been conclusively established. | Q6: Ginger may increase the risk of bleeding when taken with anticoagulant or antiplatelet drugs and could lower blood glucose or blood pressure, potentiating antidiabetic or antihypertensive medications. | R6: Use cautiously in pregnancy, gallstone disease or bleeding disorders. Discontinue before surgery and avoid high‑dose supplements when taking anticoagulants. | S6: The rhizome is used fresh, dried, pickled, preserved, candied or powdered. Supplements include encapsulated dried powders and extracts【418916103730052†L176-L189】. | T6: Typical adult dose is up to 1 000 mg/day of dried powdered extract for gastrointestinal complaints【739669106228210†L96-L133】. | W6: high | X6: schema-upgraded | Y6: 【69571933386645†L153-L169】; 【69571933386645†L240-L249】; 【799387966105800†L29-L56】; 【739669106228210†L96-L133】; 【418916103730052†L148-L163】; 【418916103730052†L176-L189】 | Z6: present | AA6: PubMed/PMC | AB6: 【69571933386645†L153-L169】; 【69571933386645†L240-L249】; 【799387966105800†L29-L56】; 【739669106228210†L96-L133】; 【418916103730052†L148-L163】; 【418916103730052†L176-L189】 | AC6: 【69571933386645†L153-L169】; 【69571933386645†L240-L249】; 【799387966105800†L29-L56】; 【739669106228210†L96-L133】; 【418916103730052†L148-L163】; 【418916103730052†L176-L189】 | AD6: 【69571933386645†L153-L169】; 【69571933386645†L240-L249】; 【799387966105800†L29-L56】; 【739669106228210†L96-L133】; 【418916103730052†L148-L163】; 【418916103730052†L176-L189】 | AE6: 【69571933386645†L153-L169】; 【69571933386645†L240-L249】; 【799387966105800†L29-L56】; 【739669106228210†L96-L133】; 【418916103730052†L148-L163】; 【418916103730052†L176-L189】 | AF6: Mechanism preserved as qualified language where evidence is preclinical. | AG6: 3 | AH6: 1 | AI6: 3 | AJ6: 7 | AK6: Medium | AL6: Present | AM6: Linked primary/secondary | AN6: 0.78571429 | AO6: Near ready | AP6: Editorial | AR6: Editorial polish | AS6: Not started | AT6: Yes | AU6: No | AV6: Yes | AW6: Finalize remaining content gaps | AX6: 1 | BA6: =IF($AR6="Published","Published",IF($AS6="Passed","Approved",IF($AR6="Ready for QA","QA review",IF($AR6="Source review","Source review",IF($AR6="Editorial polish","Editorial review","Review pending"))))) | BB6: =IF(OR($AR6="Published",$AS6="Passed",AND($AY6<>"",$BD6<>"")),"Approved",IF(OR($AY6<>"",$BC6<>"",$BF6<>""),"In review","Pending")) | BE6: =IF(OR($AY6<>"",$AZ6<>"",$BC6<>"",$BF6<>""),TODAY(),"") | BG6: =$B6&"-R"&$AX6 | BH6: =COUNTIF('Change History'!$C:$C,$B6)
A7: Ginkgo Biloba | B7: ginkgo-biloba | C7: Ginkgo biloba | D7: herb | E7: tree | F7: leaf | G7: ginkgo; maidenhair tree | H7: Native to China; cultivated worldwide as an ornamental and medicinal tree. | I7: Ginkgo Biloba (Ginkgo biloba) is a tree monograph focused on the leaf used in herbal preparations. It is associated with Native to China; cultivated worldwide as an ornamental and medicinal tree. The standardized leaf extract (EGb 761) contains terpene lactones and flavone glycosides that modulate multiple neurotransmitter systems and platelet-activating factor pathways. Appears safe at recommended doses, but fresh seeds are toxic. | J7: Ginkgo Biloba is represented here as a monograph-style entry centered on the leaf. Key reported compounds include ginkgolides A, B, C, J; bilobalide; ginkgetin; bilobetin; sciadopitysin. Typical preparation forms: Standardized leaf extract (EGb 761). The standardized leaf extract (EGb 761) contains terpene lactones and flavone glycosides that modulate multiple neurotransmitter systems and platelet-activating factor pathways. Interaction profile: May potentiate NSAIDs, anticoagulants, antiplatelets, and interact with antidepressants and antidiabetic drugs. Use caution or avoid in: Pregnancy, breastfeeding, bleeding disorders, epilepsy, planned surgery. | K7: ginkgolides A, B, C, J; bilobalide; ginkgetin; bilobetin; sciadopitysin | L7: ginkgolides; bilobalide | M7: The standardized leaf extract (EGb 761) contains terpene lactones and flavone glycosides that modulate multiple neurotransmitter systems and platelet-activating factor pathways. | N7: dopaminergic; serotonergic; cholinergic; antioxidant | O7: human + preclinical | P7: Appears safe at recommended doses, but fresh seeds are toxic. May increase bleeding risk and lower seizure threshold. | Q7: May potentiate NSAIDs, anticoagulants, antiplatelets, and interact with antidepressants and antidiabetic drugs. | R7: Pregnancy, breastfeeding, bleeding disorders, epilepsy, planned surgery. | S7: Standardized leaf extract (EGb 761). | T7: 120–240 mg/day standardized extract | U7: Typically 24% flavonoid glycosides and 6% terpene lactones. | W7: high | X7: schema-upgraded | Y7: Recovered from prior batch output in this conversation | Z7: needs-source-normalization | AA7: conversation-recovered | AB7: Recovered from prior batch output in this conversation | AC7: Recovered from prior batch output in this conversation | AD7: Recovered from prior batch output in this conversation | AE7: Recovered from prior batch output in this conversation | AF7: Keep seed toxicity distinct from leaf-extract use. | AG7: 3 | AH7: 3 | AI7: 1 | AJ7: 7 | AK7: High | AL7: Present | AM7: Conversation-recovered | AN7: 1 | AO7: Near ready | AP7: Research | AR7: Source review | AS7: Not started | AT7: No | AU7: No | AV7: Yes | AW7: Normalize source record | AX7: 1 | BA7: =IF($AR7="Published","Published",IF($AS7="Passed","Approved",IF($AR7="Ready for QA","QA review",IF($AR7="Source review","Source review",IF($AR7="Editorial polish","Editorial review","Review pending"))))) | BB7: =IF(OR($AR7="Published",$AS7="Passed",AND($AY7<>"",$BD7<>"")),"Approved",IF(OR($AY7<>"",$BC7<>"",$BF7<>""),"In review","Pending")) | BE7: =IF(OR($AY7<>"",$AZ7<>"",$BC7<>"",$BF7<>""),TODAY(),"") | BG7: =$B7&"-R"&$AX7 | BH7: =COUNTIF('Change History'!$C:$C,$B7)
A8: Holy Basil | B8: holy-basil | C8: Ocimum tenuiflorum | D8: herb | E8: herb | F8: leaf; aerial parts | H8: India, Southeast Asia | I8: Holy Basil (Ocimum tenuiflorum) is a herb monograph focused on the leaf; aerial parts used in herbal preparations. It is associated with India, Southeast Asia. Adaptogenic; anti-inflammatory; modulates cortisol and stress pathways. Generally safe; possible mild GI upset. | J8: Holy Basil is represented here as a monograph-style entry centered on the leaf; aerial parts. Key reported compounds include eugenol; ursolic acid; rosmarinic acid. Typical preparation forms: Leaf extracts, teas. Adaptogenic; anti-inflammatory; modulates cortisol and stress pathways. Interaction profile: Anticoagulants, antidiabetic drugs. Use caution or avoid in: Pregnancy (limited data). | K8: eugenol; ursolic acid; rosmarinic acid | L8: eugenol; ursolic acid | M8: Adaptogenic; anti-inflammatory; modulates cortisol and stress pathways | N8: adaptogen; anti-inflammatory; antioxidant | O8: preclinical + limited human | P8: Generally safe; possible mild GI upset | Q8: Anticoagulants, antidiabetic drugs | R8: Pregnancy (limited data) | S8: Leaf extracts, teas | U8: Eugenol or ursolic acid content | W8: medium | X8: schema-upgraded | Y8: NCCIH; PubMed | Z8: present | AA8: NCCIH; PubMed/PMC | AB8: NCCIH; PubMed | AC8: NCCIH; PubMed | AD8: NCCIH; PubMed | AE8: NCCIH; PubMed | AF8: Carried forward from batch CSV; needs source-linked monograph expansion. | AG8: 2 | AH8: 3 | AI8: 3 | AJ8: 8 | AK8: Medium | AL8: Missing | AM8: Linked primary/secondary | AN8: 0.92857143 | AO8: Ready | AP8: Editorial | AR8: Ready for QA | AS8: Not started | AT8: Yes | AU8: Yes | AV8: Yes | AX8: 1 | BA8: =IF($AR8="Published","Published",IF($AS8="Passed","Approved",IF($AR8="Ready for QA","QA review",IF($AR8="Source review","Source review",IF($AR8="Editorial polish","Editorial review","Review pending"))))) | BB8: =IF(OR($AR8="Published",$AS8="Passed",AND($AY8<>"",$BD8<>"")),"Approved",IF(OR($AY8<>"",$BC8<>"",$BF8<>""),"In review","Pending")) | BE8: =IF(OR($AY8<>"",$AZ8<>"",$BC8<>"",$BF8<>""),TODAY(),"") | BG8: =$B8&"-R"&$AX8 | BH8: =COUNTIF('Change History'!$C:$C,$B8)
A9: Kava | B9: kava | C9: Piper methysticum | D9: herb | E9: shrub | F9: root; rhizome | G9: kava; kava-kava; awa; yaqona | H9: Indigenous to the South Pacific islands (Polynesia, Melanesia and Micronesia). | I9: Kava (Piper methysticum) is a shrub monograph focused on the root; rhizome used in herbal preparations. It is associated with Indigenous to the South Pacific islands (Polynesia, Melanesia and Micronesia). Kavalactones modulate GABA-A receptors and ion channels, producing anxiolytic and sedative effects without classical benzodiazepine-site binding. Rare but serious liver injury has been reported, especially with nontraditional extracts or concurrent alcohol/hepatotoxic drug use. | J9: Kava is represented here as a monograph-style entry centered on the root; rhizome. Key reported compounds include kavain; dihydrokavain; methysticin; dihydromethysticin; yangonin; desmethoxyyangonin; flavokavain A/B/C. Typical preparation forms: Traditional aqueous root beverage; modern standardized root extracts. Kavalactones modulate GABA-A receptors and ion channels, producing anxiolytic and sedative effects without classical benzodiazepine-site binding. Interaction profile: Additive sedation with CNS depressants and alcohol; possible hepatic enzyme interactions. Use caution or avoid in: Liver disease, pregnancy, breastfeeding, concurrent CNS depressants or hepatotoxic drugs. | K9: kavain; dihydrokavain; methysticin; dihydromethysticin; yangonin; desmethoxyyangonin; flavokavain A/B/C | L9: total kavalactones | M9: Kavalactones modulate GABA-A receptors and ion channels, producing anxiolytic and sedative effects without classical benzodiazepine-site binding. | N9: gabaergic | O9: human + preclinical | P9: Rare but serious liver injury has been reported, especially with nontraditional extracts or concurrent alcohol/hepatotoxic drug use. | Q9: Additive sedation with CNS depressants and alcohol; possible hepatic enzyme interactions. | R9: Liver disease, pregnancy, breastfeeding, concurrent CNS depressants or hepatotoxic drugs. | S9: Traditional aqueous root beverage; modern standardized root extracts. | T9: ~250 mg/day total kavalactones upper practical limit | U9: Standardized to kavalactone content. | V9: Avoid stems/leaves; extraction method matters. | W9: medium | X9: schema-upgraded | Y9: Recovered from prior batch output in this conversation | Z9: needs-source-normalization | AA9: conversation-recovered | AB9: Recovered from prior batch output in this conversation | AC9: Recovered from prior batch output in this conversation | AD9: Recovered from prior batch output in this conversation | AE9: Recovered from prior batch output in this conversation | AF9: Separate traditional aqueous prep from solvent extracts. | AG9: 2 | AH9: 3 | AI9: 1 | AJ9: 6 | AK9: High | AL9: Present | AM9: Conversation-recovered | AN9: 1 | AO9: Near ready | AP9: Research | AR9: Source review | AS9: Not started | AT9: No | AU9: No | AV9: Yes | AW9: Normalize source record | AX9: 1 | BA9: =IF($AR9="Published","Published",IF($AS9="Passed","Approved",IF($AR9="Ready for QA","QA review",IF($AR9="Source review","Source review",IF($AR9="Editorial polish","Editorial review","Review pending"))))) | BB9: =IF(OR($AR9="Published",$AS9="Passed",AND($AY9<>"",$BD9<>"")),"Approved",IF(OR($AY9<>"",$BC9<>"",$BF9<>""),"In review","Pending")) | BE9: =IF(OR($AY9<>"",$AZ9<>"",$BC9<>"",$BF9<>""),TODAY(),"") | BG9: =$B9&"-R"&$AX9 | BH9: =COUNTIF('Change History'!$C:$C,$B9)
A10: Lemon Balm | B10: lemon-balm | C10: Melissa officinalis | D10: herb | E10: herb | F10: leaf; aerial parts | H10: Europe, Mediterranean | I10: Lemon Balm (Melissa officinalis) is a herb monograph focused on the leaf; aerial parts used in herbal preparations. It is associated with Europe, Mediterranean. GABAergic (GABA transaminase inhibition); mild cholinergic activity. Generally safe; mild sedation possible. | J10: Lemon Balm is represented here as a monograph-style entry centered on the leaf; aerial parts. Key reported compounds include rosmarinic acid; citral; citronellal; linalool; flavonoids. Typical preparation forms: Leaf extracts, teas, tinctures. GABAergic (GABA transaminase inhibition); mild cholinergic activity. Interaction profile: Sedatives, thyroid medications. Use caution or avoid in: Hypothyroidism (caution). | K10: rosmarinic acid; citral; citronellal; linalool; flavonoids | L10: rosmarinic acid | M10: GABAergic (GABA transaminase inhibition); mild cholinergic activity | N10: gabaergic; cholinergic; antioxidant | O10: preclinical + limited human | P10: Generally safe; mild sedation possible | Q10: Sedatives, thyroid medications | R10: Hypothyroidism (caution) | S10: Leaf extracts, teas, tinctures | U10: Rosmarinic acid content | W10: medium | X10: schema-upgraded | Y10: EMA herbal monograph; NCCIH | Z10: present | AA10: NCCIH; EMA | AB10: EMA herbal monograph; NCCIH | AC10: EMA herbal monograph; NCCIH | AD10: EMA herbal monograph; NCCIH | AE10: EMA herbal monograph; NCCIH | AF10: Carried forward from batch CSV; needs source-linked monograph expansion. | AG10: 2 | AH10: 3 | AI10: 3 | AJ10: 8 | AK10: Medium | AL10: Missing | AM10: Linked primary/secondary | AN10: 0.92857143 | AO10: Ready | AP10: Editorial | AR10: Ready for QA | AS10: Not started | AT10: Yes | AU10: Yes | AV10: Yes | AX10: 1 | BA10: =IF($AR10="Published","Published",IF($AS10="Passed","Approved",IF($AR10="Ready for QA","QA review",IF($AR10="Source review","Source review",IF($AR10="Editorial polish","Editorial review","Review pending"))))) | BB10: =IF(OR($AR10="Published",$AS10="Passed",AND($AY10<>"",$BD10<>"")),"Approved",IF(OR($AY10<>"",$BC10<>"",$BF10<>""),"In review","Pending")) | BE10: =IF(OR($AY10<>"",$AZ10<>"",$BC10<>"",$BF10<>""),TODAY(),"") | BG10: =$B10&"-R"&$AX10 | BH10: =COUNTIF('Change History'!$C:$C,$B10)
A11: Maca | B11: maca | C11: Lepidium meyenii | D11: herb | E11: root | F11: root; hypocotyl | H11: Peru (Andes) | I11: Maca (Lepidium meyenii) is a root monograph focused on the root; hypocotyl used in herbal preparations. It is associated with Peru (Andes). May influence endocrine signaling and energy metabolism (unclear mechanism). Generally safe; mild GI upset possible. | J11: Maca is represented here as a monograph-style entry centered on the root; hypocotyl. Key reported compounds include macamides; macaenes; glucosinolates. Typical preparation forms: Dried root powder, extracts. May influence endocrine signaling and energy metabolism (unclear mechanism). Interaction profile: Limited data. Use caution or avoid in: Hormone-sensitive conditions (caution). | K11: macamides; macaenes; glucosinolates | L11: macamides | M11: May influence endocrine signaling and energy metabolism (unclear mechanism) | N11: adaptogen; hormonal | O11: preclinical + limited human | P11: Generally safe; mild GI upset possible | Q11: Limited data | R11: Hormone-sensitive conditions (caution) | S11: Dried root powder, extracts | W11: medium | X11: schema-upgraded | Y11: PubMed; NIH | Z11: present | AA11: NIH/ODS; PubMed/PMC | AB11: PubMed; NIH | AC11: PubMed; NIH | AD11: PubMed; NIH | AE11: PubMed; NIH | AF11: Carried forward from batch CSV; needs source-linked monograph expansion. | AG11: 2 | AH11: 3 | AI11: 3 | AJ11: 8 | AK11: Medium | AL11: Missing | AM11: Linked primary/secondary | AN11: 0.85714286 | AO11: Ready | AP11: Editorial | AR11: Ready for QA | AS11: Not started | AT11: Yes | AU11: Yes | AV11: Yes | AX11: 1 | BA11: =IF($AR11="Published","Published",IF($AS11="Passed","Approved",IF($AR11="Ready for QA","QA review",IF($AR11="Source review","Source review",IF($AR11="Editorial polish","Editorial review","Review pending"))))) | BB11: =IF(OR($AR11="Published",$AS11="Passed",AND($AY11<>"",$BD11<>"")),"Approved",IF(OR($AY11<>"",$BC11<>"",$BF11<>""),"In review","Pending")) | BE11: =IF(OR($AY11<>"",$AZ11<>"",$BC11<>"",$BF11<>""),TODAY(),"") | BG11: =$B11&"-R"&$AX11 | BH11: =COUNTIF('Change History'!$C:$C,$B11)
A12: Milk Thistle | B12: milk-thistle | C12: Silybum marianum | D12: herb | E12: herb | F12: seed; fruit | G12: milk thistle; St. Mary's thistle; blessed milkthistle | H12: Native to the Mediterranean region; now naturalized worldwide. | I12: Milk Thistle (Silybum marianum) is a herb monograph focused on the seed; fruit used in herbal preparations. It is associated with Native to the Mediterranean region; now naturalized worldwide. Silymarin flavonolignans exhibit antioxidant, anti-inflammatory and antifibrotic activity relevant to hepatoprotection. Generally well tolerated; mild GI side effects and occasional allergic reactions. | J12: Milk Thistle is represented here as a monograph-style entry centered on the seed; fruit. Key reported compounds include silybin A/B; isosilybin A/B; silychristin; silydianin; isosilychristin. Typical preparation forms: Seed/fruit extracts standardized to silymarin. Silymarin flavonolignans exhibit antioxidant, anti-inflammatory and antifibrotic activity relevant to hepatoprotection. Interaction profile: Possible CYP2C9/CYP3A4 interaction risk; may affect warfarin and some other drugs. Use caution or avoid in: Asteraceae allergy; caution in pregnancy/breastfeeding. | K12: silybin A/B; isosilybin A/B; silychristin; silydianin; isosilychristin | L12: silymarin; silybin | M12: Silymarin flavonolignans exhibit antioxidant, anti-inflammatory and antifibrotic activity relevant to hepatoprotection. | N12: antioxidant; anti-inflammatory; hepatoprotective | O12: human + preclinical | P12: Generally well tolerated; mild GI side effects and occasional allergic reactions. | Q12: Possible CYP2C9/CYP3A4 interaction risk; may affect warfarin and some other drugs. | R12: Asteraceae allergy; caution in pregnancy/breastfeeding. | S12: Seed/fruit extracts standardized to silymarin. | T12: 250–750 mg silymarin 2–3 times daily | U12: Typically 70–80% silymarin. | W12: high | X12: schema-upgraded | Y12: Recovered from prior batch output in this conversation | Z12: needs-source-normalization | AA12: conversation-recovered | AB12: Recovered from prior batch output in this conversation | AC12: Recovered from prior batch output in this conversation | AD12: Recovered from prior batch output in this conversation | AE12: Recovered from prior batch output in this conversation | AF12: Keep hepatoprotective claims narrower than “treats liver disease.” | AG12: 3 | AH12: 3 | AI12: 1 | AJ12: 7 | AK12: High | AL12: Present | AM12: Conversation-recovered | AN12: 1 | AO12: Near ready | AP12: Research | AR12: Source review | AS12: Not started | AT12: No | AU12: No | AV12: Yes | AW12: Normalize source record | AX12: 1 | BA12: =IF($AR12="Published","Published",IF($AS12="Passed","Approved",IF($AR12="Ready for QA","QA review",IF($AR12="Source review","Source review",IF($AR12="Editorial polish","Editorial review","Review pending"))))) | BB12: =IF(OR($AR12="Published",$AS12="Passed",AND($AY12<>"",$BD12<>"")),"Approved",IF(OR($AY12<>"",$BC12<>"",$BF12<>""),"In review","Pending")) | BE12: =IF(OR($AY12<>"",$AZ12<>"",$BC12<>"",$BF12<>""),TODAY(),"") | BG12: =$B12&"-R"&$AX12 | BH12: =COUNTIF('Change History'!$C:$C,$B12)
A13: Peppermint | B13: peppermint | C13: Mentha × piperita | D13: herb | E13: herb | F13: unspecified | G13: peppermint; Mentha × piperita | H13: Peppermint is a hybrid between water mint and spearmint that grows throughout Europe, North America and the Mediterranean【376436993997216†L159-L162】. | I13: Peppermint (Mentha × piperita) is a herb monograph focused on the unspecified used in herbal preparations. It is associated with Peppermint is a hybrid between water mint and spearmint that grows throughout Europe, North America and the Mediterranean【376436993997216†L159-L162】. Peppermint oil contains more than 80 constituents; menthol is the main bioactive component. Menthol is generally regarded as safe. | J13: Peppermint is represented here as a monograph-style entry centered on the unspecified. Key reported compounds include l‑menthol; l‑menthone; isomenthone; menthyl acetate; 1,8‑cineole (eucalyptol); menthofuran; limonene. Typical preparation forms: Leaves and flowering tops are used fresh or dried to make teas and flavourings. Medicinal products include enteric‑coated capsules of peppermint oil and topical preparations. Peppermint oil contains more than 80 constituents; menthol is the main bioactive component. Menthol acts as a smooth‑muscle relaxant by blocking L‑type calcium channels and activating transient receptor potential channels (TRPM8 and TRPA1). These actions underlie the spasmolytic and analgesic properties of peppermint oil. Peppermint oil also has antimicrobial, antiviral and anti‑inflammatory effects【271856535371736†L224-L289】【271856535371736†L312-L333】. Interaction profile: Peppermint oil may inhibit cytochrome P450 enzymes (e.g., CYP2A6 and UGT2B7) and could theoretically interact with drugs metabolised by these pathways. Use caution or avoid in: Avoid in infants and young children, and in people with gastro‑oesophageal reflux disease or bile duct obstruction. Use cautiously in those taking hepatotoxic drugs due to potential pulegone/menthofuran toxicity. | K13: l‑menthol; l‑menthone; isomenthone; menthyl acetate; 1,8‑cineole (eucalyptol); menthofuran; limonene | M13: Peppermint oil contains more than 80 constituents; menthol is the main bioactive component. Menthol acts as a smooth‑muscle relaxant by blocking L‑type calcium channels and activating transient receptor potential channels (TRPM8 and TRPA1). These actions underlie the spasmolytic and analgesic properties of peppermint oil. Peppermint oil also has antimicrobial, antiviral and anti‑inflammatory effects【271856535371736†L224-L289】【271856535371736†L312-L333】. | N13: anti-inflammatory; spasmolytic; antimicrobial | P13: Menthol is generally regarded as safe. Enteric‑coated peppermint oil is well tolerated; the most common adverse effects reported in clinical trials are heartburn, nausea, abdominal pain and dry mouth【220193048567304†L45-L53】. High doses of minor constituents such as pulegone or menthofuran can cause hepatotoxicity in animals, but typical medicinal doses contain negligible amounts and no cases of human hepatotoxicity have been reported【271856535371736†L1296-L1354】. Peppermint oil should not be applied near the faces of infants or young children because menthol inhalation can cause serious adverse reactions【220193048567304†L45-L53】. | Q13: Peppermint oil may inhibit cytochrome P450 enzymes (e.g., CYP2A6 and UGT2B7) and could theoretically interact with drugs metabolised by these pathways. | R13: Avoid in infants and young children, and in people with gastro‑oesophageal reflux disease or bile duct obstruction. Use cautiously in those taking hepatotoxic drugs due to potential pulegone/menthofuran toxicity. | S13: Leaves and flowering tops are used fresh or dried to make teas and flavourings. Medicinal products include enteric‑coated capsules of peppermint oil and topical preparations. | W13: medium | X13: schema-upgraded | Y13: 【697136726945063†L340-L345】; 【271856535371736†L224-L289】; 【271856535371736†L312-L333】; 【220193048567304†L45-L53】; 【271856535371736†L1296-L1354】; 【376436993997216†L159-L162】 | Z13: present | AA13: PubMed/PMC | AB13: 【697136726945063†L340-L345】; 【271856535371736†L224-L289】; 【271856535371736†L312-L333】; 【220193048567304†L45-L53】; 【271856535371736†L1296-L1354】; 【376436993997216†L159-L162】 | AC13: 【697136726945063†L340-L345】; 【271856535371736†L224-L289】; 【271856535371736†L312-L333】; 【220193048567304†L45-L53】; 【271856535371736†L1296-L1354】; 【376436993997216†L159-L162】 | AD13: 【697136726945063†L340-L345】; 【271856535371736†L224-L289】; 【271856535371736†L312-L333】; 【220193048567304†L45-L53】; 【271856535371736†L1296-L1354】; 【376436993997216†L159-L162】 | AE13: 【697136726945063†L340-L345】; 【271856535371736†L224-L289】; 【271856535371736†L312-L333】; 【220193048567304†L45-L53】; 【271856535371736†L1296-L1354】; 【376436993997216†L159-L162】 | AF13: Mechanism preserved as qualified language where evidence is preclinical. | AG13: 2 | AH13: 1 | AI13: 3 | AJ13: 6 | AK13: Medium | AL13: Missing | AM13: Linked primary/secondary | AN13: 0.71428571 | AO13: Near ready | AP13: Editorial | AR13: Editorial polish | AS13: Not started | AT13: Yes | AU13: No | AV13: Yes | AW13: Finalize remaining content gaps | AX13: 1 | BA13: =IF($AR13="Published","Published",IF($AS13="Passed","Approved",IF($AR13="Ready for QA","QA review",IF($AR13="Source review","Source review",IF($AR13="Editorial polish","Editorial review","Review pending"))))) | BB13: =IF(OR($AR13="Published",$AS13="Passed",AND($AY13<>"",$BD13<>"")),"Approved",IF(OR($AY13<>"",$BC13<>"",$BF13<>""),"In review","Pending")) | BE13: =IF(OR($AY13<>"",$AZ13<>"",$BC13<>"",$BF13<>""),TODAY(),"") | BG13: =$B13&"-R"&$AX13 | BH13: =COUNTIF('Change History'!$C:$C,$B13)
A14: Rhodiola Rosea | B14: rhodiola-rosea | C14: Rhodiola rosea | D14: herb | E14: adaptogenic root | F14: root | H14: Europe, Asia (cold regions) | I14: Rhodiola Rosea (Rhodiola rosea) is a adaptogenic root monograph focused on the root used in herbal preparations. It is associated with Europe, Asia (cold regions). Adaptogen; modulates HPA axis; influences serotonin, dopamine, norepinephrine; antioxidant. Generally well tolerated; possible dizziness, dry mouth, insomnia. | J14: Rhodiola Rosea is represented here as a monograph-style entry centered on the root. Key reported compounds include rosavin; rosarin; rosin; salidroside; tyrosol. Typical preparation forms: Standardized root extracts. Adaptogen; modulates HPA axis; influences serotonin, dopamine, norepinephrine; antioxidant. Interaction profile: SSRIs, MAOIs, stimulants. Use caution or avoid in: Bipolar disorder; avoid high doses before sleep. | K14: rosavin; rosarin; rosin; salidroside; tyrosol | L14: rosavins; salidroside | M14: Adaptogen; modulates HPA axis; influences serotonin, dopamine, norepinephrine; antioxidant | N14: adaptogen; serotonergic; dopaminergic; antioxidant | O14: preclinical + limited human | P14: Generally well tolerated; possible dizziness, dry mouth, insomnia | Q14: SSRIs, MAOIs, stimulants | R14: Bipolar disorder; avoid high doses before sleep | S14: Standardized root extracts | U14: Typically 3% rosavins, 1% salidroside | W14: medium | X14: schema-upgraded | Y14: NCCIH; PubMed adaptogen reviews | Z14: present | AA14: NCCIH; PubMed/PMC | AB14: NCCIH; PubMed adaptogen reviews | AC14: NCCIH; PubMed adaptogen reviews | AD14: NCCIH; PubMed adaptogen reviews | AE14: NCCIH; PubMed adaptogen reviews | AF14: Carried forward from batch CSV; needs source-linked monograph expansion. | AG14: 2 | AH14: 3 | AI14: 3 | AJ14: 8 | AK14: Medium | AL14: Missing | AM14: Linked primary/secondary | AN14: 0.92857143 | AO14: Ready | AP14: Editorial | AR14: Ready for QA | AS14: Not started | AT14: Yes | AU14: Yes | AV14: Yes | AX14: 1 | BA14: =IF($AR14="Published","Published",IF($AS14="Passed","Approved",IF($AR14="Ready for QA","QA review",IF($AR14="Source review","Source review",IF($AR14="Editorial polish","Editorial review","Review pending"))))) | BB14: =IF(OR($AR14="Published",$AS14="Passed",AND($AY14<>"",$BD14<>"")),"Approved",IF(OR($AY14<>"",$BC14<>"",$BF14<>""),"In review","Pending")) | BE14: =IF(OR($AY14<>"",$AZ14<>"",$BC14<>"",$BF14<>""),TODAY(),"") | BG14: =$B14&"-R"&$AX14 | BH14: =COUNTIF('Change History'!$C:$C,$B14)
A15: Saw Palmetto | B15: saw-palmetto | C15: Serenoa repens | D15: herb | E15: berry extract | F15: berry | H15: Southeastern United States | I15: Saw Palmetto (Serenoa repens) is a berry extract monograph focused on the berry used in herbal preparations. It is associated with Southeastern United States. 5-alpha-reductase inhibition; anti-androgenic effects. Generally safe; mild GI upset, headache. | J15: Saw Palmetto is represented here as a monograph-style entry centered on the berry. Key reported compounds include fatty acids; phytosterols (beta-sitosterol). Typical preparation forms: Berry extracts. 5-alpha-reductase inhibition; anti-androgenic effects. Interaction profile: Hormonal therapies, anticoagulants. Use caution or avoid in: Pregnancy. | K15: fatty acids; phytosterols (beta-sitosterol) | L15: fatty acids; beta-sitosterol | M15: 5-alpha-reductase inhibition; anti-androgenic effects | N15: hormonal; anti-androgenic | O15: preclinical + limited human | P15: Generally safe; mild GI upset, headache | Q15: Hormonal therapies, anticoagulants | R15: Pregnancy | S15: Berry extracts | U15: Standardized to fatty acid content | W15: medium | X15: schema-upgraded | Y15: NIH ODS; EMA | Z15: present | AA15: NIH/ODS; EMA | AB15: NIH ODS; EMA | AC15: NIH ODS; EMA | AD15: NIH ODS; EMA | AE15: NIH ODS; EMA | AF15: Carried forward from batch CSV; needs source-linked monograph expansion. | AG15: 2 | AH15: 3 | AI15: 3 | AJ15: 8 | AK15: Medium | AL15: Missing | AM15: Linked primary/secondary | AN15: 0.92857143 | AO15: Ready | AP15: Editorial | AR15: Ready for QA | AS15: Not started | AT15: Yes | AU15: Yes | AV15: Yes | AX15: 1 | BA15: =IF($AR15="Published","Published",IF($AS15="Passed","Approved",IF($AR15="Ready for QA","QA review",IF($AR15="Source review","Source review",IF($AR15="Editorial polish","Editorial review","Review pending"))))) | BB15: =IF(OR($AR15="Published",$AS15="Passed",AND($AY15<>"",$BD15<>"")),"Approved",IF(OR($AY15<>"",$BC15<>"",$BF15<>""),"In review","Pending")) | BE15: =IF(OR($AY15<>"",$AZ15<>"",$BC15<>"",$BF15<>""),TODAY(),"") | BG15: =$B15&"-R"&$AX15 | BH15: =COUNTIF('Change History'!$C:$C,$B15)
A16: St Johns Wort | B16: st-johns-wort | C16: Hypericum perforatum | D16: herb | E16: herb | F16: flowering tops | G16: St. John's wort; Hypericum; goatweed | H16: Native to Europe and West Asia; naturalized in North America and other temperate regions. | I16: St. John's wort (Hypericum perforatum) is a herb monograph focused on the flowering tops used in herbal preparations. It is associated with Native to Europe and West Asia; naturalized in North America and other temperate regions. Hyperforin and related compounds inhibit monoamine reuptake and affect TRPC6-linked neuroplasticity; additional monoamine oxidase and stress-pathway effects have been proposed. Can cause photosensitivity, GI upset, dizziness, insomnia, restlessness. | J16: St. John's wort is represented here as a monograph-style entry centered on the flowering tops. Key reported compounds include hyperforin; hypericin; pseudohypericin; quercetin; rutin; kaempferol. Typical preparation forms: Dried flowering tops or standardized extracts. Hyperforin and related compounds inhibit monoamine reuptake and affect TRPC6-linked neuroplasticity; additional monoamine oxidase and stress-pathway effects have been proposed. Interaction profile: Major interactions with antidepressants, oral contraceptives, cyclosporine, tacrolimus, HIV meds, anticancer drugs, warfarin, digoxin and others. Use caution or avoid in: Pregnancy, breastfeeding, bipolar disorder, concomitant prescription meds with CYP/P-gp liability. | K16: hyperforin; hypericin; pseudohypericin; quercetin; rutin; kaempferol | L16: hyperforin; hypericin | M16: Hyperforin and related compounds inhibit monoamine reuptake and affect TRPC6-linked neuroplasticity; additional monoamine oxidase and stress-pathway effects have been proposed. | N16: serotonergic; dopaminergic | O16: human + preclinical | P16: Can cause photosensitivity, GI upset, dizziness, insomnia, restlessness. Strong inducer of CYP3A4 and P-gp. | Q16: Major interactions with antidepressants, oral contraceptives, cyclosporine, tacrolimus, HIV meds, anticancer drugs, warfarin, digoxin and others. | R16: Pregnancy, breastfeeding, bipolar disorder, concomitant prescription meds with CYP/P-gp liability. | S16: Dried flowering tops or standardized extracts. | T16: 300 mg extract three times daily | U16: Often 0.3% hypericin or 2–5% hyperforin. | W16: high | X16: schema-upgraded | Y16: Recovered from prior batch output in this conversation | Z16: needs-source-normalization | AA16: conversation-recovered | AB16: Recovered from prior batch output in this conversation | AC16: Recovered from prior batch output in this conversation | AD16: Recovered from prior batch output in this conversation | AE16: Recovered from prior batch output in this conversation | AF16: Flag as high-interaction herb. | AG16: 3 | AH16: 3 | AI16: 1 | AJ16: 7 | AK16: High | AL16: Present | AM16: Conversation-recovered | AN16: 1 | AO16: Near ready | AP16: Research | AR16: Source review | AS16: Not started | AT16: No | AU16: No | AV16: Yes | AW16: Normalize source record | AX16: 1 | BA16: =IF($AR16="Published","Published",IF($AS16="Passed","Approved",IF($AR16="Ready for QA","QA review",IF($AR16="Source review","Source review",IF($AR16="Editorial polish","Editorial review","Review pending"))))) | BB16: =IF(OR($AR16="Published",$AS16="Passed",AND($AY16<>"",$BD16<>"")),"Approved",IF(OR($AY16<>"",$BC16<>"",$BF16<>""),"In review","Pending")) | BE16: =IF(OR($AY16<>"",$AZ16<>"",$BC16<>"",$BF16<>""),TODAY(),"") | BG16: =$B16&"-R"&$AX16 | BH16: =COUNTIF('Change History'!$C:$C,$B16)
A17: Turmeric | B17: turmeric | C17: Curcuma longa | D17: herb | E17: rhizome | F17: unspecified | G17: turmeric; Curcuma longa | H17: Native to India and cultivated throughout the tropics; turmeric is not found in the wild and is grown as a domesticated plant【754431674042811†L224-L241】. | I17: Turmeric (Curcuma longa) is a rhizome monograph focused on the unspecified used in herbal preparations. It is associated with Native to India and cultivated throughout the tropics; turmeric is not found in the wild and is grown as a domesticated plant【754431674042811†L224-L241】. The golden rhizomes of turmeric contain non‑volatile curcuminoids—curcumin (curcumin I), demethoxycurcumin (curcumin II) and bisdemethoxycurcumin (curcumin III)—as well as volatile mono‑ and sesquiterpenoids【768158627760254†L420-L432】【768158627760254†L442-L468】. Conventional oral preparations of turmeric or curcumin appear safe for up to 2–3 months. | J17: Turmeric is represented here as a monograph-style entry centered on the unspecified. Key reported compounds include curcumin; demethoxycurcumin; bisdemethoxycurcumin. Typical preparation forms: The rhizomes are boiled, dried and ground into powder used as a spice, dye and supplement. Extracts standardized for curcuminoid content are available as capsules or tablets. The golden rhizomes of turmeric contain non‑volatile curcuminoids—curcumin (curcumin I), demethoxycurcumin (curcumin II) and bisdemethoxycurcumin (curcumin III)—as well as volatile mono‑ and sesquiterpenoids【768158627760254†L420-L432】【768158627760254†L442-L468】. Curcumin and related curcuminoids exhibit antioxidant and anti‑inflammatory effects by modulating multiple molecular targets (e.g., NF‑κB, Nrf2, COX‑2). Most data are preclinical; human evidence is limited, so this mechanism should be considered proposed. Interaction profile: Curcumin may enhance the effects of anticoagulant, antiplatelet or antidiabetic drugs and could interact with drugs metabolized by cytochrome P450 enzymes; caution is advised. Use caution or avoid in: Avoid high‑dose turmeric supplements in people with gallbladder obstruction, bleeding disorders or those taking anticoagulant or antiplatelet medications. Use is not recommended during pregnancy or breastfeeding. | K17: curcumin; demethoxycurcumin; bisdemethoxycurcumin | M17: The golden rhizomes of turmeric contain non‑volatile curcuminoids—curcumin (curcumin I), demethoxycurcumin (curcumin II) and bisdemethoxycurcumin (curcumin III)—as well as volatile mono‑ and sesquiterpenoids【768158627760254†L420-L432】【768158627760254†L442-L468】. Curcumin and related curcuminoids exhibit antioxidant and anti‑inflammatory effects by modulating multiple molecular targets (e.g., NF‑κB, Nrf2, COX‑2). Most data are preclinical; human evidence is limited, so this mechanism should be considered proposed. | N17: anti-inflammatory; antioxidant | P17: Conventional oral preparations of turmeric or curcumin appear safe for up to 2–3 months. Reported adverse effects include nausea, vomiting, acid reflux, stomach upset, diarrhoea or constipation. Highly bioavailable curcumin products have been linked to liver damage in rare cases. The safety of turmeric supplements during pregnancy or breastfeeding is uncertain【628537290338832†L207-L223】. | Q17: Curcumin may enhance the effects of anticoagulant, antiplatelet or antidiabetic drugs and could interact with drugs metabolized by cytochrome P450 enzymes; caution is advised. | R17: Avoid high‑dose turmeric supplements in people with gallbladder obstruction, bleeding disorders or those taking anticoagulant or antiplatelet medications. Use is not recommended during pregnancy or breastfeeding. | S17: The rhizomes are boiled, dried and ground into powder used as a spice, dye and supplement. Extracts standardized for curcuminoid content are available as capsules or tablets. | W17: medium | X17: schema-upgraded | Y17: 【768158627760254†L420-L432】; 【768158627760254†L442-L468】; 【628537290338832†L207-L223】; 【754431674042811†L224-L241】 | Z17: present | AA17: PubMed/PMC | AB17: 【768158627760254†L420-L432】; 【768158627760254†L442-L468】; 【628537290338832†L207-L223】; 【754431674042811†L224-L241】 | AC17: 【768158627760254†L420-L432】; 【768158627760254†L442-L468】; 【628537290338832†L207-L223】; 【754431674042811†L224-L241】 | AD17: 【768158627760254†L420-L432】; 【768158627760254†L442-L468】; 【628537290338832†L207-L223】; 【754431674042811†L224-L241】 | AE17: 【768158627760254†L420-L432】; 【768158627760254†L442-L468】; 【628537290338832†L207-L223】; 【754431674042811†L224-L241】 | AF17: Mechanism preserved as qualified language where evidence is preclinical. | AG17: 2 | AH17: 1 | AI17: 3 | AJ17: 6 | AK17: Medium | AL17: Missing | AM17: Linked primary/secondary | AN17: 0.71428571 | AO17: Near ready | AP17: Editorial | AR17: Editorial polish | AS17: Not started | AT17: Yes | AU17: No | AV17: Yes | AW17: Finalize remaining content gaps | AX17: 1 | BA17: =IF($AR17="Published","Published",IF($AS17="Passed","Approved",IF($AR17="Ready for QA","QA review",IF($AR17="Source review","Source review",IF($AR17="Editorial polish","Editorial review","Review pending"))))) | BB17: =IF(OR($AR17="Published",$AS17="Passed",AND($AY17<>"",$BD17<>"")),"Approved",IF(OR($AY17<>"",$BC17<>"",$BF17<>""),"In review","Pending")) | BE17: =IF(OR($AY17<>"",$AZ17<>"",$BC17<>"",$BF17<>""),TODAY(),"") | BG17: =$B17&"-R"&$AX17 | BH17: =COUNTIF('Change History'!$C:$C,$B17)
A18: Valerian | B18: valerian | C18: Valeriana officinalis | D18: herb | E18: herb | F18: root; rhizome | G18: valerian; all-heal; garden heliotrope | H18: Native to Europe and Asia; naturalized in North America and other temperate regions. | I18: Valerian (Valeriana officinalis) is a herb monograph focused on the root; rhizome used in herbal preparations. It is associated with Native to Europe and Asia; naturalized in North America and other temperate regions. Valerenic acid derivatives modulate GABA-A signaling and may inhibit GABA breakdown. Short-term use appears safe; side effects include headache, GI upset, mental dullness, excitability, vivid dreams. | J18: Valerian is represented here as a monograph-style entry centered on the root; rhizome. Key reported compounds include valerenic acid; valerenol; valerenal; valepotriates (valtrate, isovaltrate); sesquiterpenoids. Typical preparation forms: Dried roots/rhizomes as teas, tinctures, or extracts. Valerenic acid derivatives modulate GABA-A signaling and may inhibit GABA breakdown. Interaction profile: May potentiate sedatives and alcohol. Use caution or avoid in: Pregnancy, breastfeeding, liver disease, concurrent CNS depressants. | K18: valerenic acid; valerenol; valerenal; valepotriates (valtrate, isovaltrate); sesquiterpenoids | L18: valerenic acid | M18: Valerenic acid derivatives modulate GABA-A signaling and may inhibit GABA breakdown. | N18: gabaergic | O18: preclinical + limited human | P18: Short-term use appears safe; side effects include headache, GI upset, mental dullness, excitability, vivid dreams. Rare liver injury reported. | Q18: May potentiate sedatives and alcohol. | R18: Pregnancy, breastfeeding, liver disease, concurrent CNS depressants. | S18: Dried roots/rhizomes as teas, tinctures, or extracts. | T18: 300–600 mg extract | W18: medium | X18: schema-upgraded | Y18: Recovered from prior batch output in this conversation | Z18: needs-source-normalization | AA18: conversation-recovered | AB18: Recovered from prior batch output in this conversation | AC18: Recovered from prior batch output in this conversation | AD18: Recovered from prior batch output in this conversation | AE18: Recovered from prior batch output in this conversation | AF18: Mechanism should stay qualified, not stated as established in humans. | AG18: 2 | AH18: 3 | AI18: 1 | AJ18: 6 | AK18: High | AL18: Present | AM18: Conversation-recovered | AN18: 0.92857143 | AO18: Near ready | AP18: Research | AR18: Source review | AS18: Not started | AT18: No | AU18: No | AV18: Yes | AW18: Normalize source record | AX18: 1 | BA18: =IF($AR18="Published","Published",IF($AS18="Passed","Approved",IF($AR18="Ready for QA","QA review",IF($AR18="Source review","Source review",IF($AR18="Editorial polish","Editorial review","Review pending"))))) | BB18: =IF(OR($AR18="Published",$AS18="Passed",AND($AY18<>"",$BD18<>"")),"Approved",IF(OR($AY18<>"",$BC18<>"",$BF18<>""),"In review","Pending")) | BE18: =IF(OR($AY18<>"",$AZ18<>"",$BC18<>"",$BF18<>""),TODAY(),"") | BG18: =$B18&"-R"&$AX18 | BH18: =COUNTIF('Change History'!$C:$C,$B18)
A19: American Skullcap | B19: american-skullcap | C19: Scutellaria lateriflora | D19: herb | E19: herb | F19: aerial parts | G19: American skullcap; mad-dog skullcap; Scutellaria lateriflora | H19: Native to North America; especially eastern and central United States and Canada. | I19: American skullcap is an aerial-parts monograph used primarily for calm, tension, and sleep-adjacent positioning. It is stack-relevant for gentle GABAergic support, but product identity matters because American and Chinese skullcap are not interchangeable. | J19: American skullcap is used in teas, tinctures, capsules, and extracts. Reported flavones include baicalin, baicalein, and scutellarin. Position as calming and nervous-system support rather than as a generic 'sedative' shortcut, and keep species identity explicit in frontend labels. | K19: baicalin; baicalein; scutellarin | L19: baicalin; baicalein | M19: Proposed mechanism centers on flavone-driven GABAergic and neuroinhibitory support with additional anti-inflammatory and antioxidant effects. | N19: gabaergic; calming; antioxidant; anti-inflammatory | O19: limited human + preclinical | P19: Usually tolerated, but drowsiness, dizziness, or additive sedation are possible in sensitive users or higher-dose combinations. | Q19: Use caution with sedatives, alcohol, anticonvulsants, and polyherbal sleep formulas. | R19: Pregnancy and breastfeeding: insufficient safety data. Use caution in heavy-sedation contexts and in users combining multiple CNS depressants. | S19: Teas, tinctures, capsules, and aerial-parts extracts. | T19: Product-specific extract dosing; traditional tea/tincture use common | U19: Species identity should distinguish American skullcap from Chinese skullcap; extract standardization is inconsistent. | V19: Mislabeling between skullcap species materially changes chemistry and positioning. | W19: medium | X19: schema-upgraded | Y19: https://plants.sc.egov.usda.gov/home/search?query=Scutellaria%20lateriflora | https://pubchem.ncbi.nlm.nih.gov/compound/Baicalin | https://pubchem.ncbi.nlm.nih.gov/compound/Baicalein | https://pubchem.ncbi.nlm.nih.gov/#query=scutellarin | Z19: present | AA19: USDA Plants + PubChem | AB19: https://plants.sc.egov.usda.gov/home/search?query=Scutellaria%20lateriflora | https://pubchem.ncbi.nlm.nih.gov/compound/Baicalin | AC19: https://pubchem.ncbi.nlm.nih.gov/compound/Baicalein | https://pubchem.ncbi.nlm.nih.gov/#query=scutellarin | AD19: https://plants.sc.egov.usda.gov/home/search?query=Scutellaria%20lateriflora | AE19: https://plants.sc.egov.usda.gov/home/search?query=Scutellaria%20lateriflora | AF19: Keep species-separated from Chinese skullcap in stacks and frontend copy. | AG19: 2 | AH19: 2 | AI19: 3 | AJ19: 7 | AK19: Medium | AL19: Present | AM19: Linked primary/secondary | AN19: 0.81 | AO19: Ready | AP19: Research | AR19: Ready for QA | AS19: Not started | AT19: Yes | AU19: Yes | AV19: Yes | AX19: 1 | BA19: QA review | BB19: Pending | BG19: american-skullcap-R1 | BH19: 0
A20: Motherwort | B20: motherwort | C20: Leonurus cardiaca | D20: herb | E20: herb | F20: aerial parts | G20: motherwort; Leonurus cardiaca; lion's tail | H20: Native to Eurasia; naturalized widely in North America. | I20: Motherwort is an aerial-parts monograph with historical use around calm, palpitations, and menstrual-support positioning. It is useful for the system because it combines calming relevance with cardiovascular and uterine caution logic. | J20: Motherwort is used in teas, tinctures, and capsules. Reported constituents include leonurine and stachydrine along with flavonoid fractions. Position cautiously: calming and cycle-support language can coexist with stronger contraindication gating for pregnancy and cardiovascular-medication overlap. | K20: leonurine; stachydrine; flavonoids | L20: leonurine; stachydrine | M20: Proposed mechanism includes mild GABAergic and autonomic-calming effects with additional cardiometabolic and smooth-muscle-adjacent actions attributed to leonurine and related alkaloids. | N20: calming; cardiovascular-adjacent; smooth-muscle-adjacent | O20: traditional use + preclinical | P20: May cause GI upset, sedation, or dizziness in some users; avoid framing as universally gentle because uterine and cardiovascular considerations matter. | Q20: Use caution with anticoagulants, antihypertensives, sedatives, and other agents affecting uterine tone or bleeding. | R20: Avoid in pregnancy. Use caution with heavy menstrual bleeding, anticoagulant use, low blood pressure, or arrhythmia management. | S20: Teas, tinctures, and aerial-parts extracts. | T20: Product-specific tincture/extract dosing | U20: Standardization is inconsistent and many products are positioned more by tradition than compound assay. | V20: Species identity and extract standardization vary; safety framing should outweigh casual wellness positioning. | W20: medium | X20: schema-upgraded | Y20: https://plants.sc.egov.usda.gov/home/search?query=Leonurus%20cardiaca | https://pubchem.ncbi.nlm.nih.gov/compound/Leonurine | https://pubchem.ncbi.nlm.nih.gov/compound/Stachydrine | Z20: present | AA20: USDA Plants + PubChem | AB20: https://plants.sc.egov.usda.gov/home/search?query=Leonurus%20cardiaca | https://pubchem.ncbi.nlm.nih.gov/compound/Leonurine | AC20: https://pubchem.ncbi.nlm.nih.gov/compound/Stachydrine | AD20: https://plants.sc.egov.usda.gov/home/search?query=Leonurus%20cardiaca | AE20: https://plants.sc.egov.usda.gov/home/search?query=Leonurus%20cardiaca | AF20: Gate hard for pregnancy and bleeding-risk contexts. | AG20: 2 | AH20: 2 | AI20: 3 | AJ20: 7 | AK20: Medium | AL20: Present | AM20: Linked primary/secondary | AN20: 0.79 | AO20: Ready | AP20: Research | AR20: Ready for QA | AS20: Not started | AT20: Yes | AU20: Yes | AV20: Yes | AX20: 1 | BA20: QA review | BB20: Pending | BG20: motherwort-R1 | BH20: 0
A21: Saffron | B21: saffron | C21: Crocus sativus | D21: herb | E21: stigma | F21: stigma | G21: saffron; Crocus sativus | H21: Cultivated in Southwest Asia, the Mediterranean, and other dry temperate regions. | I21: Saffron is a stigma monograph with mood-support and sensory-positioning relevance. It is high-value for the system because it has frontend appeal, a relatively distinct chemistry, and practical differentiation from generic calming herbs. | J21: Saffron is used as culinary stigma threads, powders, and standardized extracts. Key compounds include crocin, safranal, and picrocrocin. Position around mood/stress support with restrained claims and careful cost/quality framing because adulteration risk is meaningful. | K21: crocin; safranal; picrocrocin | L21: crocin; safranal | M21: Proposed mechanism includes serotonergic and glutamatergic modulation together with antioxidant and neuroprotective effects associated with crocins and volatile constituents such as safranal. | N21: mood-support; serotonergic-adjacent; antioxidant; neuroprotective | O21: mixed human + preclinical | P21: Usually tolerated in supplement-range doses, but dizziness, GI upset, headache, or overstimulation are possible in some users. | Q21: Use caution with serotonergic drugs, anticoagulants, antihypertensives, and mood-active stacks. | R21: Pregnancy: avoid high-dose medicinal use. Use caution in bipolar-spectrum activation risk or in serotonergic polypharmacy. | S21: Whole stigma, powders, capsules, and standardized extracts. | T21: Product-specific extract dosing | U21: High-value ingredient with meaningful adulteration and color-standardization issues; extract identity should be explicit. | V21: Adulteration/substitution risk is significant; distinguish culinary stigma from extract products. | W21: medium-high | X21: schema-upgraded | Y21: https://plants.sc.egov.usda.gov/home/search?query=Crocus%20sativus | https://pubchem.ncbi.nlm.nih.gov/#query=crocin | https://pubchem.ncbi.nlm.nih.gov/#query=safranal | https://pubchem.ncbi.nlm.nih.gov/#query=picrocrocin | Z21: present | AA21: USDA Plants + PubChem | AB21: https://plants.sc.egov.usda.gov/home/search?query=Crocus%20sativus | https://pubchem.ncbi.nlm.nih.gov/#query=crocin | AC21: https://pubchem.ncbi.nlm.nih.gov/#query=safranal | https://pubchem.ncbi.nlm.nih.gov/#query=picrocrocin | AD21: https://plants.sc.egov.usda.gov/home/search?query=Crocus%20sativus | AE21: https://plants.sc.egov.usda.gov/home/search?query=Crocus%20sativus | AF21: Keep premium-ingredient positioning but reinforce serotonergic and pregnancy caution. | AG21: 3 | AH21: 2 | AI21: 3 | AJ21: 8 | AK21: High | AL21: Present | AM21: Linked primary/secondary | AN21: 0.84 | AO21: Ready | AP21: Research | AR21: Ready for QA | AS21: Not started | AT21: Yes | AU21: Yes | AV21: Yes | AX21: 1 | BA21: QA review | BB21: Pending | BG21: saffron-R1 | BH21: 0
A22: Licorice | B22: licorice | C22: Glycyrrhiza glabra | D22: herb | E22: root | F22: root | G22: licorice; liquorice; sweet root | H22: Native to southwestern Asia and parts of Europe; cultivated broadly. | I22: Licorice is a root monograph used for soothing GI/respiratory positioning and for endocrine-adjacent effects driven largely by glycyrrhizin. It is a high-leverage addition because whole-root licorice and DGL are not interchangeable from a safety standpoint. | J22: Licorice root is used as tea, decoction, powder, extract, and deglycyrrhizinated licorice (DGL) products. Major constituents include glycyrrhizin, liquiritigenin, isoliquiritigenin, and glabridin. Frontend logic should split whole-root licorice from DGL whenever blood-pressure or potassium risk matters. | K22: glycyrrhizin; liquiritigenin; isoliquiritigenin; glabridin | L22: glycyrrhizin; liquiritigenin | M22: Mechanism includes 11beta-HSD2 inhibition with downstream mineralocorticoid-like effects plus anti-inflammatory and mucosal-support activity from flavonoid constituents. | N22: endocrine-modulating; anti-inflammatory; demulcent | O22: limited human + preclinical | P22: Chronic or high-glycyrrhizin intake can raise blood pressure, lower potassium, and increase edema or arrhythmia risk in susceptible users. | Q22: Use caution with diuretics, corticosteroids, digoxin, antihypertensives, warfarin, and other drugs affected by potassium or blood-pressure shifts. | R22: Avoid in pregnancy, uncontrolled hypertension, kidney disease, hypokalemia, heart failure, or edema-prone users unless clinically supervised. | S22: Teas, decoctions, powders, extracts, and DGL chewables/capsules. | T22: Product-specific dosing; DGL and whole-root licorice must be separated | U22: Glycyrrhizin content varies widely; DGL removes most glycyrrhizin and changes risk profile materially. | V22: DGL vs whole-root confusion materially changes safety and frontend recommendation logic. | W22: medium-high | X22: schema-upgraded | Y22: https://www.nccih.nih.gov/health/licorice-root | https://pubchem.ncbi.nlm.nih.gov/compound/Glycyrrhizin | https://pubchem.ncbi.nlm.nih.gov/compound/Liquiritigenin | https://pubchem.ncbi.nlm.nih.gov/compound/Isoliquiritigenin | https://pubchem.ncbi.nlm.nih.gov/compound/Glabridin | Z22: present | AA22: NCCIH + PubChem | AB22: https://www.nccih.nih.gov/health/licorice-root | https://pubchem.ncbi.nlm.nih.gov/compound/Glycyrrhizin | AC22: https://pubchem.ncbi.nlm.nih.gov/compound/Liquiritigenin | https://pubchem.ncbi.nlm.nih.gov/compound/Isoliquiritigenin | https://pubchem.ncbi.nlm.nih.gov/compound/Glabridin | AD22: https://www.nccih.nih.gov/health/licorice-root | AE22: https://www.nccih.nih.gov/health/licorice-root | AF22: Frontend must distinguish DGL from glycyrrhizin-containing licorice. | AG22: 3 | AH22: 2 | AI22: 3 | AJ22: 8 | AK22: High | AL22: Present | AM22: Linked primary/secondary | AN22: 0.86 | AO22: Ready | AP22: Research | AR22: Ready for QA | AS22: Not started | AT22: Yes | AU22: Yes | AV22: Yes | AX22: 1 | BA22: QA review | BB22: Pending | BG22: licorice-R1 | BH22: 0
A23: lemon-balm | B23: Melissa officinalis | C23: GABA transaminase inhibition, calming | D23: rosmarinic acid | E23: mild sedation
A24: holy-basil | B24: Ocimum sanctum | C24: adaptogenic, cortisol modulation | D24: eugenol | E24: generally safe
A25: valerian | B25: Valeriana officinalis | C25: GABAergic sedation | D25: valerenic acids | E25: sedation; avoid alcohol
A26: cordyceps | B26: Cordyceps militaris | C26: ATP production support, adaptogenic | D26: cordycepin | E26: generally safe
A27: turmeric | B27: Curcuma longa | C27: anti-inflammatory, NF-kB modulation | D27: curcuminoids | E27: low bioavailability; may interact with anticoagulants
A28: ginger | B28: Zingiber officinale | C28: anti-inflammatory, GI motility support | D28: gingerols, shogaols | E28: generally safe
A29: green-tea | B29: Camellia sinensis | C29: antioxidant, mild stimulant | D29: EGCG, caffeine | E29: caffeine sensitivity
A30: kava | B30: Piper methysticum | C30: GABAergic, anxiolytic | D30: kavalactones | E30: liver toxicity risk with misuse
A31: reishi | B31: Ganoderma lucidum | C31: immunomodulatory, adaptogenic | D31: beta-glucans, triterpenes | E31: generally safe; may affect blood pressure
A32: lions-mane | B32: Hericium erinaceus | C32: neurotrophic, NGF stimulation | D32: hericenones, erinacines | E32: generally safe
A33: peppermint | B33: Mentha piperita | C33: smooth muscle relaxation, GI relief | D33: menthol | E33: may worsen reflux in some
A34: black-seed | B34: Nigella sativa | C34: anti-inflammatory, antioxidant | D34: thymoquinone | E34: generally safe
... A46: clove | B46: Syzygium aromaticum | C46: analgesic, antimicrobial | D46: eugenol | E46: high doses may irritate

Sheet Summary View
A1: slug | B1: scientificName | C1: mechanismTags | D1: evidenceLevel | E1: confidence | F1: citationStatus | G1: reviewPriority | H1: totalScore | I1: completenessPct | J1: readinessFlag
A2: ashwagandha | B2: Withania somnifera | C2: adaptogen; anti-inflammatory; antioxidant; gabaergic | D2: human + preclinical | E2: medium | F2: needs-source-normalization | G2: High | H2: 6 | I2: 1 | J2: Near ready
A3: black-cohosh | B3: Actaea racemosa | C3: serotonergic; anti-inflammatory; hormonal | D3: preclinical + limited human | E3: medium | F3: present | G3: Medium | H3: 8 | I3: 0.85714286 | J3: Ready
A4: echinacea-purpurea | B4: Echinacea purpurea | C4: immunomodulatory | E4: medium | F4: present | G4: Medium | H4: 6 | I4: 0.71428571 | J4: Near ready
A5: garlic | B5: Allium sativum | C5: anti-inflammatory; antioxidant; immunomodulatory | E5: medium | F5: present | G5: Medium | H5: 6 | I5: 0.71428571 | J5: Near ready
A6: ginger | B6: Zingiber officinale | C6: anti-inflammatory; antioxidant; immunomodulatory | E6: high | F6: present | G6: Medium | H6: 7 | I6: 0.78571429 | J6: Near ready
A7: ginkgo-biloba | B7: Ginkgo biloba | C7: dopaminergic; serotonergic; cholinergic; antioxidant | D7: human + preclinical | E7: high | F7: needs-source-normalization | G7: High | H7: 7 | I7: 1 | J7: Near ready
A8: holy-basil | B8: Ocimum tenuiflorum | C8: adaptogen; anti-inflammatory; antioxidant | D8: preclinical + limited human | E8: medium | F8: present | G8: Medium | H8: 8 | I8: 0.92857143 | J8: Ready
A9: kava | B9: Piper methysticum | C9: gabaergic | D9: human + preclinical | E9: medium | F9: needs-source-normalization | G9: High | H9: 6 | I9: 1 | J9: Near ready
A10: lemon-balm | B10: Melissa officinalis | C10: gabaergic; cholinergic; antioxidant | D10: preclinical + limited human | E10: medium | F10: present | G10: Medium | H10: 8 | I10: 0.92857143 | J10: Ready
A11: maca | B11: Lepidium meyenii | C11: adaptogen; hormonal | D11: preclinical + limited human | E11: medium | F11: present | G11: Medium | H11: 8 | I11: 0.85714286 | J11: Ready
A12: milk-thistle | B12: Silybum marianum | C12: antioxidant; anti-inflammatory; hepatoprotective | D12: human + preclinical | E12: high | F12: needs-source-normalization | G12: High | H12: 7 | I12: 1 | J12: Near ready
A13: peppermint | B13: Mentha × piperita | C13: anti-inflammatory; spasmolytic; antimicrobial | E13: medium | F13: present | G13: Medium | H13: 6 | I13: 0.71428571 | J13: Near ready
A14: rhodiola-rosea | B14: Rhodiola rosea | C14: adaptogen; serotonergic; dopaminergic; antioxidant | D14: preclinical + limited human | E14: medium | F14: present | G14: Medium | H14: 8 | I14: 0.92857143 | J14: Ready
A15: saw-palmetto | B15: Serenoa repens | C15: hormonal; anti-androgenic | D15: preclinical + limited human | E15: medium | F15: present | G15: Medium | H15: 8 | I15: 0.92857143 | J15: Ready
A16: st-johns-wort | B16: Hypericum perforatum | C16: serotonergic; dopaminergic | D16: human + preclinical | E16: high | F16: needs-source-normalization | G16: High | H16: 7 | I16: 1 | J16: Near ready
A17: turmeric | B17: Curcuma longa | C17: anti-inflammatory; antioxidant | E17: medium | F17: present | G17: Medium | H17: 6 | I17: 0.71428571 | J17: Near ready
A18: valerian | B18: Valeriana officinalis | C18: gabaergic | D18: preclinical + limited human | E18: medium | F18: needs-source-normalization | G18: High | H18: 6 | I18: 0.92857143 | J18: Near ready

Sheet Rankings
A1: slug | B1: scientificName | C1: mechanismTags | D1: confidence | E1: citationStatus | F1: totalScore | G1: reviewPriority
A2: black-cohosh | B2: Actaea racemosa | C2: serotonergic; anti-inflammatory; hormonal | D2: medium | E2: present | F2: 8 | G2: Medium
A3: holy-basil | B3: Ocimum tenuiflorum | C3: adaptogen; anti-inflammatory; antioxidant | D3: medium | E3: present | F3: 8 | G3: Medium
A4: lemon-balm | B4: Melissa officinalis | C4: gabaergic; cholinergic; antioxidant | D4: medium | E4: present | F4: 8 | G4: Medium
A5: maca | B5: Lepidium meyenii | C5: adaptogen; hormonal | D5: medium | E5: present | F5: 8 | G5: Medium
A6: rhodiola-rosea | B6: Rhodiola rosea | C6: adaptogen; serotonergic; dopaminergic; antioxidant | D6: medium | E6: present | F6: 8 | G6: Medium
A7: saw-palmetto | B7: Serenoa repens | C7: hormonal; anti-androgenic | D7: medium | E7: present | F7: 8 | G7: Medium
A8: ginger | B8: Zingiber officinale | C8: anti-inflammatory; antioxidant; immunomodulatory | D8: high | E8: present | F8: 7 | G8: Medium
A9: ginkgo-biloba | B9: Ginkgo biloba | C9: dopaminergic; serotonergic; cholinergic; antioxidant | D9: high | E9: needs-source-normalization | F9: 7 | G9: High
A10: milk-thistle | B10: Silybum marianum | C10: antioxidant; anti-inflammatory; hepatoprotective | D10: high | E10: needs-source-normalization | F10: 7 | G10: High
A11: st-johns-wort | B11: Hypericum perforatum | C11: serotonergic; dopaminergic | D11: high | E11: needs-source-normalization | F11: 7 | G11: High
A12: ashwagandha | B12: Withania somnifera | C12: adaptogen; anti-inflammatory; antioxidant; gabaergic | D12: medium | E12: needs-source-normalization | F12: 6 | G12: High
A13: echinacea-purpurea | B13: Echinacea purpurea | C13: immunomodulatory | D13: medium | E13: present | F13: 6 | G13: Medium
... A18: valerian | B18: Valeriana officinalis | C18: gabaergic | D18: medium | E18: needs-source-normalization | F18: 6 | G18: High

Sheet Action Queue
A1: reviewPriority | B1: slug | C1: scientificName | D1: citationStatus | E1: dosageStatus | F1: sourceTier | G1: qualityConcerns | H1: notesForCodex | I1: totalScore | J1: completenessPct
A2: High | B2: valerian | C2: Valeriana officinalis | D2: needs-source-normalization | E2: Present | F2: Conversation-recovered | H2: Mechanism should stay qualified, not stated as established in humans. | I2: 6 | J2: 0.92857143
A3: High | B3: ginkgo-biloba | C3: Ginkgo biloba | D3: needs-source-normalization | E3: Present | F3: Conversation-recovered | H3: Keep seed toxicity distinct from leaf-extract use. | I3: 7 | J3: 1
A4: High | B4: milk-thistle | C4: Silybum marianum | D4: needs-source-normalization | E4: Present | F4: Conversation-recovered | H4: Keep hepatoprotective claims narrower than “treats liver disease.” | I4: 7 | J4: 1
A5: High | B5: st-johns-wort | C5: Hypericum perforatum | D5: needs-source-normalization | E5: Present | F5: Conversation-recovered | H5: Flag as high-interaction herb. | I5: 7 | J5: 1
A6: High | B6: ashwagandha | C6: Withania somnifera | D6: needs-source-normalization | E6: Present | F6: Conversation-recovered | H6: Separate root-based products from leaf-heavy extracts. | I6: 6 | J6: 1
A7: High | B7: kava | C7: Piper methysticum | D7: needs-source-normalization | E7: Present | F7: Conversation-recovered | G7: Avoid stems/leaves; extraction method matters. | H7: Separate traditional aqueous prep from solvent extracts. | I7: 6 | J7: 1
A8: Medium | B8: echinacea-purpurea | C8: Echinacea purpurea | D8: present | E8: Missing | F8: Linked primary/secondary | H8: Mechanism preserved as qualified language where evidence is preclinical. | I8: 6 | J8: 0.71428571
A9: Medium | B9: garlic | C9: Allium sativum | D9: present | E9: Missing | F9: Linked primary/secondary | H9: Mechanism preserved as qualified language where evidence is preclinical. | I9: 6 | J9: 0.71428571
A10: Medium | B10: peppermint | C10: Mentha × piperita | D10: present | E10: Missing | F10: Linked primary/secondary | H10: Mechanism preserved as qualified language where evidence is preclinical. | I10: 6 | J10: 0.71428571
A11: Medium | B11: turmeric | C11: Curcuma longa | D11: present | E11: Missing | F11: Linked primary/secondary | H11: Mechanism preserved as qualified language where evidence is preclinical. | I11: 6 | J11: 0.71428571
A12: Medium | B12: ginger | C12: Zingiber officinale | D12: present | E12: Present | F12: Linked primary/secondary | H12: Mechanism preserved as qualified language where evidence is preclinical. | I12: 7 | J12: 0.78571429
A13: Medium | B13: black-cohosh | C13: Actaea racemosa | D13: present | E13: Missing | F13: Linked primary/secondary | G13: Adulteration/misidentification risk in commercial products. | H13: Treat menopausal mechanism claims as mixed evidence, not established estrogenic action. | I13: 8 | J13: 0.85714286
A14: Medium | B14: maca | C14: Lepidium meyenii | D14: present | E14: Missing | F14: Linked primary/secondary | H14: Carried forward from batch CSV; needs source-linked monograph expansion. | I14: 8 | J14: 0.85714286
A15: Medium | B15: holy-basil | C15: Ocimum tenuiflorum | D15: present | E15: Missing | F15: Linked primary/secondary | H15: Carried forward from batch CSV; needs source-linked monograph expansion. | I15: 8 | J15: 0.92857143
A16: Medium | B16: lemon-balm | C16: Melissa officinalis | D16: present | E16: Missing | F16: Linked primary/secondary | H16: Carried forward from batch CSV; needs source-linked monograph expansion. | I16: 8 | J16: 0.92857143
A17: Medium | B17: rhodiola-rosea | C17: Rhodiola rosea | D17: present | E17: Missing | F17: Linked primary/secondary | H17: Carried forward from batch CSV; needs source-linked monograph expansion. | I17: 8 | J17: 0.92857143
A18: Medium | B18: saw-palmetto | C18: Serenoa repens | D18: present | E18: Missing | F18: Linked primary/secondary | H18: Carried forward from batch CSV; needs source-linked monograph expansion. | I18: 8 | J18: 0.92857143

Sheet Legend
A1: Field | B1: Meaning | C1: Suggested use | D1: Notes
A2: reviewPriority | B2: Operational urgency | C2: Use in editorial triage | D2: High = source normalization or major evidence gaps
A3: citationStatus | B3: Citation hygiene state | C3: Filter before publishing | D3: Normalize all needs-source-normalization rows first
A4: completenessPct | B4: Core monograph coverage | C4: Sort ascending to find weak entries | D4: Computed from major monograph body fields
A5: readinessFlag | B5: Publishability signal | C5: Use with confidence + citations | D5: Ready means high coverage plus linked citations
A6: totalScore | B6: Quality composite | C6: Rank product candidates | D6: Blend of confidence, evidence, and citation quality

Sheet Mechanism Matrix
A1: slug | B1: scientificName | C1: confidence | D1: evidenceLevel | E1: adaptogen | F1: anti-inflammatory | G1: antioxidant | H1: gabaergic | I1: serotonergic | J1: hormonal | K1: immunomodulatory | L1: dopaminergic | M1: cholinergic | N1: hepatoprotective | O1: spasmolytic | P1: antimicrobial | Q1: anti-androgenic
A2: ashwagandha | B2: Withania somnifera | C2: medium | D2: human + preclinical | E2: 1 | F2: 1 | G2: 1 | H2: 1 | I2: 0 | J2: 0 | K2: 0 | L2: 0 | M2: 0 | N2: 0 | O2: 0 | P2: 0 | Q2: 0
A3: black-cohosh | B3: Actaea racemosa | C3: medium | D3: preclinical + limited human | E3: 0 | F3: 1 | G3: 0 | H3: 0 | I3: 1 | J3: 1 | K3: 0 | L3: 0 | M3: 0 | N3: 0 | O3: 0 | P3: 0 | Q3: 0
A4: echinacea-purpurea | B4: Echinacea purpurea | C4: medium | E4: 0 | F4: 0 | G4: 0 | H4: 0 | I4: 0 | J4: 0 | K4: 1 | L4: 0 | M4: 0 | N4: 0 | O4: 0 | P4: 0 | Q4: 0
A5: garlic | B5: Allium sativum | C5: medium | E5: 0 | F5: 1 | G5: 1 | H5: 0 | I5: 0 | J5: 0 | K5: 1 | L5: 0 | M5: 0 | N5: 0 | O5: 0 | P5: 0 | Q5: 0
A6: ginger | B6: Zingiber officinale | C6: high | E6: 0 | F6: 1 | G6: 1 | H6: 0 | I6: 0 | J6: 0 | K6: 1 | L6: 0 | M6: 0 | N6: 0 | O6: 0 | P6: 0 | Q6: 0
A7: ginkgo-biloba | B7: Ginkgo biloba | C7: high | D7: human + preclinical | E7: 0 | F7: 0 | G7: 1 | H7: 0 | I7: 1 | J7: 0 | K7: 0 | L7: 1 | M7: 1 | N7: 0 | O7: 0 | P7: 0 | Q7: 0
A8: holy-basil | B8: Ocimum tenuiflorum | C8: medium | D8: preclinical + limited human | E8: 1 | F8: 1 | G8: 1 | H8: 0 | I8: 0 | J8: 0 | K8: 0 | L8: 0 | M8: 0 | N8: 0 | O8: 0 | P8: 0 | Q8: 0
A9: kava | B9: Piper methysticum | C9: medium | D9: human + preclinical | E9: 0 | F9: 0 | G9: 0 | H9: 1 | I9: 0 | J9: 0 | K9: 0 | L9: 0 | M9: 0 | N9: 0 | O9: 0 | P9: 0 | Q9: 0
A10: lemon-balm | B10: Melissa officinalis | C10: medium | D10: preclinical + limited human | E10: 0 | F10: 0 | G10: 1 | H10: 1 | I10: 0 | J10: 0 | K10: 0 | L10: 0 | M10: 1 | N10: 0 | O10: 0 | P10: 0 | Q10: 0
A11: maca | B11: Lepidium meyenii | C11: medium | D11: preclinical + limited human | E11: 1 | F11: 0 | G11: 0 | H11: 0 | I11: 0 | J11: 1 | K11: 0 | L11: 0 | M11: 0 | N11: 0 | O11: 0 | P11: 0 | Q11: 0
A12: milk-thistle | B12: Silybum marianum | C12: high | D12: human + preclinical | E12: 0 | F12: 1 | G12: 1 | H12: 0 | I12: 0 | J12: 0 | K12: 0 | L12: 0 | M12: 0 | N12: 1 | O12: 0 | P12: 0 | Q12: 0
A13: peppermint | B13: Mentha × piperita | C13: medium | E13: 0 | F13: 1 | G13: 0 | H13: 0 | I13: 0 | J13: 0 | K13: 0 | L13: 0 | M13: 0 | N13: 0 | O13: 1 | P13: 1 | Q13: 0
A14: rhodiola-rosea | B14: Rhodiola rosea | C14: medium | D14: preclinical + limited human | E14: 1 | F14: 0 | G14: 1 | H14: 0 | I14: 1 | J14: 0 | K14: 0 | L14: 1 | M14: 0 | N14: 0 | O14: 0 | P14: 0 | Q14: 0
A15: saw-palmetto | B15: Serenoa repens | C15: medium | D15: preclinical + limited human | E15: 0 | F15: 0 | G15: 0 | H15: 0 | I15: 0 | J15: 1 | K15: 0 | L15: 0 | M15: 0 | N15: 0 | O15: 0 | P15: 0 | Q15: 1
A16: st-johns-wort | B16: Hypericum perforatum | C16: high | D16: human + preclinical | E16: 0 | F16: 0 | G16: 0 | H16: 0 | I16: 1 | J16: 0 | K16: 0 | L16: 1 | M16: 0 | N16: 0 | O16: 0 | P16: 0 | Q16: 0
A17: turmeric | B17: Curcuma longa | C17: medium | E17: 0 | F17: 1 | G17: 1 | H17: 0 | I17: 0 | J17: 0 | K17: 0 | L17: 0 | M17: 0 | N17: 0 | O17: 0 | P17: 0 | Q17: 0
A18: valerian | B18: Valeriana officinalis | C18: medium | D18: preclinical + limited human | E18: 0 | F18: 0 | G18: 0 | H18: 1 | I18: 0 | J18: 0 | K18: 0 | L18: 0 | M18: 0 | N18: 0 | O18: 0 | P18: 0 | Q18: 0

Sheet Editorial Pipeline
A1: slug | B1: scientificName | C1: reviewPriority | D1: readinessFlag | E1: citationStatus | F1: confidence | G1: dosageStatus | H1: completenessPct | I1: summaryMissing | J1: descriptionMissing | K1: standardizationMissing | L1: sourceNormalizationNeeded | M1: recommendedNextAction | P1: reviewPriority | Q1: count
A2: ashwagandha | B2: Withania somnifera | E2: needs-source-normalization | F2: medium | I2: No | J2: No | K2: No | L2: Yes | M2: Normalize sources to NCCIH/EMA/PubMed | Q2: 17
A3: black-cohosh | B3: Actaea racemosa | E3: present | F3: medium | I3: No | J3: No | K3: Yes | L3: No | M3: Add extract marker or standardization details
A4: echinacea-purpurea | B4: Echinacea purpurea | E4: present | F4: medium | I4: No | J4: No | K4: Yes | L4: No | M4: Add extract marker or standardization details
A5: garlic | B5: Allium sativum | E5: present | F5: medium | I5: No | J5: No | K5: Yes | L5: No | M5: Add extract marker or standardization details
A6: ginger | B6: Zingiber officinale | E6: present | F6: high | I6: No | J6: No | K6: Yes | L6: No | M6: Add extract marker or standardization details
A7: ginkgo-biloba | B7: Ginkgo biloba | E7: needs-source-normalization | F7: high | I7: No | J7: No | K7: No | L7: Yes | M7: Normalize sources to NCCIH/EMA/PubMed
A8: holy-basil | B8: Ocimum tenuiflorum | E8: present | F8: medium | I8: No | J8: No | K8: No | L8: No | M8: Monitor / optional refinement
A9: kava | B9: Piper methysticum | E9: needs-source-normalization | F9: medium | I9: No | J9: No | K9: No | L9: Yes | M9: Normalize sources to NCCIH/EMA/PubMed
A10: lemon-balm | B10: Melissa officinalis | E10: present | F10: medium | I10: No | J10: No | K10: No | L10: No | M10: Monitor / optional refinement
A11: maca | B11: Lepidium meyenii | E11: present | F11: medium | I11: No | J11: No | K11: Yes | L11: No | M11: Add extract marker or standardization details
A12: milk-thistle | B12: Silybum marianum | E12: needs-source-normalization | F12: high | I12: No | J12: No | K12: No | L12: Yes | M12: Normalize sources to NCCIH/EMA/PubMed
A13: peppermint | B13: Mentha × piperita | E13: present | F13: medium | I13: No | J13: No | K13: Yes | L13: No | M13: Add extract marker or standardization details
A14: rhodiola-rosea | B14: Rhodiola rosea | E14: present | F14: medium | I14: No | J14: No | K14: No | L14: No | M14: Monitor / optional refinement
... A18: valerian | B18: Valeriana officinalis | E18: needs-source-normalization | F18: medium | I18: No | J18: No | K18: Yes | L18: Yes | M18: Normalize sources to NCCIH/EMA/PubMed

Sheet Citation Cleanup
A1: slug | B1: scientificName | C1: citationStatus | D1: sourceAuthority | E1: sources | F1: cleanupAction | G1: owner | H1: status
A2: ashwagandha | B2: Withania somnifera | C2: needs-source-normalization | D2: conversation-recovered | E2: Recovered from prior batch output in this conversation | F2: Replace conversation-recovered source string with direct NCCIH/EMA/PubMed citations | H2: Open
A3: ginkgo-biloba | B3: Ginkgo biloba | C3: needs-source-normalization | D3: conversation-recovered | E3: Recovered from prior batch output in this conversation | F3: Replace conversation-recovered source string with direct NCCIH/EMA/PubMed citations | H3: Open
A4: kava | B4: Piper methysticum | C4: needs-source-normalization | D4: conversation-recovered | E4: Recovered from prior batch output in this conversation | F4: Replace conversation-recovered source string with direct NCCIH/EMA/PubMed citations | H4: Open
A5: milk-thistle | B5: Silybum marianum | C5: needs-source-normalization | D5: conversation-recovered | E5: Recovered from prior batch output in this conversation | F5: Replace conversation-recovered source string with direct NCCIH/EMA/PubMed citations | H5: Open
A6: st-johns-wort | B6: Hypericum perforatum | C6: needs-source-normalization | D6: conversation-recovered | E6: Recovered from prior batch output in this conversation | F6: Replace conversation-recovered source string with direct NCCIH/EMA/PubMed citations | H6: Open
A7: valerian | B7: Valeriana officinalis | C7: needs-source-normalization | D7: conversation-recovered | E7: Recovered from prior batch output in this conversation | F7: Replace conversation-recovered source string with direct NCCIH/EMA/PubMed citations | H7: Open

Sheet Publishing Workflow
A1: slug | B1: scientificName | C1: reviewPriority | D1: totalScore | E1: citationStatus | F1: readinessFlag | G1: editorialOwner | H1: reviewDate | I1: publishStatus | J1: qaStatus | K1: sourceLockFlag | L1: frontendReadyFlag | M1: webCopyReadyFlag | N1: publishBlocker
A2: ashwagandha | B2: Withania somnifera | C2: High | D2: 6 | E2: needs-source-normalization | F2: Near ready | G2: Research | I2: Source review | J2: Not started | K2: No | L2: No | M2: Yes | N2: Normalize source record
A3: black-cohosh | B3: Actaea racemosa | C3: Medium | D3: 8 | E3: present | F3: Ready | G3: Editorial | I3: Ready for QA | J3: Not started | K3: Yes | L3: Yes | M3: Yes
A4: echinacea-purpurea | B4: Echinacea purpurea | C4: Medium | D4: 6 | E4: present | F4: Near ready | G4: Editorial | I4: Editorial polish | J4: Not started | K4: Yes | L4: No | M4: Yes | N4: Finalize remaining content gaps
A5: garlic | B5: Allium sativum | C5: Medium | D5: 6 | E5: present | F5: Near ready | G5: Editorial | I5: Editorial polish | J5: Not started | K5: Yes | L5: No | M5: Yes | N5: Finalize remaining content gaps
A6: ginger | B6: Zingiber officinale | C6: Medium | D6: 7 | E6: present | F6: Near ready | G6: Editorial | I6: Editorial polish | J6: Not started | K6: Yes | L6: No | M6: Yes | N6: Finalize remaining content gaps
A7: ginkgo-biloba | B7: Ginkgo biloba | C7: High | D7: 7 | E7: needs-source-normalization | F7: Near ready | G7: Research | I7: Source review | J7: Not started | K7: No | L7: No | M7: Yes | N7: Normalize source record
A8: holy-basil | B8: Ocimum tenuiflorum | C8: Medium | D8: 8 | E8: present | F8: Ready | G8: Editorial | I8: Ready for QA | J8: Not started | K8: Yes | L8: Yes | M8: Yes
A9: kava | B9: Piper methysticum | C9: High | D9: 6 | E9: needs-source-normalization | F9: Near ready | G9: Research | I9: Source review | J9: Not started | K9: No | L9: No | M9: Yes | N9: Normalize source record
A10: lemon-balm | B10: Melissa officinalis | C10: Medium | D10: 8 | E10: present | F10: Ready | G10: Editorial | I10: Ready for QA | J10: Not started | K10: Yes | L10: Yes | M10: Yes
A11: maca | B11: Lepidium meyenii | C11: Medium | D11: 8 | E11: present | F11: Ready | G11: Editorial | I11: Ready for QA | J11: Not started | K11: Yes | L11: Yes | M11: Yes
A12: milk-thistle | B12: Silybum marianum | C12: High | D12: 7 | E12: needs-source-normalization | F12: Near ready | G12: Research | I12: Source review | J12: Not started | K12: No | L12: No | M12: Yes | N12: Normalize source record
A13: peppermint | B13: Mentha × piperita | C13: Medium | D13: 6 | E13: present | F13: Near ready | G13: Editorial | I13: Editorial polish | J13: Not started | K13: Yes | L13: No | M13: Yes | N13: Finalize remaining content gaps
A14: rhodiola-rosea | B14: Rhodiola rosea | C14: Medium | D14: 8 | E14: present | F14: Ready | G14: Editorial | I14: Ready for QA | J14: Not started | K14: Yes | L14: Yes | M14: Yes
A15: saw-palmetto | B15: Serenoa repens | C15: Medium | D15: 8 | E15: present | F15: Ready | G15: Editorial | I15: Ready for QA | J15: Not started | K15: Yes | L15: Yes | M15: Yes
A16: st-johns-wort | B16: Hypericum perforatum | C16: High | D16: 7 | E16: needs-source-normalization | F16: Near ready | G16: Research | I16: Source review | J16: Not started | K16: No | L16: No | M16: Yes | N16: Normalize source record
A17: turmeric | B17: Curcuma longa | C17: Medium | D17: 6 | E17: present | F17: Near ready | G17: Editorial | I17: Editorial polish | J17: Not started | K17: Yes | L17: No | M17: Yes | N17: Finalize remaining content gaps
A18: valerian | B18: Valeriana officinalis | C18: High | D18: 6 | E18: needs-source-normalization | F18: Near ready | G18: Research | I18: Source review | J18: Not started | K18: No | L18: No | M18: Yes | N18: Normalize source record

Sheet Frontend Ready
A1: slug | B1: scientificName | C1: publishStatus | D1: qaStatus | E1: frontendReadyFlag | F1: webCopyReadyFlag | G1: publishBlocker
A2: black-cohosh | B2: Actaea racemosa | C2: Ready for QA | D2: Not started | E2: Yes | F2: Yes
A3: holy-basil | B3: Ocimum tenuiflorum | C3: Ready for QA | D3: Not started | E3: Yes | F3: Yes
A4: lemon-balm | B4: Melissa officinalis | C4: Ready for QA | D4: Not started | E4: Yes | F4: Yes
A5: maca | B5: Lepidium meyenii | C5: Ready for QA | D5: Not started | E5: Yes | F5: Yes
A6: rhodiola-rosea | B6: Rhodiola rosea | C6: Ready for QA | D6: Not started | E6: Yes | F6: Yes
A7: saw-palmetto | B7: Serenoa repens | C7: Ready for QA | D7: Not started | E7: Yes | F7: Yes

Sheet Production Dashboard
A1: Production KPI | E1: Workflow Counts
A2: Total monographs | B2: 17 | E2: Ready for QA | F2: 6
A3: Frontend ready | B3: 6 | E3: Source review | F3: 6
A4: QA not started | B4: 17 | E4: Editorial polish | F4: 5
A5: Avg completeness | B5: 0.88235294 | E5: Published | F5: 0

Sheet Publishing Guide
A1: Field | B1: Meaning | C1: Use
A2: editorialOwner | B2: Primary responsible lane | C2: Assign Editorial, Research, or QA
A3: reviewDate | B3: Next review checkpoint | C3: Use yyyy-mm-dd
A4: publishStatus | B4: Current production state | C4: Drive pipeline progression
A5: qaStatus | B5: Quality gate | C5: Passed required before publish
A6: sourceLockFlag | B6: Sources normalized and stable | C6: Set Yes only after citation cleanup
A7: frontendReadyFlag | B7: Safe to surface in app/web | C7: Depends on source + content readiness
A8: webCopyReadyFlag | B8: Summary/description ready for frontend copy | C8: Use with frontend exports
A9: publishBlocker | B9: Primary remaining issue | C9: Clear before publish

Sheet Row Review Board
A1: slug | B1: scientificName | C1: editorialOwner | D1: reviewPriority | E1: readinessFlag | F1: publishStatus | G1: qaStatus | H1: reviewStage | I1: reviewStatus | J1: reviewerName | K1: approvalTimestamp | L1: publishBlocker | M1: reviewerNotes | N1: changeSummary | O1: rowReviewKey
A2: ='Herb Monographs'!B2 | B2: ='Herb Monographs'!C2 | C2: ='Herb Monographs'!AP2 | D2: ='Herb Monographs'!AK2 | E2: ='Herb Monographs'!AO2 | F2: ='Herb Monographs'!AR2 | G2: ='Herb Monographs'!AS2 | H2: ='Herb Monographs'!BA2 | I2: ='Herb Monographs'!BB2 | J2: =IF('Herb Monographs'!AY2="","",'Herb Monographs'!AY2) | K2: =IF('Herb Monographs'!BD2="","",'Herb Monographs'!BD2) | L2: =IF('Herb Monographs'!AW2="","",'Herb Monographs'!AW2) | M2: =IF('Herb Monographs'!BC2="","",'Herb Monographs'!BC2) | N2: =IF('Herb Monographs'!BF2="","",'Herb Monographs'!BF2) | O2: ='Herb Monographs'!BG2
A3: ='Herb Monographs'!B3 | B3: ='Herb Monographs'!C3 | C3: ='Herb Monographs'!AP3 | D3: ='Herb Monographs'!AK3 | E3: ='Herb Monographs'!AO3 | F3: ='Herb Monographs'!AR3 | G3: ='Herb Monographs'!AS3 | H3: ='Herb Monographs'!BA3 | I3: ='Herb Monographs'!BB3 | J3: =IF('Herb Monographs'!AY3="","",'Herb Monographs'!AY3) | K3: =IF('Herb Monographs'!BD3="","",'Herb Monographs'!BD3) | L3: =IF('Herb Monographs'!AW3="","",'Herb Monographs'!AW3) | M3: =IF('Herb Monographs'!BC3="","",'Herb Monographs'!BC3) | N3: =IF('Herb Monographs'!BF3="","",'Herb Monographs'!BF3) | O3: ='Herb Monographs'!BG3
A4: ='Herb Monographs'!B4 | B4: ='Herb Monographs'!C4 | C4: ='Herb Monographs'!AP4 | D4: ='Herb Monographs'!AK4 | E4: ='Herb Monographs'!AO4 | F4: ='Herb Monographs'!AR4 | G4: ='Herb Monographs'!AS4 | H4: ='Herb Monographs'!BA4 | I4: ='Herb Monographs'!BB4 | J4: =IF('Herb Monographs'!AY4="","",'Herb Monographs'!AY4) | K4: =IF('Herb Monographs'!BD4="","",'Herb Monographs'!BD4) | L4: =IF('Herb Monographs'!AW4="","",'Herb Monographs'!AW4) | M4: =IF('Herb Monographs'!BC4="","",'Herb Monographs'!BC4) | N4: =IF('Herb Monographs'!BF4="","",'Herb Monographs'!BF4) | O4: ='Herb Monographs'!BG4
A5: ='Herb Monographs'!B5 | B5: ='Herb Monographs'!C5 | C5: ='Herb Monographs'!AP5 | D5: ='Herb Monographs'!AK5 | E5: ='Herb Monographs'!AO5 | F5: ='Herb Monographs'!AR5 | G5: ='Herb Monographs'!AS5 | H5: ='Herb Monographs'!BA5 | I5: ='Herb Monographs'!BB5 | J5: =IF('Herb Monographs'!AY5="","",'Herb Monographs'!AY5) | K5: =IF('Herb Monographs'!BD5="","",'Herb Monographs'!BD5) | L5: =IF('Herb Monographs'!AW5="","",'Herb Monographs'!AW5) | M5: =IF('Herb Monographs'!BC5="","",'Herb Monographs'!BC5) | N5: =IF('Herb Monographs'!BF5="","",'Herb Monographs'!BF5) | O5: ='Herb Monographs'!BG5
A6: ='Herb Monographs'!B6 | B6: ='Herb Monographs'!C6 | C6: ='Herb Monographs'!AP6 | D6: ='Herb Monographs'!AK6 | E6: ='Herb Monographs'!AO6 | F6: ='Herb Monographs'!AR6 | G6: ='Herb Monographs'!AS6 | H6: ='Herb Monographs'!BA6 | I6: ='Herb Monographs'!BB6 | J6: =IF('Herb Monographs'!AY6="","",'Herb Monographs'!AY6) | K6: =IF('Herb Monographs'!BD6="","",'Herb Monographs'!BD6) | L6: =IF('Herb Monographs'!AW6="","",'Herb Monographs'!AW6) | M6: =IF('Herb Monographs'!BC6="","",'Herb Monographs'!BC6) | N6: =IF('Herb Monographs'!BF6="","",'Herb Monographs'!BF6) | O6: ='Herb Monographs'!BG6
A7: ='Herb Monographs'!B7 | B7: ='Herb Monographs'!C7 | C7: ='Herb Monographs'!AP7 | D7: ='Herb Monographs'!AK7 | E7: ='Herb Monographs'!AO7 | F7: ='Herb Monographs'!AR7 | G7: ='Herb Monographs'!AS7 | H7: ='Herb Monographs'!BA7 | I7: ='Herb Monographs'!BB7 | J7: =IF('Herb Monographs'!AY7="","",'Herb Monographs'!AY7) | K7: =IF('Herb Monographs'!BD7="","",'Herb Monographs'!BD7) | L7: =IF('Herb Monographs'!AW7="","",'Herb Monographs'!AW7) | M7: =IF('Herb Monographs'!BC7="","",'Herb Monographs'!BC7) | N7: =IF('Herb Monographs'!BF7="","",'Herb Monographs'!BF7) | O7: ='Herb Monographs'!BG7
A8: ='Herb Monographs'!B8 | B8: ='Herb Monographs'!C8 | C8: ='Herb Monographs'!AP8 | D8: ='Herb Monographs'!AK8 | E8: ='Herb Monographs'!AO8 | F8: ='Herb Monographs'!AR8 | G8: ='Herb Monographs'!AS8 | H8: ='Herb Monographs'!BA8 | I8: ='Herb Monographs'!BB8 | J8: =IF('Herb Monographs'!AY8="","",'Herb Monographs'!AY8) | K8: =IF('Herb Monographs'!BD8="","",'Herb Monographs'!BD8) | L8: =IF('Herb Monographs'!AW8="","",'Herb Monographs'!AW8) | M8: =IF('Herb Monographs'!BC8="","",'Herb Monographs'!BC8) | N8: =IF('Herb Monographs'!BF8="","",'Herb Monographs'!BF8) | O8: ='Herb Monographs'!BG8
A9: ='Herb Monographs'!B9 | B9: ='Herb Monographs'!C9 | C9: ='Herb Monographs'!AP9 | D9: ='Herb Monographs'!AK9 | E9: ='Herb Monographs'!AO9 | F9: ='Herb Monographs'!AR9 | G9: ='Herb Monographs'!AS9 | H9: ='Herb Monographs'!BA9 | I9: ='Herb Monographs'!BB9 | J9: =IF('Herb Monographs'!AY9="","",'Herb Monographs'!AY9) | K9: =IF('Herb Monographs'!BD9="","",'Herb Monographs'!BD9) | L9: =IF('Herb Monographs'!AW9="","",'Herb Monographs'!AW9) | M9: =IF('Herb Monographs'!BC9="","",'Herb Monographs'!BC9) | N9: =IF('Herb Monographs'!BF9="","",'Herb Monographs'!BF9) | O9: ='Herb Monographs'!BG9
A10: ='Herb Monographs'!B10 | B10: ='Herb Monographs'!C10 | C10: ='Herb Monographs'!AP10 | D10: ='Herb Monographs'!AK10 | E10: ='Herb Monographs'!AO10 | F10: ='Herb Monographs'!AR10 | G10: ='Herb Monographs'!AS10 | H10: ='Herb Monographs'!BA10 | I10: ='Herb Monographs'!BB10 | J10: =IF('Herb Monographs'!AY10="","",'Herb Monographs'!AY10) | K10: =IF('Herb Monographs'!BD10="","",'Herb Monographs'!BD10) | L10: =IF('Herb Monographs'!AW10="","",'Herb Monographs'!AW10) | M10: =IF('Herb Monographs'!BC10="","",'Herb Monographs'!BC10) | N10: =IF('Herb Monographs'!BF10="","",'Herb Monographs'!BF10) | O10: ='Herb Monographs'!BG10
A11: ='Herb Monographs'!B11 | B11: ='Herb Monographs'!C11 | C11: ='Herb Monographs'!AP11 | D11: ='Herb Monographs'!AK11 | E11: ='Herb Monographs'!AO11 | F11: ='Herb Monographs'!AR11 | G11: ='Herb Monographs'!AS11 | H11: ='Herb Monographs'!BA11 | I11: ='Herb Monographs'!BB11 | J11: =IF('Herb Monographs'!AY11="","",'Herb Monographs'!AY11) | K11: =IF('Herb Monographs'!BD11="","",'Herb Monographs'!BD11) | L11: =IF('Herb Monographs'!AW11="","",'Herb Monographs'!AW11) | M11: =IF('Herb Monographs'!BC11="","",'Herb Monographs'!BC11) | N11: =IF('Herb Monographs'!BF11="","",'Herb Monographs'!BF11) | O11: ='Herb Monographs'!BG11
A12: ='Herb Monographs'!B12 | B12: ='Herb Monographs'!C12 | C12: ='Herb Monographs'!AP12 | D12: ='Herb Monographs'!AK12 | E12: ='Herb Monographs'!AO12 | F12: ='Herb Monographs'!AR12 | G12: ='Herb Monographs'!AS12 | H12: ='Herb Monographs'!BA12 | I12: ='Herb Monographs'!BB12 | J12: =IF('Herb Monographs'!AY12="","",'Herb Monographs'!AY12) | K12: =IF('Herb Monographs'!BD12="","",'Herb Monographs'!BD12) | L12: =IF('Herb Monographs'!AW12="","",'Herb Monographs'!AW12) | M12: =IF('Herb Monographs'!BC12="","",'Herb Monographs'!BC12) | N12: =IF('Herb Monographs'!BF12="","",'Herb Monographs'!BF12) | O12: ='Herb Monographs'!BG12
A13: ='Herb Monographs'!B13 | B13: ='Herb Monographs'!C13 | C13: ='Herb Monographs'!AP13 | D13: ='Herb Monographs'!AK13 | E13: ='Herb Monographs'!AO13 | F13: ='Herb Monographs'!AR13 | G13: ='Herb Monographs'!AS13 | H13: ='Herb Monographs'!BA13 | I13: ='Herb Monographs'!BB13 | J13: =IF('Herb Monographs'!AY13="","",'Herb Monographs'!AY13) | K13: =IF('Herb Monographs'!BD13="","",'Herb Monographs'!BD13) | L13: =IF('Herb Monographs'!AW13="","",'Herb Monographs'!AW13) | M13: =IF('Herb Monographs'!BC13="","",'Herb Monographs'!BC13) | N13: =IF('Herb Monographs'!BF13="","",'Herb Monographs'!BF13) | O13: ='Herb Monographs'!BG13
... A18: ='Herb Monographs'!B18 | B18: ='Herb Monographs'!C18 | C18: ='Herb Monographs'!AP18 | D18: ='Herb Monographs'!AK18 | E18: ='Herb Monographs'!AO18 | F18: ='Herb Monographs'!AR18 | G18: ='Herb Monographs'!AS18 | H18: ='Herb Monographs'!BA18 | I18: ='Herb Monographs'!BB18 | J18: =IF('Herb Monographs'!AY18="","",'Herb Monographs'!AY18) | K18: =IF('Herb Monographs'!BD18="","",'Herb Monographs'!BD18) | L18: =IF('Herb Monographs'!AW18="","",'Herb Monographs'!AW18) | M18: =IF('Herb Monographs'!BC18="","",'Herb Monographs'!BC18) | N18: =IF('Herb Monographs'!BF18="","",'Herb Monographs'!BF18) | O18: ='Herb Monographs'!BG18

Sheet Change History
A1: logId | B1: timestamp | C1: slug | D1: fieldChanged | E1: oldValue | F1: newValue | G1: changedBy | H1: reviewedBy | I1: approvalTimestamp | J1: changeNote
A2: 1
A3: 2
A4: 3
A5: 4
A6: 5
A7: 6
A8: 7
A9: 8
A10: 9
A11: 10
A12: 11
A13: 12
... A201: 200

Sheet Approval History
A1: rowReviewKey | B1: slug | C1: reviewStatus | D1: approvalTimestamp | E1: reviewerName | F1: sourceLockFlag | G1: frontendReadyFlag | H1: webCopyReadyFlag | I1: publishStatus | J1: qaStatus
A2: ='Herb Monographs'!BG2 | B2: ='Herb Monographs'!B2 | C2: ='Herb Monographs'!BB2 | D2: =IF('Herb Monographs'!BD2="","",'Herb Monographs'!BD2) | E2: =IF('Herb Monographs'!AY2="","",'Herb Monographs'!AY2) | F2: ='Herb Monographs'!AT2 | G2: ='Herb Monographs'!AU2 | H2: ='Herb Monographs'!AV2 | I2: ='Herb Monographs'!AR2 | J2: ='Herb Monographs'!AS2
A3: ='Herb Monographs'!BG3 | B3: ='Herb Monographs'!B3 | C3: ='Herb Monographs'!BB3 | D3: =IF('Herb Monographs'!BD3="","",'Herb Monographs'!BD3) | E3: =IF('Herb Monographs'!AY3="","",'Herb Monographs'!AY3) | F3: ='Herb Monographs'!AT3 | G3: ='Herb Monographs'!AU3 | H3: ='Herb Monographs'!AV3 | I3: ='Herb Monographs'!AR3 | J3: ='Herb Monographs'!AS3
A4: ='Herb Monographs'!BG4 | B4: ='Herb Monographs'!B4 | C4: ='Herb Monographs'!BB4 | D4: =IF('Herb Monographs'!BD4="","",'Herb Monographs'!BD4) | E4: =IF('Herb Monographs'!AY4="","",'Herb Monographs'!AY4) | F4: ='Herb Monographs'!AT4 | G4: ='Herb Monographs'!AU4 | H4: ='Herb Monographs'!AV4 | I4: ='Herb Monographs'!AR4 | J4: ='Herb Monographs'!AS4
A5: ='Herb Monographs'!BG5 | B5: ='Herb Monographs'!B5 | C5: ='Herb Monographs'!BB5 | D5: =IF('Herb Monographs'!BD5="","",'Herb Monographs'!BD5) | E5: =IF('Herb Monographs'!AY5="","",'Herb Monographs'!AY5) | F5: ='Herb Monographs'!AT5 | G5: ='Herb Monographs'!AU5 | H5: ='Herb Monographs'!AV5 | I5: ='Herb Monographs'!AR5 | J5: ='Herb Monographs'!AS5
A6: ='Herb Monographs'!BG6 | B6: ='Herb Monographs'!B6 | C6: ='Herb Monographs'!BB6 | D6: =IF('Herb Monographs'!BD6="","",'Herb Monographs'!BD6) | E6: =IF('Herb Monographs'!AY6="","",'Herb Monographs'!AY6) | F6: ='Herb Monographs'!AT6 | G6: ='Herb Monographs'!AU6 | H6: ='Herb Monographs'!AV6 | I6: ='Herb Monographs'!AR6 | J6: ='Herb Monographs'!AS6
A7: ='Herb Monographs'!BG7 | B7: ='Herb Monographs'!B7 | C7: ='Herb Monographs'!BB7 | D7: =IF('Herb Monographs'!BD7="","",'Herb Monographs'!BD7) | E7: =IF('Herb Monographs'!AY7="","",'Herb Monographs'!AY7) | F7: ='Herb Monographs'!AT7 | G7: ='Herb Monographs'!AU7 | H7: ='Herb Monographs'!AV7 | I7: ='Herb Monographs'!AR7 | J7: ='Herb Monographs'!AS7
A8: ='Herb Monographs'!BG8 | B8: ='Herb Monographs'!B8 | C8: ='Herb Monographs'!BB8 | D8: =IF('Herb Monographs'!BD8="","",'Herb Monographs'!BD8) | E8: =IF('Herb Monographs'!AY8="","",'Herb Monographs'!AY8) | F8: ='Herb Monographs'!AT8 | G8: ='Herb Monographs'!AU8 | H8: ='Herb Monographs'!AV8 | I8: ='Herb Monographs'!AR8 | J8: ='Herb Monographs'!AS8
A9: ='Herb Monographs'!BG9 | B9: ='Herb Monographs'!B9 | C9: ='Herb Monographs'!BB9 | D9: =IF('Herb Monographs'!BD9="","",'Herb Monographs'!BD9) | E9: =IF('Herb Monographs'!AY9="","",'Herb Monographs'!AY9) | F9: ='Herb Monographs'!AT9 | G9: ='Herb Monographs'!AU9 | H9: ='Herb Monographs'!AV9 | I9: ='Herb Monographs'!AR9 | J9: ='Herb Monographs'!AS9
A10: ='Herb Monographs'!BG10 | B10: ='Herb Monographs'!B10 | C10: ='Herb Monographs'!BB10 | D10: =IF('Herb Monographs'!BD10="","",'Herb Monographs'!BD10) | E10: =IF('Herb Monographs'!AY10="","",'Herb Monographs'!AY10) | F10: ='Herb Monographs'!AT10 | G10: ='Herb Monographs'!AU10 | H10: ='Herb Monographs'!AV10 | I10: ='Herb Monographs'!AR10 | J10: ='Herb Monographs'!AS10
A11: ='Herb Monographs'!BG11 | B11: ='Herb Monographs'!B11 | C11: ='Herb Monographs'!BB11 | D11: =IF('Herb Monographs'!BD11="","",'Herb Monographs'!BD11) | E11: =IF('Herb Monographs'!AY11="","",'Herb Monographs'!AY11) | F11: ='Herb Monographs'!AT11 | G11: ='Herb Monographs'!AU11 | H11: ='Herb Monographs'!AV11 | I11: ='Herb Monographs'!AR11 | J11: ='Herb Monographs'!AS11
A12: ='Herb Monographs'!BG12 | B12: ='Herb Monographs'!B12 | C12: ='Herb Monographs'!BB12 | D12: =IF('Herb Monographs'!BD12="","",'Herb Monographs'!BD12) | E12: =IF('Herb Monographs'!AY12="","",'Herb Monographs'!AY12) | F12: ='Herb Monographs'!AT12 | G12: ='Herb Monographs'!AU12 | H12: ='Herb Monographs'!AV12 | I12: ='Herb Monographs'!AR12 | J12: ='Herb Monographs'!AS12
A13: ='Herb Monographs'!BG13 | B13: ='Herb Monographs'!B13 | C13: ='Herb Monographs'!BB13 | D13: =IF('Herb Monographs'!BD13="","",'Herb Monographs'!BD13) | E13: =IF('Herb Monographs'!AY13="","",'Herb Monographs'!AY13) | F13: ='Herb Monographs'!AT13 | G13: ='Herb Monographs'!AU13 | H13: ='Herb Monographs'!AV13 | I13: ='Herb Monographs'!AR13 | J13: ='Herb Monographs'!AS13
... A18: ='Herb Monographs'!BG18 | B18: ='Herb Monographs'!B18 | C18: ='Herb Monographs'!BB18 | D18: =IF('Herb Monographs'!BD18="","",'Herb Monographs'!BD18) | E18: =IF('Herb Monographs'!AY18="","",'Herb Monographs'!AY18) | F18: ='Herb Monographs'!AT18 | G18: ='Herb Monographs'!AU18 | H18: ='Herb Monographs'!AV18 | I18: ='Herb Monographs'!AR18 | J18: ='Herb Monographs'!AS18

Sheet Review Dashboard
A1: Row-Level Review Dashboard
A3: Metric | B3: Value | D3: Next Action | E3: Rule
A4: Total monographs | B4: =COUNTA('Herb Monographs'!B2:B18) | D4: Source review | E4: Publish status = Source review
A5: Approved rows | B5: =COUNTIF('Herb Monographs'!BB2:BB18,"Approved") | D5: Editorial review | E5: Publish status = Editorial polish
A6: In review | B6: =COUNTIF('Herb Monographs'!BB2:BB18,"In review") | D6: QA review | E6: Publish status = Ready for QA
A7: Pending review | B7: =COUNTIF('Herb Monographs'!BB2:BB18,"Pending") | D7: Approve | E7: qaStatus = Passed OR approval timestamp entered
A8: Rows with blockers | B8: =COUNTIF('Herb Monographs'!AW2:AW18,"<>") | D8: Publish | E8: publishStatus = Published
A9: Rows with history entries | B9: =COUNTIF('Herb Monographs'!BH2:BH18,">0")
D10: Metric | E10: Value
D11: Approved timestamps present | E11: =COUNTIF('Herb Monographs'!BD2:BD18,"<>")
D12: Rows missing reviewer notes | E12: =COUNTBLANK('Herb Monographs'!BC2:BC18)

Sheet Review Guide
A1: Field | B1: Meaning | C1: How to use
A2: reviewRound | B2: Iteration number for the row | C2: Increment when a row goes through another formal review pass
A3: reviewerName | B3: Person or function doing the review | C3: Assign when row is actively reviewed
A4: reviewerRole | B4: Type of reviewer | C4: Use Research / Editorial / QA / Medical / Final
A5: reviewStage | B5: Current stage of review | C5: Auto-derived from publish + QA state
A6: reviewStatus | B6: Pending / In review / Approved | C6: Pending until notes or owner set; approved when QA passes or approval timestamp entered
A7: reviewerNotes | B7: Row-specific editorial or medical notes | C7: Capture issues that must be resolved before publish
A8: approvalTimestamp | B8: Date/time row was approved | C8: Enter when final reviewer signs off
A9: lastModifiedTimestamp | B9: Simple workbook timestamp proxy | C9: Auto-populates when row review fields are touched
A10: changeSummary | B10: Short description of what changed | C10: Use concise diff language
A11: rowReviewKey | B11: Stable row + round key | C11: Used to join approval + change history sheets
A12: historyEntries | B12: Count of change-log rows for the slug | C12: Helps identify rows that changed often

Sheet Compound Layer Dashboard
A1: Compound Layer V2 Dashboard | B1: Value | C1: Notes
A2: Total compounds in integrated master | B2: 478 | C2: Unified from compound workbook + cleaned high-signal CSV
A3: Compounds linked to at least one herb | B3: 443 | C3: Reverse lookup ready compounds
A4: Total herb-compound links | B4: 80 | C4: Includes herb-row links and dataset-derived links
A5: Exact herb-row matches | B5: 32 | C5: From Herb Monographs activeCompounds
A6: Dataset-derived links | B6: 0 | C6: From integrated compound dataset
A7: Unmatched herb-row compounds | B7: 48 | C7: Normalization targets for next pass
A8: Unique pathway rows | B8: 655 | C8: Pathway-target index entries
A9: Herbs in enrichment queue | B9: 17 | C9: Current herb layer review queue

Sheet Compound Master V2
A1: canonicalCompoundId | B1: compoundName | C1: aliases | D1: compoundClass | E1: mechanism | F1: mechanismTags | G1: pathwayTargets | H1: pharmacokinetics | I1: safetyNotes | J1: drugInteractions | K1: confidence | L1: evidence | M1: sourceUrls | N1: sourceQuality | O1: sourceBasis | P1: sourceWorkbook | Q1: relatedHerbSlugs | R1: herbCount | S1: reverseLookupReady | T1: integrationNotes
A2: 11-keto-beta-boswellic acid | B2: 11-keto-beta-boswellic acid | D2: organic acid | E2: Boswellic acids, especially AKBA, act as relatively selective 5-lipoxygenase inhibitors and reduce leukotriene synthesis in inflammatory pathways. | F2: multi-target signaling modulation | G2: general or unknown targets | H2: moderate absorption; hepatic metabolism | I2: low | J2: no well-documented interactions | L2: compound_level | M2: https://plants.sc.egov.usda.gov/home/search?query=frankincense%20%28boswellia%29 | https://pubchem.ncbi.nlm.nih.gov/#query=11-keto-beta-boswellic%20acid | N2: trusted_gov_added | O2: PubChem compound page (NIH); USDA Plants database | Q2: frankincense-boswellia | R2: 1 | S2: Yes | T2: Integrated from cleaned high-signal dataset
A3: 5-hydroxytryptophan | B3: 5-hydroxytryptophan (5-HTP) | D3: amino acid derivative | E3: Immediate serotonin precursor formed from tryptophan and decarboxylated by aromatic L-amino-acid decarboxylase to serotonin; strongest mechanism is precursor loading rather than receptor binding. | F3: serotonergic modulation | G3: Aromatic L-amino-acid decarboxylase pathway; HTR1A, HTR2A (serotonin receptors); melatonin precursor biology; serotonin biosynthesis | H3: Crosses the blood-brain barrier, but substantial peripheral decarboxylation to serotonin occurs unless decarboxylase activity is inhibited. | I3: Nausea and vomiting are common; serotonergic toxicity risk rises with interacting serotonergic drugs. | J3: SSRIs/SNRIs/MAOIs/triptans and other serotonergic agents (additive ↑ serotonin-toxicity risk); carbidopa (can increase 5-HTP exposure and GI/serotonergic adverse effects). | K3: High | L3: mixed | M3: https://plants.sc.egov.usda.gov/home/search?query=Griffonia%20simplicifolia | https://pmc.ncbi.nlm.nih.gov/articles/PMC5580516/ | https://pmc.ncbi.nlm.nih.gov/articles/PMC6141939/ | https://pubchem.ncbi.nlm.nih.gov/#query=5-hydroxytryptophan%20%285-htp%29 | https://pubchem.ncbi.nlm.nih.gov/compound/5-Hydroxytryptophan | https://pubchem.ncbi.nlm.nih.gov/compound/Oxitriptan | N3: inferred_plus_trusted_gov | O3: scientific name; PubChem compound page (NIH); USDA Plants database | P3: Batch11_neuroprecursors_2026-04-06 | Q3: griffonia-simplicifolia | R3: 1 | S3: Yes | T3: Integrated from cleaned high-signal dataset; Integrated from compound monograph workbook
A4: 5-meo-dmt | B4: 5-meo-dmt | D4: alkaloid | E4: Tryptamines act on serotonergic receptors, especially 5-HT2A, producing psychedelic effects. | F4: serotonin receptor interaction | G4: serotonergic_5HT2A_agonism | H4: rapid absorption; CNS penetration; hepatic metabolism | I4: moderate-high | J4: avoid with SSRIs/MAOIs; risk of serotonin syndrome | L4: compound_level | M4: https://plants.sc.egov.usda.gov/home/search?query=Anadenanthera%20Colubrina | https://plants.sc.egov.usda.gov/home/search?query=Piptadenia%20peregrina | https://plants.sc.egov.usda.gov/home/search?query=Virola%20calophylla | https://plants.sc.egov.usda.gov/home/search?query=Virola%20elongata | https://plants.sc.egov.usda.gov/home/search?query=Virola%20sebifera | https://plants.sc.egov.usda.gov/home/search?query=Virola%20spp. | https://plants.sc.egov.usda.gov/home/search?query=anadenanthera%20colubrina | https://plants.sc.egov.usda.gov/home/search?query=anadenanthera%20peregrina | https://pubchem.ncbi.nlm.nih.gov/#query=5-methoxy-n%2Cn-dimethyltryptamine | N4: inferred_plus_trusted_gov; trusted_gov_added | O4: PubChem compound page (NIH); USDA Plants database; Unknown; PubChem compound page (NIH); USDA Plants database; scientific name; PubChem compound page (NIH); USDA Plants database | Q4: anadenanthera-colubrina; anadenanthera-colubrina-ceb-l; anadenanthera-peregrina; piptadenia-peregrina; virola-calophylla; virola-elongata; virola-sebifera; virola-spp. | R4: 8 | S4: Yes | T4: Integrated from cleaned high-signal dataset
A5: 6-gingerol | B5: 6-gingerol | D5: other | E5: insufficient evidence | F5: COX/NF-kB inhibition | G5: inflammatory_pathway_modulation | H5: oral absorption; hepatic metabolism; systemic distribution | I5: low | J5: no well-documented interactions | L5: compound_level | M5: https://plants.sc.egov.usda.gov/home/search?query=ginger | https://pubchem.ncbi.nlm.nih.gov/#query=6-gingerol | N5: trusted_gov_added | O5: PubChem compound page (NIH); USDA Plants database | Q5: zingiber-officinale | R5: 1 | S5: Yes | T5: Integrated from cleaned high-signal dataset
A6: 7-hydroxymitragynine | B6: 7-hydroxymitragynine | D6: other | E6: Mitragynine and 7-hydroxymitragynine act as partial agonists at μ-opioid receptors with additional adrenergic and serotonergic activity. | F6: multi-target signaling modulation | G6: general or unknown targets | H6: moderate absorption; hepatic metabolism | I6: low | J6: no well-documented interactions | L6: compound_level | M6: https://plants.sc.egov.usda.gov/home/search?query=Mitragyna%20speciosa | https://plants.sc.egov.usda.gov/home/search?query=kratom%20hybrids | https://pubchem.ncbi.nlm.nih.gov/#query=7-hydroxymitragynine | N6: inferred_plus_trusted_gov; trusted_gov_added | O6: PubChem compound page (NIH); USDA Plants database; scientific name; PubChem compound page (NIH); USDA Plants database | Q6: kratom-hybrids; mitragyna-speciosa | R6: 2 | S6: Yes | T6: Integrated from cleaned high-signal dataset
A7: 8-cineole | B7: 8-cineole | D7: other | E7: insufficient evidence | F7: multi-target signaling modulation | G7: general or unknown targets | H7: Absorption and bioavailability vary; some compounds metabolized via cytochrome P450 enzymes. | I7: low | J7: no well-documented interactions | L7: compound_level | M7: https://plants.sc.egov.usda.gov/home/search?query=Artemisia%20herba-alba | https://plants.sc.egov.usda.gov/home/search?query=catnip | https://pubchem.ncbi.nlm.nih.gov/#query=8-cineole | N7: inferred_plus_trusted_gov; trusted_gov_added | O7: PubChem compound page (NIH); USDA Plants database; scientific name; PubChem compound page (NIH); USDA Plants database | Q7: artemisia-herba-alba; nepeta-cataria | R7: 2 | S7: Yes | T7: Integrated from cleaned high-signal dataset
A8: absinthin | B8: absinthin | D8: other | E8: Thujone is associated with GABA_A receptor antagonism; other constituents contribute bitter, digestive, and broader preclinical bioactivities. | F8: GABAergic modulation | G8: gabaergic_modulation | H8: moderate absorption; hepatic metabolism | I8: low | J8: no well-documented interactions | L8: compound_level | M8: https://plants.sc.egov.usda.gov/home/search?query=artemisia%20absinthium | https://pubchem.ncbi.nlm.nih.gov/#query=absinthin | N8: trusted_gov_added | O8: PubChem compound page (NIH); USDA Plants database | Q8: artemisia-absinthium | R8: 1 | S8: Yes | T8: Integrated from cleaned high-signal dataset
A9: acetyl-11-keto-beta-boswellic acid | B9: acetyl-11-keto-beta-boswellic acid (akba) | D9: organic acid | E9: Boswellic acids, especially AKBA, act as relatively selective 5-lipoxygenase inhibitors and reduce leukotriene synthesis in inflammatory pathways. | F9: multi-target signaling modulation | G9: general or unknown targets | H9: moderate absorption; hepatic metabolism | I9: low | J9: no well-documented interactions | L9: compound_level | M9: https://plants.sc.egov.usda.gov/home/search?query=frankincense%20%28boswellia%29 | https://pubchem.ncbi.nlm.nih.gov/#query=acetyl-11-keto-beta-boswellic%20acid%20%28akba%29 | N9: trusted_gov_added | O9: PubChem compound page (NIH); USDA Plants database | Q9: frankincense-boswellia | R9: 1 | S9: Yes | T9: Integrated from cleaned high-signal dataset
A10: acetyl-beta-boswellic acid | B10: acetyl-beta-boswellic acid | D10: organic acid | E10: Boswellic acids, especially AKBA, act as relatively selective 5-lipoxygenase inhibitors and reduce leukotriene synthesis in inflammatory pathways. | F10: multi-target signaling modulation | G10: general or unknown targets | H10: moderate absorption; hepatic metabolism | I10: low | J10: no well-documented interactions | L10: compound_level | M10: https://plants.sc.egov.usda.gov/home/search?query=frankincense%20%28boswellia%29 | https://pubchem.ncbi.nlm.nih.gov/#query=acetyl-beta-boswellic%20acid | N10: trusted_gov_added | O10: PubChem compound page (NIH); USDA Plants database | Q10: frankincense-boswellia | R10: 1 | S10: Yes | T10: Integrated from cleaned high-signal dataset
A11: acetyl-l-carnitine | B11: acetyl-L-carnitine | D11: amino acid derivative | E11: Facilitates mitochondrial fatty acid transport via the carnitine shuttle and supports acetyl-CoA metabolism. | G11: Carnitine shuttle system; Mitochondrial beta-oxidation | H11: Absorbed orally; crosses the blood-brain barrier. | I11: Generally well tolerated; mild GI upset reported. | J11: Thyroid hormone (possible interaction); anticoagulants (theoretical interaction). | K11: moderate | L11: Batch10 | P11: manual_batch10 | R11: 0 | S11: No | T11: Integrated from compound monograph workbook
A12: aconitine | B12: aconitine | D12: other | E12: insufficient evidence | F12: multi-target signaling modulation | G12: general or unknown targets | H12: Absorption and bioavailability vary; some compounds metabolized via cytochrome P450 enzymes. | I12: low | J12: no well-documented interactions | L12: compound_level | M12: https://plants.sc.egov.usda.gov/home/search?query=Aconitum%20ferox | https://plants.sc.egov.usda.gov/home/search?query=Aconitum%20napellus | https://pubchem.ncbi.nlm.nih.gov/#query=aconitine | N12: inferred_plus_trusted_gov | O12: scientific name; PubChem compound page (NIH); USDA Plants database | Q12: aconitum-ferox; aconitum-napellus | R12: 2 | S12: Yes | T12: Integrated from cleaned high-signal dataset
A13: adenosine | B13: adenosine | D13: polysaccharides | E13: insufficient evidence | F13: adenosine receptor antagonism | G13: adenosine_antagonism | H13: Absorption and bioavailability vary; some compounds metabolized via cytochrome P450 enzymes. | I13: low | J13: no well-documented interactions | L13: compound_level | M13: https://plants.sc.egov.usda.gov/home/search?query=Cordyceps%20sinensis | https://pubchem.ncbi.nlm.nih.gov/#query=adenosine | N13: inferred_plus_trusted_gov | O13: scientific name; PubChem compound page (NIH); USDA Plants database | Q13: cordyceps-sinensis | R13: 1 | S13: Yes | T13: Integrated from cleaned high-signal dataset
A14: aegeline | B14: aegeline | D14: coumarins | E14: insufficient evidence | F14: multi-target signaling modulation | G14: general or unknown targets | H14: moderate absorption; hepatic metabolism | I14: low | J14: no well-documented interactions | L14: compound_level | M14: https://plants.sc.egov.usda.gov/home/search?query=aegle%20marmelos | https://pubchem.ncbi.nlm.nih.gov/#query=aegeline | N14: trusted_gov_added | O14: PubChem compound page (NIH); USDA Plants database | Q14: aegle-marmelos | R14: 1 | S14: Yes | T14: Integrated from cleaned high-signal dataset
A15: aescin | B15: aescin | D15: other | E15: insufficient evidence | F15: multi-target signaling modulation | G15: general or unknown targets | H15: Absorption and bioavailability vary; some compounds metabolized via cytochrome P450 enzymes. | I15: low | J15: no well-documented interactions | L15: compound_level | M15: https://plants.sc.egov.usda.gov/home/search?query=Aesculus%20hippocastanum | https://pubchem.ncbi.nlm.nih.gov/#query=aescin | N15: inferred_plus_trusted_gov | O15: scientific name; PubChem compound page (NIH); USDA Plants database | Q15: aesculus-hippocastanum | R15: 1 | S15: Yes | T15: Integrated from cleaned high-signal dataset
A16: aesculin | B16: aesculin | D16: other | E16: insufficient evidence | F16: multi-target signaling modulation | G16: general or unknown targets | H16: Absorption and bioavailability vary; some compounds metabolized via cytochrome P450 enzymes. | I16: low | J16: no well-documented interactions | L16: compound_level | M16: https://plants.sc.egov.usda.gov/home/search?query=Aesculus%20hippocastanum | https://pubchem.ncbi.nlm.nih.gov/#query=aesculin | N16: inferred_plus_trusted_gov | O16: scientific name; PubChem compound page (NIH); USDA Plants database | Q16: aesculus-hippocastanum | R16: 1 | S16: Yes | T16: Integrated from cleaned high-signal dataset
A17: agnuside | B17: agnuside | D17: Agnuside, flavonoids, diterpenes | E17: insufficient evidence | F17: multi-target signaling modulation | G17: general or unknown targets | H17: Oral; dopamine agonist, pituitary modulator | I17: low | J17: no well-documented interactions | L17: compound_level | M17: https://plants.sc.egov.usda.gov/home/search?query=Vitex%20agnus-castus | https://pubchem.ncbi.nlm.nih.gov/#query=agnuside | N17: inferred_plus_trusted_gov | O17: scientific name; PubChem compound page (NIH); USDA Plants database | Q17: vitex-agnus-castus | R17: 1 | S17: Yes | T17: Integrated from cleaned high-signal dataset
A18: agrimoniin | B18: agrimoniin | D18: Tannins, agrimoniin, flavonoids | E18: insufficient evidence | F18: multi-target signaling modulation | G18: general or unknown targets | H18: Oral; mucosal toning and anti-inflammatory | I18: low | J18: no well-documented interactions | L18: compound_level | M18: https://plants.sc.egov.usda.gov/home/search?query=Agrimonia%20eupatoria | https://pubchem.ncbi.nlm.nih.gov/#query=agrimoniin | N18: inferred_plus_trusted_gov | O18: scientific name; PubChem compound page (NIH); USDA Plants database | Q18: agrimonia-eupatoria | R18: 1 | S18: Yes | T18: Integrated from cleaned high-signal dataset
A19: ajmaline | B19: ajmaline | D19: other | E19: insufficient evidence | F19: multi-target signaling modulation | G19: general or unknown targets | H19: Absorption and bioavailability vary; some compounds metabolized via cytochrome P450 enzymes. | I19: low | J19: no well-documented interactions | L19: compound_level | M19: https://plants.sc.egov.usda.gov/home/search?query=Rauvolfia%20serpentina | https://plants.sc.egov.usda.gov/home/search?query=Rauvolfia%20vomitoria | https://pubchem.ncbi.nlm.nih.gov/#query=ajmaline | N19: inferred_plus_trusted_gov | O19: scientific name; PubChem compound page (NIH); USDA Plants database | Q19: rauvolfia-serpentina; rauvolfia-vomitoria | R19: 2 | S19: Yes | T19: Integrated from cleaned high-signal dataset
A20: ajoene | B20: ajoene | D20: other | E20: insufficient evidence | F20: multi-target signaling modulation | G20: general or unknown targets | H20: Oral; vasodilatory, antibacterial, antithrombotic | I20: low | J20: no well-documented interactions | L20: compound_level | M20: https://plants.sc.egov.usda.gov/home/search?query=Allium%20sativum | https://pubchem.ncbi.nlm.nih.gov/#query=ajoene | N20: inferred_plus_trusted_gov | O20: scientific name; PubChem compound page (NIH); USDA Plants database | Q20: allium-sativum | R20: 1 | S20: Yes | T20: Integrated from cleaned high-signal dataset
A21: akba | B21: akba | D21: other | E21: insufficient evidence | F21: multi-target signaling modulation | G21: general or unknown targets | H21: Absorption and bioavailability vary; some compounds metabolized via cytochrome P450 enzymes. | I21: low | J21: no well-documented interactions | L21: compound_level | M21: https://plants.sc.egov.usda.gov/home/search?query=Boswellia%20sacra | https://pubchem.ncbi.nlm.nih.gov/#query=akba | N21: inferred_plus_trusted_gov | O21: scientific name; PubChem compound page (NIH); USDA Plants database | Q21: boswellia-sacra | R21: 1 | S21: Yes | T21: Integrated from cleaned high-signal dataset
A22: alangine | B22: alangine | D22: alkaloids | E22: insufficient evidence | F22: multi-target signaling modulation | G22: general or unknown targets | H22: Absorption and bioavailability vary; some compounds metabolized via cytochrome P450 enzymes. | I22: low | J22: no well-documented interactions | L22: compound_level | M22: https://plants.sc.egov.usda.gov/home/search?query=Alangium%20salvifolium | https://pubchem.ncbi.nlm.nih.gov/#query=alangine | N22: inferred_plus_trusted_gov | O22: scientific name; PubChem compound page (NIH); USDA Plants database | Q22: alangium-salvifolium | R22: 1 | S22: Yes | T22: Integrated from cleaned high-signal dataset
A23: alchorneine | B23: alchorneine | D23: iboga alkaloids | E23: insufficient evidence | F23: multi-target signaling modulation | G23: general or unknown targets | H23: Absorption and bioavailability vary; some compounds metabolized via cytochrome P450 enzymes. | I23: low | J23: no well-documented interactions | L23: compound_level | M23: https://plants.sc.egov.usda.gov/home/search?query=Alchornea%20floribunda | https://pubchem.ncbi.nlm.nih.gov/#query=alchorneine | N23: inferred_plus_trusted_gov | O23: scientific name; PubChem compound page (NIH); USDA Plants database | Q23: alchornea-floribunda | R23: 1 | S23: Yes | T23: Integrated from cleaned high-signal dataset
... A26: allyl isothiocyanate | B26: allyl isothiocyanate | D26: other | E26: insufficient evidence | F26: multi-target signaling modulation | G26: general or unknown targets | H26: Absorption and bioavailability vary; some compounds metabolized via cytochrome P450 enzymes. | I26: low | J26: no well-documented interactions | L26: compound_level | M26: https://plants.sc.egov.usda.gov/home/search?query=Armoracia%20rusticana | https://pubchem.ncbi.nlm.nih.gov/#query=allyl%20isothiocyanate | N26: inferred_plus_trusted_gov | O26: scientific name; PubChem compound page (NIH); USDA Plants database | Q26: armoracia-rusticana | R26: 1 | S26: Yes | T26: Integrated from cleaned high-signal dataset
A27: aloe-emodin | B27: aloe-emodin | D27: anthraquinone | E27: Modulates MAPK and NF-kB pathways | F27: multi-target signaling modulation | G27: MAPK pathway; NF-kB inhibition; general or unknown targets | H27: Absorption and bioavailability vary; some compounds metabolized via cytochrome P450 enzymes. | I27: low | J27: Laxatives (additive effect) | L27: Batch8 | M27: https://plants.sc.egov.usda.gov/home/search?query=Cassia%20alata | https://plants.sc.egov.usda.gov/home/search?query=Cassia%20occidentalis | https://pubchem.ncbi.nlm.nih.gov/#query=aloe-emodin | N27: inferred_plus_trusted_gov | O27: scientific name; PubChem compound page (NIH); USDA Plants database | P27: precision_monographs_batch8.xlsx | Q27: cassia-alata; cassia-occidentalis | R27: 2 | S27: Yes | T27: Integrated from cleaned high-signal dataset; Integrated from compound monograph workbook
A28: aloin | B28: aloin | D28: Aloin, polysaccharides, anthraquinones | E28: insufficient evidence | F28: multi-target signaling modulation | G28: general or unknown targets | H28: Oral/topical; demulcent and laxative effects | I28: low | J28: no well-documented interactions | L28: compound_level | M28: https://plants.sc.egov.usda.gov/home/search?query=Aloe%20vera | https://pubchem.ncbi.nlm.nih.gov/#query=aloin | N28: inferred_plus_trusted_gov | O28: scientific name; PubChem compound page (NIH); USDA Plants database | Q28: aloe-vera | R28: 1 | S28: Yes | T28: Integrated from cleaned high-signal dataset
A29: alpha-asarone | B29: alpha-asarone | D29: other | E29: insufficient evidence | F29: GABAergic modulation; multi-target signaling modulation | G29: gabaergic_modulation; general or unknown targets | H29: moderate absorption; hepatic metabolism | I29: low | J29: no well-documented interactions | L29: compound_level | M29: https://plants.sc.egov.usda.gov/home/search?query=Acorus%20tatarinowii | https://plants.sc.egov.usda.gov/home/search?query=acorus%20americanus | https://plants.sc.egov.usda.gov/home/search?query=acorus%20calamus | https://plants.sc.egov.usda.gov/home/search?query=acorus%20calamus%20var.%20angustatus | https://pubchem.ncbi.nlm.nih.gov/#query=alpha-asarone | N29: inferred_plus_trusted_gov; trusted_gov_added | O29: PubChem compound page (NIH); USDA Plants database; scientific name; PubChem compound page (NIH); USDA Plants database | Q29: acorus-americanus; acorus-calamus; acorus-calamus-angustatus; acorus-tatarinowii | R29: 4 | S29: Yes | T29: Integrated from cleaned high-signal dataset
A30: alpha-bisabolol | B30: alpha-bisabolol | D30: other | E30: Chamomile's CNS effects are partly attributed to apigenin, which binds at the central benzodiazepine site associated with GABA_A receptor signaling; other constituents contribute anti-inflammatory and spasmolytic activity. | F30: GABAergic modulation | G30: gabaergic_modulation; inflammatory_pathway_modulation | H30: moderate absorption; hepatic metabolism | I30: low | J30: no well-documented interactions | L30: compound_level | M30: https://plants.sc.egov.usda.gov/home/search?query=chamomile | https://pubchem.ncbi.nlm.nih.gov/#query=alpha-bisabolol | N30: trusted_gov_added | O30: PubChem compound page (NIH); USDA Plants database | Q30: matricaria-chamomilla | R30: 1 | S30: Yes | T30: Integrated from cleaned high-signal dataset
A31: alpha-gpc l-alpha-glycerylphosphorylcholine | B31: alpha-GPC (L-alpha-glycerylphosphorylcholine) | D31: choline-containing phospholipid metabolite | E31: Highly bioavailable choline donor that increases choline availability for acetylcholine synthesis and phospholipid metabolism; primary value is precursor loading rather than direct receptor pharmacology. | G31: Acetylcholine synthesis pathway; choline pool replenishment; phospholipid metabolism | H31: Rapid oral absorption with meaningful choline delivery; brain effects are usually discussed in terms of choline availability rather than intact alpha-GPC receptor action. | I31: Usually well tolerated; headache, dizziness, GI upset, and insomnia are the more practical adverse-effect cautions. | J31: Anticholinergic drugs (functional opposition); cholinergic drugs / acetylcholinesterase inhibitors (possible additive cholinergic effects). | K31: Moderate | L31: mixed | M31: https://pubchem.ncbi.nlm.nih.gov/compound/Glycerophosphocholine | https://pubmed.ncbi.nlm.nih.gov/18839195/ | https://pubmed.ncbi.nlm.nih.gov/24482832/ | P31: Batch12_cholinergic_cognition_2026-04-07 | R31: 0 | S31: No | T31: Integrated from compound monograph workbook
A32: alpha-pinene | B32: alpha-pinene | D32: terpenes | E32: insufficient evidence | F32: multi-target signaling modulation | G32: general or unknown targets | H32: Absorption and bioavailability vary; some compounds metabolized via cytochrome P450 enzymes. | I32: low | J32: no well-documented interactions | L32: compound_level | M32: https://plants.sc.egov.usda.gov/home/search?query=Juniperus%20sibirica | https://pubchem.ncbi.nlm.nih.gov/#query=alpha-pinene | N32: inferred_plus_trusted_gov | O32: scientific name; PubChem compound page (NIH); USDA Plants database | Q32: juniperus-sibirica | R32: 1 | S32: Yes | T32: Integrated from cleaned high-signal dataset
A33: alpha-thujone | B33: alpha-thujone | D33: other | E33: Thujone is associated with GABA_A receptor antagonism; other constituents contribute bitter, digestive, and broader preclinical bioactivities. | F33: GABAergic modulation | G33: gabaergic_modulation | H33: moderate absorption; hepatic metabolism | I33: low | J33: no well-documented interactions | L33: compound_level | M33: https://plants.sc.egov.usda.gov/home/search?query=artemisia%20absinthium | https://pubchem.ncbi.nlm.nih.gov/#query=alpha-thujone | N33: trusted_gov_added | O33: PubChem compound page (NIH); USDA Plants database | Q33: artemisia-absinthium | R33: 1 | S33: Yes | T33: Integrated from cleaned high-signal dataset
A34: amarogentin | B34: amarogentin | D34: other | E34: insufficient evidence | F34: multi-target signaling modulation | G34: general or unknown targets | H34: Oral; gastric secretagogue | I34: low | J34: no well-documented interactions | L34: compound_level | M34: https://plants.sc.egov.usda.gov/home/search?query=Gentiana%20lutea | https://pubchem.ncbi.nlm.nih.gov/#query=amarogentin | N34: inferred_plus_trusted_gov | O34: scientific name; PubChem compound page (NIH); USDA Plants database | Q34: gentiana-lutea | R34: 1 | S34: Yes | T34: Integrated from cleaned high-signal dataset
A35: amentoflavone | B35: amentoflavone | D35: biflavonoids | E35: insufficient evidence | F35: multi-target signaling modulation | G35: general or unknown targets | H35: Absorption and bioavailability vary; some compounds metabolized via cytochrome P450 enzymes. | I35: low | J35: no well-documented interactions | L35: compound_level | M35: https://plants.sc.egov.usda.gov/home/search?query=Selaginella%20tamariscina | https://pubchem.ncbi.nlm.nih.gov/#query=amentoflavone | N35: inferred_plus_trusted_gov | O35: scientific name; PubChem compound page (NIH); USDA Plants database | Q35: selaginella-tamariscina | R35: 1 | S35: Yes | T35: Integrated from cleaned high-signal dataset
A36: anabasine | B36: anabasine | D36: other | E36: Nicotine acts as an agonist at nicotinic acetylcholine receptors, increasing dopamine and norepinephrine release. | F36: muscarinic receptor interaction | G36: cholinergic_modulation; dopaminergic_modulation | H36: rapid systemic absorption; crosses BBB; hepatic metabolism | I36: low | J36: no well-documented interactions | L36: compound_level | M36: https://plants.sc.egov.usda.gov/home/search?query=nicotiana%20rustica | https://pubchem.ncbi.nlm.nih.gov/#query=anabasine | N36: trusted_gov_added | O36: PubChem compound page (NIH); USDA Plants database | Q36: nicotiana-rustica | R36: 1 | S36: Yes | T36: Integrated from cleaned high-signal dataset
A37: anethole | B37: anethole | D37: other | E37: insufficient evidence | F37: multi-target signaling modulation | G37: general or unknown targets | H37: Absorption and bioavailability vary; some compounds metabolized via cytochrome P450 enzymes. | I37: low | J37: no well-documented interactions | L37: compound_level | M37: https://plants.sc.egov.usda.gov/home/search?query=Agastache%20foeniculum | https://plants.sc.egov.usda.gov/home/search?query=Foeniculum%20vulgare | https://plants.sc.egov.usda.gov/home/search?query=Pimpinella%20anisum | https://pubchem.ncbi.nlm.nih.gov/#query=anethole | N37: inferred_plus_trusted_gov | O37: scientific name; PubChem compound page (NIH); USDA Plants database | Q37: agastache-foeniculum; foeniculum-vulgare; pimpinella-anisum | R37: 3 | S37: Yes | T37: Integrated from cleaned high-signal dataset
A38: anisomelic acid | B38: anisomelic acid | D38: diterpenes | E38: insufficient evidence | F38: multi-target signaling modulation | G38: general or unknown targets | H38: Absorption and bioavailability vary; some compounds metabolized via cytochrome P450 enzymes. | I38: low | J38: no well-documented interactions | L38: compound_level | M38: https://plants.sc.egov.usda.gov/home/search?query=Anisomeles%20indica | https://pubchem.ncbi.nlm.nih.gov/#query=anisomelic%20acid | N38: inferred_plus_trusted_gov | O38: scientific name; PubChem compound page (NIH); USDA Plants database | Q38: anisomeles-indica | R38: 1 | S38: Yes | T38: Integrated from cleaned high-signal dataset
A39: annonacin | B39: annonacin | D39: other | E39: insufficient evidence | F39: multi-target signaling modulation | G39: general or unknown targets | H39: Absorption and bioavailability vary; some compounds metabolized via cytochrome P450 enzymes. | I39: low | J39: no well-documented interactions | L39: compound_level | M39: https://plants.sc.egov.usda.gov/home/search?query=Annona%20muricata | https://pubchem.ncbi.nlm.nih.gov/#query=annonacin | N39: inferred_plus_trusted_gov | O39: scientific name; PubChem compound page (NIH); USDA Plants database | Q39: annona-muricata | R39: 1 | S39: Yes | T39: Integrated from cleaned high-signal dataset
A40: anonaine | B40: anonaine | D40: other | E40: insufficient evidence | F40: multi-target signaling modulation | G40: general or unknown targets | H40: moderate absorption; hepatic metabolism | I40: low | J40: no well-documented interactions | L40: compound_level | M40: https://plants.sc.egov.usda.gov/home/search?query=american%20yellow%20lotus | https://pubchem.ncbi.nlm.nih.gov/#query=anonaine | N40: trusted_gov_added | O40: PubChem compound page (NIH); USDA Plants database | Q40: nelumbo-lutea | R40: 1 | S40: Yes | T40: Integrated from cleaned high-signal dataset
A41: anthocyanins delphinidin | B41: anthocyanins (delphinidin | D41: other | E41: Anthocyanins and organic acids contribute antioxidant and ACE-inhibitory activity. | F41: multi-target signaling modulation | G41: general or unknown targets | H41: moderate absorption; hepatic metabolism | I41: low | J41: no well-documented interactions | L41: compound_level | M41: https://plants.sc.egov.usda.gov/home/search?query=hibiscus%20sabdariffa | https://pubchem.ncbi.nlm.nih.gov/#query=anthocyanins%20%28delphinidin | N41: trusted_gov_added | O41: PubChem compound page (NIH); USDA Plants database | Q41: hibiscus-sabdariffa | R41: 1 | S41: Yes | T41: Integrated from cleaned high-signal dataset
A42: apigenin | B42: apigenin | D42: other | E42: Chamomile's CNS effects are partly attributed to apigenin, which binds at the central benzodiazepine site associated with GABA_A receptor signaling; other constituents contribute anti-inflammatory and spasmolytic activity. | F42: GABAergic modulation; multi-target signaling modulation; muscarinic receptor interaction | G42: cholinergic_modulation; gabaergic_modulation; general or unknown targets; inflammatory_pathway_modulation | H42: rapid systemic absorption; crosses BBB; hepatic metabolism | I42: low | J42: no well-documented interactions | L42: compound_level | M42: https://plants.sc.egov.usda.gov/home/search?query=Apium%20graveolens | https://plants.sc.egov.usda.gov/home/search?query=Matricaria%20chamomilla | https://plants.sc.egov.usda.gov/home/search?query=amorpha%20fruticosa | https://plants.sc.egov.usda.gov/home/search?query=chamomile | https://plants.sc.egov.usda.gov/home/search?query=turnera%20diffusa | https://pubchem.ncbi.nlm.nih.gov/#query=apigenin | N42: inferred_plus_trusted_gov; trusted_gov_added | O42: PubChem compound page (NIH); USDA Plants database; scientific name; PubChem compound page (NIH); USDA Plants database | Q42: amorpha-fruticosa; apium-graveolens; matricaria-chamomilla; turnera-diffusa | R42: 4 | S42: Yes | T42: Integrated from cleaned high-signal dataset
A43: apomorphine | B43: apomorphine | D43: other | E43: Compounds show dopaminergic receptor interaction and mild sedative effects. | F43: multi-target signaling modulation | G43: dopaminergic_modulation | H43: moderate absorption; hepatic metabolism | I43: low | J43: no well-documented interactions | L43: compound_level | M43: https://plants.sc.egov.usda.gov/home/search?query=Blue%20Lotus | https://pubchem.ncbi.nlm.nih.gov/#query=apomorphine | N43: trusted_gov_added | O43: PubChem compound page (NIH); USDA Plants database | Q43: blue-lotus-nymphaea-caerulea | R43: 1 | S43: Yes | T43: Integrated from cleaned high-signal dataset
... A50: asclepiadin | B50: asclepiadin | D50: Asclepiadin, cardiac glycosides, resins | E50: insufficient evidence | F50: multi-target signaling modulation | G50: general or unknown targets | H50: Oral; expectorant and bronchial tonic | I50: low | J50: no well-documented interactions | L50: compound_level | M50: https://plants.sc.egov.usda.gov/home/search?query=Asclepias%20tuberosa | https://pubchem.ncbi.nlm.nih.gov/#query=asclepiadin | N50: inferred_plus_trusted_gov | O50: scientific name; PubChem compound page (NIH); USDA Plants database | Q50: asclepias-tuberosa | R50: 1 | S50: Yes | T50: Integrated from cleaned high-signal dataset
A51: ashwagandha withanolides | B51: ashwagandha (withanolides) | D51: steroidal lactone | E51: Modulates GABAergic and HPA-axis signaling (stress response) | G51: GABA-A modulation; cortisol regulation | J51: Sedatives (additive CNS depression) | L51: Sprint6 | P51: precision_monographs_sprint6.xlsx | R51: 0 | S51: No | T51: Integrated from compound monograph workbook
A52: asiatic acid | B52: asiatic acid | D52: organic acid | E52: insufficient evidence | F52: COX/NF-kB inhibition; multi-target signaling modulation | G52: general or unknown targets; inflammatory_pathway_modulation | H52: moderate absorption; hepatic metabolism | I52: low | J52: no well-documented interactions | L52: compound_level | M52: https://plants.sc.egov.usda.gov/home/search?query=Centella%20asiatica | https://plants.sc.egov.usda.gov/home/search?query=centella%20asiatica | https://pubchem.ncbi.nlm.nih.gov/#query=asiatic%20acid | N52: inferred_plus_trusted_gov; trusted_gov_added | O52: PubChem compound page (NIH); USDA Plants database; scientific name; PubChem compound page (NIH); USDA Plants database | Q52: centella-asiatica; gotu-kola | R52: 2 | S52: Yes | T52: Integrated from cleaned high-signal dataset
A53: asiaticoside | B53: asiaticoside | D53: other | E53: insufficient evidence | F53: COX/NF-kB inhibition; multi-target signaling modulation | G53: general or unknown targets; inflammatory_pathway_modulation | H53: moderate absorption; hepatic metabolism | I53: low | J53: no well-documented interactions | L53: compound_level | M53: https://plants.sc.egov.usda.gov/home/search?query=Centella%20asiatica | https://plants.sc.egov.usda.gov/home/search?query=centella%20asiatica | https://pubchem.ncbi.nlm.nih.gov/#query=asiaticoside | N53: inferred_plus_trusted_gov; trusted_gov_added | O53: PubChem compound page (NIH); USDA Plants database; scientific name; PubChem compound page (NIH); USDA Plants database | Q53: centella-asiatica; gotu-kola | R53: 2 | S53: Yes | T53: Integrated from cleaned high-signal dataset
A54: asperuloside | B54: asperuloside | D54: Iridoids, tannins, asperuloside | E54: insufficient evidence | F54: multi-target signaling modulation | G54: general or unknown targets | H54: Oral; lymphatic and urinary tonic | I54: low | J54: no well-documented interactions | L54: compound_level | M54: https://plants.sc.egov.usda.gov/home/search?query=Galium%20aparine | https://pubchem.ncbi.nlm.nih.gov/#query=asperuloside | N54: inferred_plus_trusted_gov | O54: scientific name; PubChem compound page (NIH); USDA Plants database | Q54: galium-aparine | R54: 1 | S54: Yes | T54: Integrated from cleaned high-signal dataset
A55: aspidospermine | B55: aspidospermine | D55: yohimbine-type alkaloids | E55: insufficient evidence | F55: multi-target signaling modulation | G55: general or unknown targets | H55: Absorption and bioavailability vary; some compounds metabolized via cytochrome P450 enzymes. | I55: low | J55: no well-documented interactions | L55: compound_level | M55: https://plants.sc.egov.usda.gov/home/search?query=Aspidosperma%20quebracho-blanco | https://pubchem.ncbi.nlm.nih.gov/#query=aspidospermine | N55: inferred_plus_trusted_gov | O55: scientific name; PubChem compound page (NIH); USDA Plants database | Q55: aspidosperma-quebracho-blanco | R55: 1 | S55: Yes | T55: Integrated from cleaned high-signal dataset
A56: astragaloside iv | B56: astragaloside iv | D56: Astragaloside IV, polysaccharides, flavonoids | E56: insufficient evidence | F56: multi-target signaling modulation | G56: general or unknown targets | H56: Oral; macrophage and telomerase activation | I56: low | J56: no well-documented interactions | L56: compound_level | M56: https://plants.sc.egov.usda.gov/home/search?query=Astragalus%20membranaceus | https://pubchem.ncbi.nlm.nih.gov/#query=astragaloside%20iv | N56: inferred_plus_trusted_gov | O56: scientific name; PubChem compound page (NIH); USDA Plants database | Q56: astragalus-membranaceus | R56: 1 | S56: Yes | T56: Integrated from cleaned high-signal dataset
A57: atractylenolide i | B57: atractylenolide i | D57: other | E57: insufficient evidence | F57: multi-target signaling modulation | G57: general or unknown targets | H57: Absorption and bioavailability vary; some compounds metabolized via cytochrome P450 enzymes. | I57: low | J57: no well-documented interactions | L57: compound_level | M57: https://plants.sc.egov.usda.gov/home/search?query=Atractylodes%20macrocephala | https://pubchem.ncbi.nlm.nih.gov/#query=atractylenolide%20i | N57: inferred_plus_trusted_gov | O57: scientific name; PubChem compound page (NIH); USDA Plants database | Q57: atractylodes-macrocephala | R57: 1 | S57: Yes | T57: Integrated from cleaned high-signal dataset
A58: atractylenolide ii | B58: atractylenolide ii | D58: other | E58: insufficient evidence | F58: multi-target signaling modulation | G58: general or unknown targets | H58: Absorption and bioavailability vary; some compounds metabolized via cytochrome P450 enzymes. | I58: low | J58: no well-documented interactions | L58: compound_level | M58: https://plants.sc.egov.usda.gov/home/search?query=Atractylodes%20macrocephala | https://pubchem.ncbi.nlm.nih.gov/#query=atractylenolide%20ii | N58: inferred_plus_trusted_gov | O58: scientific name; PubChem compound page (NIH); USDA Plants database | Q58: atractylodes-macrocephala | R58: 1 | S58: Yes | T58: Integrated from cleaned high-signal dataset
A59: atractylenolide iii | B59: atractylenolide iii | D59: other | E59: insufficient evidence | F59: multi-target signaling modulation | G59: general or unknown targets | H59: Absorption and bioavailability vary; some compounds metabolized via cytochrome P450 enzymes. | I59: low | J59: no well-documented interactions | L59: compound_level | M59: https://plants.sc.egov.usda.gov/home/search?query=Atractylodes%20macrocephala | https://pubchem.ncbi.nlm.nih.gov/#query=atractylenolide%20iii | N59: inferred_plus_trusted_gov | O59: scientific name; PubChem compound page (NIH); USDA Plants database | Q59: atractylodes-macrocephala | R59: 1 | S59: Yes | T59: Integrated from cleaned high-signal dataset
A60: atractylon | B60: atractylon | D60: other | E60: insufficient evidence | F60: multi-target signaling modulation | G60: general or unknown targets | H60: Absorption and bioavailability vary; some compounds metabolized via cytochrome P450 enzymes. | I60: low | J60: no well-documented interactions | L60: compound_level | M60: https://plants.sc.egov.usda.gov/home/search?query=Atractylodes%20macrocephala | https://pubchem.ncbi.nlm.nih.gov/#query=atractylon | N60: inferred_plus_trusted_gov | O60: scientific name; PubChem compound page (NIH); USDA Plants database | Q60: atractylodes-macrocephala | R60: 1 | S60: Yes | T60: Integrated from cleaned high-signal dataset
A61: atropine | B61: atropine | D61: alkaloid | E61: Tropane alkaloids block muscarinic acetylcholine receptors causing central and peripheral anticholinergic effects. | F61: muscarinic receptor interaction | G61: CHRM1, CHRM2 (muscarinic receptors); cholinergic_modulation | H61: Absorption and bioavailability vary; some compounds metabolized via cytochrome P450 enzymes. | I61: high | J61: avoid with other anticholinergics; additive toxicity | L61: compound_level | M61: https://plants.sc.egov.usda.gov/home/search?query=Atropa%20belladonna | https://plants.sc.egov.usda.gov/home/search?query=Brugmansia%20sanguinea | https://plants.sc.egov.usda.gov/home/search?query=Datura%20ferox | https://plants.sc.egov.usda.gov/home/search?query=Datura%20stramonium | https://plants.sc.egov.usda.gov/home/search?query=Datura%20wrightii | https://plants.sc.egov.usda.gov/home/search?query=Mandragora%20officinarum | https://plants.sc.egov.usda.gov/home/search?query=Solandra%20maxima | https://plants.sc.egov.usda.gov/home/search?query=brugmansia | https://plants.sc.egov.usda.gov/home/search?query=brugmansia%20suaveolens | https://plants.sc.egov.usda.gov/home/search?query=mandrake | https://pubchem.ncbi.nlm.nih.gov/#query=atropine | N61: inferred_plus_trusted_gov; trusted_gov_added | O61: PubChem compound page (NIH); USDA Plants database; scientific name; PubChem compound page (NIH); USDA Plants database | Q61: atropa-belladonna; brugmansia; brugmansia-sanguinea; brugmansia-suaveolens; datura-ferox; datura-stramonium; datura-wrightii; mandragora-officinarum; solandra-maxima | R61: 9 | S61: Yes | T61: Integrated from cleaned high-signal dataset
A62: aucubin | B62: aucubin | D62: other | E62: insufficient evidence | F62: multi-target signaling modulation | G62: general or unknown targets | H62: Oral/topical; mucosal and epithelial support | I62: low | J62: no well-documented interactions | L62: compound_level | M62: https://plants.sc.egov.usda.gov/home/search?query=Plantago%20major | https://pubchem.ncbi.nlm.nih.gov/#query=aucubin | N62: inferred_plus_trusted_gov | O62: scientific name; PubChem compound page (NIH); USDA Plants database | Q62: plantago-major | R62: 1 | S62: Yes | T62: Integrated from cleaned high-signal dataset
A63: azadirachtin | B63: azadirachtin | D63: other | E63: insufficient evidence | F63: multi-target signaling modulation | G63: general or unknown targets | H63: Oral/topical; antimicrobial and immune tonic | I63: low | J63: no well-documented interactions | L63: compound_level | M63: https://plants.sc.egov.usda.gov/home/search?query=Azadirachta%20indica | https://pubchem.ncbi.nlm.nih.gov/#query=azadirachtin | N63: inferred_plus_trusted_gov | O63: scientific name; PubChem compound page (NIH); USDA Plants database | Q63: azadirachta-indica | R63: 1 | S63: Yes | T63: Integrated from cleaned high-signal dataset
A64: baicalein | B64: baicalein | D64: flavonoid | E64: American skullcap flavonoids are associated with anticonvulsant and anxiolytic activity; GABAergic signaling and broader neuroinhibitory effects have been proposed in preclinical work. | F64: GABAergic modulation; multi-target signaling modulation | G64: LOX inhibition; NF-kB inhibition; gabaergic_modulation; general or unknown targets | H64: Oral; liver and immune support | I64: low | J64: Anticoagulants (↑ bleeding risk) | L64: Batch8 | M64: https://plants.sc.egov.usda.gov/home/search?query=Scutellaria%20baicalensis | https://plants.sc.egov.usda.gov/home/search?query=scutellaria%20lateriflora | https://pubchem.ncbi.nlm.nih.gov/#query=baicalein | N64: inferred_plus_trusted_gov; trusted_gov_added | O64: PubChem compound page (NIH); USDA Plants database; scientific name; PubChem compound page (NIH); USDA Plants database | P64: precision_monographs_batch8.xlsx | Q64: scutellaria-baicalensis; scutellaria-lateriflora | R64: 2 | S64: Yes | T64: Integrated from cleaned high-signal dataset; Integrated from compound monograph workbook
A65: baicalin | B65: baicalin | D65: other | E65: American skullcap flavonoids are associated with anticonvulsant and anxiolytic activity; GABAergic signaling and broader neuroinhibitory effects have been proposed in preclinical work. | F65: GABAergic modulation; multi-target signaling modulation | G65: gabaergic_modulation; general or unknown targets | H65: Oral; liver and immune support | I65: low | J65: no well-documented interactions | L65: compound_level | M65: https://plants.sc.egov.usda.gov/home/search?query=Scutellaria%20baicalensis | https://plants.sc.egov.usda.gov/home/search?query=scutellaria%20lateriflora | https://pubchem.ncbi.nlm.nih.gov/#query=baicalin | N65: inferred_plus_trusted_gov; trusted_gov_added | O65: PubChem compound page (NIH); USDA Plants database; scientific name; PubChem compound page (NIH); USDA Plants database | Q65: scutellaria-baicalensis; scutellaria-lateriflora | R65: 2 | S65: Yes | T65: Integrated from cleaned high-signal dataset
A66: benzyl benzoate | B66: benzyl benzoate | D66: other | E66: insufficient evidence | F66: multi-target signaling modulation | G66: general or unknown targets | H66: Absorption and bioavailability vary; some compounds metabolized via cytochrome P450 enzymes. | I66: low | J66: no well-documented interactions | L66: compound_level | M66: https://plants.sc.egov.usda.gov/home/search?query=Myroxylon%20balsamum | https://pubchem.ncbi.nlm.nih.gov/#query=benzyl%20benzoate | N66: inferred_plus_trusted_gov | O66: scientific name; PubChem compound page (NIH); USDA Plants database | Q66: myroxylon-balsamum | R66: 1 | S66: Yes | T66: Integrated from cleaned high-signal dataset
A67: benzyl isothiocyanate | B67: benzyl isothiocyanate | D67: other | E67: insufficient evidence | F67: multi-target signaling modulation | G67: general or unknown targets | H67: moderate absorption; hepatic metabolism | I67: low | J67: no well-documented interactions | L67: compound_level | M67: https://plants.sc.egov.usda.gov/home/search?query=carica%20papaya | https://plants.sc.egov.usda.gov/home/search?query=tropaeolum%20majus | https://pubchem.ncbi.nlm.nih.gov/#query=benzyl%20isothiocyanate | N67: trusted_gov_added | O67: PubChem compound page (NIH); USDA Plants database | Q67: carica-papaya; tropaeolum-majus | R67: 2 | S67: Yes | T67: Integrated from cleaned high-signal dataset
A68: berbamine | B68: berbamine | D68: other | E68: insufficient evidence | F68: multi-target signaling modulation | G68: general or unknown targets | H68: Oral; AMPK activation and microbial inhibition | I68: low | J68: no well-documented interactions | L68: compound_level | M68: https://plants.sc.egov.usda.gov/home/search?query=Berberis%20vulgaris | https://pubchem.ncbi.nlm.nih.gov/#query=berbamine | N68: inferred_plus_trusted_gov | O68: scientific name; PubChem compound page (NIH); USDA Plants database | Q68: berberis-vulgaris | R68: 1 | S68: Yes | T68: Integrated from cleaned high-signal dataset
A69: berberine | B69: berberine | D69: alkaloid | E69: Activates AMPK and is reported to inhibit mitochondrial respiratory complex I; downstream effects include modulation of metabolic and inflammatory signaling. | F69: multi-target signaling modulation | G69: AMPK activation; NF-kB pathway inhibition; general or unknown targets; mitochondrial complex I inhibition | H69: Poor oral bioavailability; extensive first-pass/post-oral metabolism; transporter-related disposition including P-glycoprotein involvement. | I69: Common adverse effects are gastrointestinal. Avoid in pregnancy, breastfeeding, and infants because of bilirubin/jaundice risk. | J69: Cyclosporine (documented ↑ blood concentration); P-glycoprotein substrates (possible ↑ exposure); CYP2D6/CYP2C9/CYP3A4 substrates (possible altered exposure); antidiabetic drugs (additive glucose-lowering). | K69: High | L69: compound_level | M69: https://plants.sc.egov.usda.gov/home/search?query=Berberis%20vulgaris | https://plants.sc.egov.usda.gov/home/search?query=Chelidonium%20majus | https://plants.sc.egov.usda.gov/home/search?query=Coptis%20chinensis | https://plants.sc.egov.usda.gov/home/search?query=Hydrastis%20canadensis | https://plants.sc.egov.usda.gov/home/search?query=Phellodendron%20amurense | https://plants.sc.egov.usda.gov/home/search?query=argemone%20mexicana | https://pmc.ncbi.nlm.nih.gov/articles/PMC4898966/ | https://pubchem.ncbi.nlm.nih.gov/#query=berberine | https://pubchem.ncbi.nlm.nih.gov/compound/Berberine | https://pubmed.ncbi.nlm.nih.gov/16133554/ | https://pubmed.ncbi.nlm.nih.gov/16873688/ | https://www.nccih.nih.gov/health/in-the-news-berberine | N69: inferred_plus_trusted_gov; trusted_gov_added | O69: PubChem compound page (NIH); USDA Plants database; scientific name; PubChem compound page (NIH); USDA Plants database | P69: precision_monographs_berberine_eugenol.xlsx | Q69: argemone-mexicana; berberis-vulgaris; chelidonium-majus; coptis-chinensis; hydrastis-canadensis; phellodendron-amurense | R69: 6 | S69: Yes | T69: Integrated from cleaned high-signal dataset; Integrated from compound monograph workbook
A70: beta-amyrin | B70: beta-amyrin | D70: other | E70: insufficient evidence | F70: multi-target signaling modulation | G70: general or unknown targets | H70: moderate absorption; hepatic metabolism | I70: low | J70: no well-documented interactions | L70: compound_level | M70: https://plants.sc.egov.usda.gov/home/search?query=Celastrus%20Paniculatus | https://plants.sc.egov.usda.gov/home/search?query=celastrus%20paniculatus | https://pubchem.ncbi.nlm.nih.gov/#query=beta-amyrin | N70: trusted_gov_added | O70: PubChem compound page (NIH); USDA Plants database | Q70: celastrus-paniculatus; celastrus-paniculatus-intellect-tree | R70: 2 | S70: Yes | T70: Integrated from cleaned high-signal dataset
A71: beta-asarone | B71: beta-asarone | D71: other | E71: insufficient evidence | F71: GABAergic modulation; multi-target signaling modulation | G71: gabaergic_modulation; general or unknown targets | H71: moderate absorption; hepatic metabolism | I71: low | J71: no well-documented interactions | L71: compound_level | M71: https://plants.sc.egov.usda.gov/home/search?query=Acorus%20tatarinowii | https://plants.sc.egov.usda.gov/home/search?query=acorus%20calamus | https://plants.sc.egov.usda.gov/home/search?query=acorus%20calamus%20var.%20angustatus | https://pubchem.ncbi.nlm.nih.gov/#query=beta-asarone | N71: inferred_plus_trusted_gov; trusted_gov_added | O71: PubChem compound page (NIH); USDA Plants database; scientific name; PubChem compound page (NIH); USDA Plants database | Q71: acorus-calamus; acorus-calamus-angustatus; acorus-tatarinowii | R71: 3 | S71: Yes | T71: Integrated from cleaned high-signal dataset
A72: beta-asarone low levels | B72: beta-asarone (low levels) | D72: other | E72: insufficient evidence | F72: multi-target signaling modulation | G72: general or unknown targets | H72: moderate absorption; hepatic metabolism | I72: low | J72: no well-documented interactions | L72: compound_level | M72: https://plants.sc.egov.usda.gov/home/search?query=acorus%20americanus | https://pubchem.ncbi.nlm.nih.gov/#query=beta-asarone%20%28low%20levels%29 | N72: trusted_gov_added | O72: PubChem compound page (NIH); USDA Plants database | Q72: acorus-americanus | R72: 1 | S72: Yes | T72: Integrated from cleaned high-signal dataset
A73: beta-boswellic acid | B73: beta-boswellic acid | D73: organic acid | E73: Boswellic acids, especially AKBA, act as relatively selective 5-lipoxygenase inhibitors and reduce leukotriene synthesis in inflammatory pathways. | F73: multi-target signaling modulation | G73: general or unknown targets | H73: Absorption and bioavailability vary; some compounds metabolized via cytochrome P450 enzymes. | I73: low | J73: no well-documented interactions | L73: compound_level | M73: https://plants.sc.egov.usda.gov/home/search?query=Boswellia%20sacra | https://plants.sc.egov.usda.gov/home/search?query=frankincense%20%28boswellia%29 | https://pubchem.ncbi.nlm.nih.gov/#query=beta-boswellic%20acid | N73: inferred_plus_trusted_gov; trusted_gov_added | O73: PubChem compound page (NIH); USDA Plants database; scientific name; PubChem compound page (NIH); USDA Plants database | Q73: boswellia-sacra; frankincense-boswellia | R73: 2 | S73: Yes | T73: Integrated from cleaned high-signal dataset
A74: beta-caryophyllene | B74: beta-caryophyllene | D74: other | E74: insufficient evidence | F74: multi-target signaling modulation | G74: general or unknown targets | H74: moderate absorption; hepatic metabolism | I74: low | J74: no well-documented interactions | L74: compound_level | M74: https://plants.sc.egov.usda.gov/home/search?query=Copaifera%20officinalis | https://plants.sc.egov.usda.gov/home/search?query=Syzygium%20aromaticum | https://plants.sc.egov.usda.gov/home/search?query=catnip | https://pubchem.ncbi.nlm.nih.gov/#query=beta-caryophyllene | N74: inferred_plus_trusted_gov; trusted_gov_added | O74: PubChem compound page (NIH); USDA Plants database; scientific name; PubChem compound page (NIH); USDA Plants database | Q74: copaifera-officinalis; nepeta-cataria; syzygium-aromaticum | R74: 3 | S74: Yes | T74: Integrated from cleaned high-signal dataset
A75: beta-lapachone | B75: beta-lapachone | D75: other | E75: insufficient evidence | F75: multi-target signaling modulation | G75: general or unknown targets | H75: Absorption and bioavailability vary; some compounds metabolized via cytochrome P450 enzymes. | I75: low | J75: no well-documented interactions | L75: compound_level | M75: https://plants.sc.egov.usda.gov/home/search?query=Tabebuia%20impetiginosa | https://pubchem.ncbi.nlm.nih.gov/#query=beta-lapachone | N75: inferred_plus_trusted_gov | O75: scientific name; PubChem compound page (NIH); USDA Plants database | Q75: tabebuia-impetiginosa | R75: 1 | S75: Yes | T75: Integrated from cleaned high-signal dataset
A76: beta-thujone | B76: beta-thujone | D76: other | E76: Thujone is associated with GABA_A receptor antagonism; other constituents contribute bitter, digestive, and broader preclinical bioactivities. | F76: GABAergic modulation | G76: gabaergic_modulation | H76: moderate absorption; hepatic metabolism | I76: low | J76: no well-documented interactions | L76: compound_level | M76: https://plants.sc.egov.usda.gov/home/search?query=artemisia%20absinthium | https://pubchem.ncbi.nlm.nih.gov/#query=beta-thujone | N76: trusted_gov_added | O76: PubChem compound page (NIH); USDA Plants database | Q76: artemisia-absinthium | R76: 1 | S76: Yes | T76: Integrated from cleaned high-signal dataset
A77: betulinic acid | B77: betulinic acid | D77: polysaccharides | E77: insufficient evidence | F77: multi-target signaling modulation | G77: general or unknown targets | H77: Absorption and bioavailability vary; some compounds metabolized via cytochrome P450 enzymes. | I77: low | J77: no well-documented interactions | L77: compound_level | M77: https://plants.sc.egov.usda.gov/home/search?query=Inonotus%20obliquus | https://pubchem.ncbi.nlm.nih.gov/#query=betulinic%20acid | N77: inferred_plus_trusted_gov | O77: scientific name; PubChem compound page (NIH); USDA Plants database | Q77: inonotus-obliquus | R77: 1 | S77: Yes | T77: Integrated from cleaned high-signal dataset
A78: bilobalide | B78: bilobalide | D78: flavonol glycosides | E78: Ginkgolides antagonize platelet-activating factor (PAF) receptors; bilobalide modulates GABAergic and glutamatergic transmission. | F78: GABAergic modulation | G78: gabaergic_modulation | H78: moderate absorption; hepatic metabolism | I78: low | J78: no well-documented interactions | L78: compound_level | M78: https://plants.sc.egov.usda.gov/home/search?query=ginkgo%20biloba | https://pubchem.ncbi.nlm.nih.gov/#query=bilobalide | N78: trusted_gov_added | O78: PubChem compound page (NIH); USDA Plants database | Q78: ginkgo-biloba | R78: 1 | S78: Yes | T78: Integrated from cleaned high-signal dataset
A79: bisabolol | B79: bisabolol | D79: other | E79: insufficient evidence | F79: multi-target signaling modulation | G79: general or unknown targets | H79: Oral/topical; antispasmodic and sedative | I79: low | J79: no well-documented interactions | L79: compound_level | M79: https://plants.sc.egov.usda.gov/home/search?query=Matricaria%20chamomilla | https://pubchem.ncbi.nlm.nih.gov/#query=bisabolol | N79: inferred_plus_trusted_gov | O79: scientific name; PubChem compound page (NIH); USDA Plants database | Q79: matricaria-chamomilla | R79: 1 | S79: Yes | T79: Integrated from cleaned high-signal dataset
A80: bonducin | B80: bonducin | D80: Bonducin, saponins, diterpenes | E80: insufficient evidence | F80: multi-target signaling modulation | G80: general or unknown targets | H80: Oral; febrifuge and hepatoprotective | I80: low | J80: no well-documented interactions | L80: compound_level | M80: https://plants.sc.egov.usda.gov/home/search?query=Caesalpinia%20bonduc | https://pubchem.ncbi.nlm.nih.gov/#query=bonducin | N80: inferred_plus_trusted_gov | O80: scientific name; PubChem compound page (NIH); USDA Plants database | Q80: caesalpinia-bonduc | R80: 1 | S80: Yes | T80: Integrated from cleaned high-signal dataset
A81: brunfelsamidine | B81: brunfelsamidine | D81: alkaloids | E81: insufficient evidence | F81: multi-target signaling modulation | G81: general or unknown targets | H81: Absorption and bioavailability vary; some compounds metabolized via cytochrome P450 enzymes. | I81: low | J81: no well-documented interactions | L81: compound_level | M81: https://plants.sc.egov.usda.gov/home/search?query=Brunfelsia%20americana | https://pubchem.ncbi.nlm.nih.gov/#query=brunfelsamidine | N81: inferred_plus_trusted_gov | O81: scientific name; PubChem compound page (NIH); USDA Plants database | Q81: brunfelsia-americana | R81: 1 | S81: Yes | T81: Integrated from cleaned high-signal dataset
... A90: cannabidiol | B90: cannabidiol | D90: other | E90: insufficient evidence | F90: multi-target signaling modulation | G90: endocannabinoid_modulation | H90: moderate absorption; hepatic metabolism | I90: low | J90: no well-documented interactions | L90: compound_level | M90: https://plants.sc.egov.usda.gov/home/search?query=cbd | https://pubchem.ncbi.nlm.nih.gov/#query=cannabidiol | N90: trusted_gov_added | O90: PubChem compound page (NIH); USDA Plants database | Q90: cbd | R90: 1 | S90: Yes | T90: Integrated from cleaned high-signal dataset
A91: capsaicin | B91: capsaicin | D91: capsaicinoid | E91: Capsaicinoids, especially capsaicin, act primarily as TRPV1 agonists; downstream effects include sensory neuron activation followed by desensitization and antinociceptive effects. | F91: multi-target signaling modulation | G91: TRPV1 activation; general or unknown targets | H91: moderate absorption; hepatic metabolism | I91: low | J91: Other TRPV1 agents (additive effects) | L91: Batch8 | M91: https://plants.sc.egov.usda.gov/home/search?query=capsicum%20annuum | https://pubchem.ncbi.nlm.nih.gov/#query=capsaicin | N91: trusted_gov_added | O91: PubChem compound page (NIH); USDA Plants database | P91: precision_monographs_batch8.xlsx | Q91: capsicum-annuum | R91: 1 | S91: Yes | T91: Integrated from cleaned high-signal dataset; Integrated from compound monograph workbook
A92: capsanthin | B92: capsanthin | D92: other | E92: Capsaicinoids, especially capsaicin, act primarily as TRPV1 agonists; downstream effects include sensory neuron activation followed by desensitization and antinociceptive effects. | F92: multi-target signaling modulation | G92: general or unknown targets | H92: moderate absorption; hepatic metabolism | I92: low | J92: no well-documented interactions | L92: compound_level | M92: https://plants.sc.egov.usda.gov/home/search?query=capsicum%20annuum | https://pubchem.ncbi.nlm.nih.gov/#query=capsanthin | N92: trusted_gov_added | O92: PubChem compound page (NIH); USDA Plants database | Q92: capsicum-annuum | R92: 1 | S92: Yes | T92: Integrated from cleaned high-signal dataset
A93: capsorubin | B93: capsorubin | D93: other | E93: Capsaicinoids, especially capsaicin, act primarily as TRPV1 agonists; downstream effects include sensory neuron activation followed by desensitization and antinociceptive effects. | F93: multi-target signaling modulation | G93: general or unknown targets | H93: moderate absorption; hepatic metabolism | I93: low | J93: no well-documented interactions | L93: compound_level | M93: https://plants.sc.egov.usda.gov/home/search?query=capsicum%20annuum | https://pubchem.ncbi.nlm.nih.gov/#query=capsorubin | N93: trusted_gov_added | O93: PubChem compound page (NIH); USDA Plants database | Q93: capsicum-annuum | R93: 1 | S93: Yes | T93: Integrated from cleaned high-signal dataset
A94: cardanol | B94: cardanol | D94: other | E94: insufficient evidence | F94: multi-target signaling modulation | G94: general or unknown targets | H94: Absorption and bioavailability vary; some compounds metabolized via cytochrome P450 enzymes. | I94: low | J94: no well-documented interactions | L94: compound_level | M94: https://plants.sc.egov.usda.gov/home/search?query=Anacardium%20occidentale | https://pubchem.ncbi.nlm.nih.gov/#query=cardanol | N94: inferred_plus_trusted_gov | O94: scientific name; PubChem compound page (NIH); USDA Plants database | Q94: anacardium-occidentale | R94: 1 | S94: Yes | T94: Integrated from cleaned high-signal dataset
A95: cardol | B95: cardol | D95: other | E95: insufficient evidence | F95: multi-target signaling modulation | G95: general or unknown targets | H95: Absorption and bioavailability vary; some compounds metabolized via cytochrome P450 enzymes. | I95: low | J95: no well-documented interactions | L95: compound_level | M95: https://plants.sc.egov.usda.gov/home/search?query=Anacardium%20occidentale | https://pubchem.ncbi.nlm.nih.gov/#query=cardol | N95: inferred_plus_trusted_gov | O95: scientific name; PubChem compound page (NIH); USDA Plants database | Q95: anacardium-occidentale | R95: 1 | S95: Yes | T95: Integrated from cleaned high-signal dataset
A96: carnosic acid | B96: carnosic acid | D96: organic acid | E96: insufficient evidence | F96: multi-target signaling modulation | G96: general or unknown targets | H96: Oral; antioxidant and cholagogue | I96: low | J96: no well-documented interactions | L96: compound_level | M96: https://plants.sc.egov.usda.gov/home/search?query=Rosmarinus%20officinalis | https://pubchem.ncbi.nlm.nih.gov/#query=carnosic%20acid | N96: inferred_plus_trusted_gov | O96: scientific name; PubChem compound page (NIH); USDA Plants database | Q96: rosmarinus-officinalis | R96: 1 | S96: Yes | T96: Integrated from cleaned high-signal dataset
A97: carpaine | B97: carpaine | D97: other | E97: insufficient evidence | F97: multi-target signaling modulation | G97: general or unknown targets | H97: moderate absorption; hepatic metabolism | I97: low | J97: no well-documented interactions | L97: compound_level | M97: https://plants.sc.egov.usda.gov/home/search?query=carica%20papaya | https://pubchem.ncbi.nlm.nih.gov/#query=carpaine | N97: trusted_gov_added | O97: PubChem compound page (NIH); USDA Plants database | Q97: carica-papaya | R97: 1 | S97: Yes | T97: Integrated from cleaned high-signal dataset
A98: carvacrol | B98: carvacrol | D98: phenolic monoterpenoid | E98: Activates TRPV3 and TRPA1; broader anti-inflammatory signaling is supported in preclinical/review literature. | F98: multi-target signaling modulation | G98: NF-kB pathway modulation; TRPA1 activation; TRPV3 activation; general or unknown targets | H98: Limited human PK/interactions data for this pass; keep systemic disposition claims conservative. | I98: Irritation and sensitization potential at higher exposure; topical and mucosal tolerability matter. | J98: Other topical irritants/counterirritants (possible additive sensory irritation); CYP-mediated interactions remain plausible but not well established clinically. | K98: moderate | L98: Sprint3 | M98: https://plants.sc.egov.usda.gov/home/search?query=Monarda%20fistulosa | https://plants.sc.egov.usda.gov/home/search?query=Origanum%20vulgare | https://plants.sc.egov.usda.gov/home/search?query=thymus%20vulgaris | https://pmc.ncbi.nlm.nih.gov/articles/PMC8920929/ | https://pmc.ncbi.nlm.nih.gov/articles/PMC9632228/ | https://pubchem.ncbi.nlm.nih.gov/#query=carvacrol | N98: inferred_plus_trusted_gov; trusted_gov_added | O98: PubChem compound page (NIH); USDA Plants database; scientific name; PubChem compound page (NIH); USDA Plants database | P98: precision_monographs_sprint3.xlsx | Q98: monarda-fistulosa; origanum-vulgare; thymus-vulgaris | R98: 3 | S98: Yes | T98: Integrated from cleaned high-signal dataset; Integrated from compound monograph workbook
A99: carvone | B99: carvone | D99: other | E99: insufficient evidence | F99: multi-target signaling modulation | G99: general or unknown targets | H99: Inhalation/topical; calming and antiseptic | I99: low | J99: no well-documented interactions | L99: compound_level | M99: https://plants.sc.egov.usda.gov/home/search?query=Bursera%20graveolens | https://plants.sc.egov.usda.gov/home/search?query=Lippia%20alba | https://pubchem.ncbi.nlm.nih.gov/#query=carvone | N99: inferred_plus_trusted_gov | O99: scientific name; PubChem compound page (NIH); USDA Plants database | Q99: bursera-graveolens; lippia-alba | R99: 2 | S99: Yes | T99: Integrated from cleaned high-signal dataset
A100: casimiroedine | B100: casimiroedine | D100: other | E100: insufficient evidence | F100: multi-target signaling modulation | G100: general or unknown targets | H100: moderate absorption; hepatic metabolism | I100: low | J100: no well-documented interactions | L100: compound_level | M100: https://plants.sc.egov.usda.gov/home/search?query=casimiroa%20edulis | https://pubchem.ncbi.nlm.nih.gov/#query=casimiroedine | N100: trusted_gov_added | O100: PubChem compound page (NIH); USDA Plants database | Q100: casimiroa-edulis | R100: 1 | S100: Yes | T100: Integrated from cleaned high-signal dataset
A101: casticin | B101: casticin | D101: Casticin, flavonoids, iridoids | E101: insufficient evidence | F101: multi-target signaling modulation | G101: general or unknown targets | H101: Oral; modulates estrogenic pathways | I101: low | J101: no well-documented interactions | L101: compound_level | M101: https://plants.sc.egov.usda.gov/home/search?query=Vitex%20trifolia | https://pubchem.ncbi.nlm.nih.gov/#query=casticin | N101: inferred_plus_trusted_gov | O101: scientific name; PubChem compound page (NIH); USDA Plants database | Q101: vitex-trifolia | R101: 1 | S101: Yes | T101: Integrated from cleaned high-signal dataset
A102: catechins | B102: catechins (egcg) | D102: flavonoid | E102: EGCG inhibits catechol-O-methyltransferase (COMT) and activates AMPK; caffeine antagonizes adenosine A1 and A2A receptors. | F102: adenosine receptor antagonism | G102: adenosine_antagonism | H102: moderate absorption; extensive metabolism | I102: low | J102: no well-documented interactions | L102: compound_level | M102: https://plants.sc.egov.usda.gov/home/search?query=camellia%20sinensis | https://pubchem.ncbi.nlm.nih.gov/#query=catechins%20%28egcg%29 | N102: trusted_gov_added | O102: PubChem compound page (NIH); USDA Plants database | Q102: camellia-sinensis | R102: 1 | S102: Yes | T102: Integrated from cleaned high-signal dataset
A103: cathine | B103: cathine | D103: other | E103: insufficient evidence | F103: multi-target signaling modulation | G103: dopaminergic_modulation | H103: moderate absorption; hepatic metabolism | I103: low | J103: no well-documented interactions | L103: compound_level | M103: https://plants.sc.egov.usda.gov/home/search?query=catha%20edulis | https://pubchem.ncbi.nlm.nih.gov/#query=cathine | N103: trusted_gov_added | O103: PubChem compound page (NIH); USDA Plants database | Q103: catha-edulis | R103: 1 | S103: Yes | T103: Integrated from cleaned high-signal dataset
A104: cathinone | B104: cathinone | D104: other | E104: insufficient evidence | F104: multi-target signaling modulation | G104: dopaminergic_modulation | H104: moderate absorption; hepatic metabolism | I104: low | J104: no well-documented interactions | L104: compound_level | M104: https://plants.sc.egov.usda.gov/home/search?query=catha%20edulis | https://pubchem.ncbi.nlm.nih.gov/#query=cathinone | N104: trusted_gov_added | O104: PubChem compound page (NIH); USDA Plants database | Q104: catha-edulis | R104: 1 | S104: Yes | T104: Integrated from cleaned high-signal dataset
A105: cbd | B105: cbd | D105: terpenes | E105: THC acts at CB1 receptors; terpenes may modulate neurotransmitter systems and pharmacokinetics. | F105: multi-target signaling modulation | G105: endocannabinoid_modulation | H105: Absorption and bioavailability vary; some compounds metabolized via cytochrome P450 enzymes. | I105: low | J105: no well-documented interactions | L105: compound_level | M105: https://plants.sc.egov.usda.gov/home/search?query=Cannabis%20indica | https://plants.sc.egov.usda.gov/home/search?query=Cannabis%20ruderalis | https://plants.sc.egov.usda.gov/home/search?query=Cannabis%20sativa%20%28African%20varieties%29 | https://plants.sc.egov.usda.gov/home/search?query=cannabis%20sativa | https://pubchem.ncbi.nlm.nih.gov/#query=cbd | N105: inferred_plus_trusted_gov; trusted_gov_added | O105: PubChem compound page (NIH); USDA Plants database; scientific name; PubChem compound page (NIH); USDA Plants database | Q105: cannabis-indica; cannabis-ruderalis; cannabis-sativa; cannabis-sativa-african-varieties | R105: 4 | S105: Yes | T105: Integrated from cleaned high-signal dataset
A106: celapagin | B106: celapagin | D106: other | E106: insufficient evidence | F106: multi-target signaling modulation | G106: general or unknown targets | H106: moderate absorption; hepatic metabolism | I106: low | J106: no well-documented interactions | L106: compound_level | M106: https://plants.sc.egov.usda.gov/home/search?query=Celastrus%20Paniculatus | https://plants.sc.egov.usda.gov/home/search?query=celastrus%20paniculatus | https://pubchem.ncbi.nlm.nih.gov/#query=celapagin | N106: trusted_gov_added | O106: PubChem compound page (NIH); USDA Plants database | Q106: celastrus-paniculatus; celastrus-paniculatus-intellect-tree | R106: 2 | S106: Yes | T106: Integrated from cleaned high-signal dataset
A107: celapanin | B107: celapanin | D107: other | E107: insufficient evidence | F107: multi-target signaling modulation | G107: general or unknown targets | H107: moderate absorption; hepatic metabolism | I107: low | J107: no well-documented interactions | L107: compound_level | M107: https://plants.sc.egov.usda.gov/home/search?query=Celastrus%20Paniculatus | https://plants.sc.egov.usda.gov/home/search?query=celastrus%20paniculatus | https://pubchem.ncbi.nlm.nih.gov/#query=celapanin | N107: trusted_gov_added | O107: PubChem compound page (NIH); USDA Plants database | Q107: celastrus-paniculatus; celastrus-paniculatus-intellect-tree | R107: 2 | S107: Yes | T107: Integrated from cleaned high-signal dataset
A108: celastrine | B108: celastrine | D108: other | E108: insufficient evidence | F108: multi-target signaling modulation | G108: general or unknown targets | H108: moderate absorption; hepatic metabolism | I108: low | J108: no well-documented interactions | L108: compound_level | M108: https://plants.sc.egov.usda.gov/home/search?query=Celastrus%20Paniculatus | https://plants.sc.egov.usda.gov/home/search?query=celastrus%20paniculatus | https://pubchem.ncbi.nlm.nih.gov/#query=celastrine | N108: trusted_gov_added | O108: PubChem compound page (NIH); USDA Plants database | Q108: celastrus-paniculatus; celastrus-paniculatus-intellect-tree | R108: 2 | S108: Yes | T108: Integrated from cleaned high-signal dataset
A109: cephaeline | B109: cephaeline | D109: Emetine, cephaeline, alkaloids | E109: insufficient evidence | F109: multi-target signaling modulation | G109: general or unknown targets | H109: Oral; expectorant and anti-protozoal | I109: low | J109: no well-documented interactions | L109: compound_level | M109: https://plants.sc.egov.usda.gov/home/search?query=Cephaelis%20ipecacuanha | https://pubchem.ncbi.nlm.nih.gov/#query=cephaeline | N109: inferred_plus_trusted_gov | O109: scientific name; PubChem compound page (NIH); USDA Plants database | Q109: cephaelis-ipecacuanha | R109: 1 | S109: Yes | T109: Integrated from cleaned high-signal dataset
A110: cepharanthine | B110: cepharanthine | D110: biscoclaurine alkaloids | E110: insufficient evidence | F110: multi-target signaling modulation | G110: general or unknown targets | H110: Absorption and bioavailability vary; some compounds metabolized via cytochrome P450 enzymes. | I110: low | J110: no well-documented interactions | L110: compound_level | M110: https://plants.sc.egov.usda.gov/home/search?query=Stephania%20cepharantha | https://pubchem.ncbi.nlm.nih.gov/#query=cepharanthine | N110: inferred_plus_trusted_gov | O110: scientific name; PubChem compound page (NIH); USDA Plants database | Q110: stephania-cepharantha | R110: 1 | S110: Yes | T110: Integrated from cleaned high-signal dataset
... A116: chlorogenic acid | B116: chlorogenic acid | D116: flavonoids; triterpenes | E116: insufficient evidence | F116: multi-target signaling modulation | G116: general or unknown targets | H116: Absorption and bioavailability vary; some compounds metabolized via cytochrome P450 enzymes. | I116: low | J116: no well-documented interactions | L116: compound_level | M116: https://plants.sc.egov.usda.gov/home/search?query=Cecropia%20peltata | https://plants.sc.egov.usda.gov/home/search?query=Lonicera%20japonica | https://plants.sc.egov.usda.gov/home/search?query=Moringa%20oleifera | https://pubchem.ncbi.nlm.nih.gov/#query=chlorogenic%20acid | N116: inferred_plus_trusted_gov | O116: scientific name; PubChem compound page (NIH); USDA Plants database | Q116: cecropia-peltata; lonicera-japonica; moringa-oleifera | R116: 3 | S116: Yes | T116: Integrated from cleaned high-signal dataset
A117: choline | B117: choline | D117: essential nutrient | E117: Precursor for acetylcholine synthesis and phosphatidylcholine membrane formation; involved in methyl-group metabolism. | F117: multi-target signaling modulation | G117: Acetylcholine synthesis pathway; Methylation pathways; Phospholipid metabolism; general or unknown targets | H117: Absorbed in intestine; metabolized to betaine. | I117: Excess intake can cause hypotension, sweating, and fishy body odor. | J117: Anticholinergic drugs (functional opposition ↓ effect). | K117: high | L117: Batch10 | M117: https://plants.sc.egov.usda.gov/home/search?query=Capsella%20bursa-pastoris | https://pubchem.ncbi.nlm.nih.gov/#query=choline | N117: inferred_plus_trusted_gov | O117: scientific name; PubChem compound page (NIH); USDA Plants database | P117: manual_batch10 | Q117: capsella-bursa-pastoris | R117: 1 | S117: Yes | T117: Integrated from cleaned high-signal dataset; Integrated from compound monograph workbook
A118: chrysoeriol | B118: chrysoeriol | D118: other | E118: insufficient evidence | F118: muscarinic receptor interaction | G118: cholinergic_modulation | H118: rapid systemic absorption; crosses BBB; hepatic metabolism | I118: low | J118: no well-documented interactions | L118: compound_level | M118: https://plants.sc.egov.usda.gov/home/search?query=amorpha%20fruticosa | https://pubchem.ncbi.nlm.nih.gov/#query=chrysoeriol | N118: trusted_gov_added | O118: PubChem compound page (NIH); USDA Plants database | Q118: amorpha-fruticosa | R118: 1 | S118: Yes | T118: Integrated from cleaned high-signal dataset
A119: chrysophanol | B119: chrysophanol | D119: other | E119: insufficient evidence | F119: multi-target signaling modulation | G119: general or unknown targets | H119: Absorption and bioavailability vary; some compounds metabolized via cytochrome P450 enzymes. | I119: low | J119: no well-documented interactions | L119: compound_level | M119: https://plants.sc.egov.usda.gov/home/search?query=Cassia%20alata | https://plants.sc.egov.usda.gov/home/search?query=Rheum%20palmatum | https://pubchem.ncbi.nlm.nih.gov/#query=chrysophanol | N119: inferred_plus_trusted_gov | O119: scientific name; PubChem compound page (NIH); USDA Plants database | Q119: cassia-alata; rheum-palmatum | R119: 2 | S119: Yes | T119: Integrated from cleaned high-signal dataset
A120: chymopapain | B120: chymopapain | D120: other | E120: insufficient evidence | F120: multi-target signaling modulation | G120: general or unknown targets | H120: moderate absorption; hepatic metabolism | I120: low | J120: no well-documented interactions | L120: compound_level | M120: https://plants.sc.egov.usda.gov/home/search?query=carica%20papaya | https://pubchem.ncbi.nlm.nih.gov/#query=chymopapain | N120: trusted_gov_added | O120: PubChem compound page (NIH); USDA Plants database | Q120: carica-papaya | R120: 1 | S120: Yes | T120: Integrated from cleaned high-signal dataset
A121: cineole | B121: cineole | D121: other | E121: insufficient evidence | F121: multi-target signaling modulation | G121: general or unknown targets | H121: Absorption and bioavailability vary; some compounds metabolized via cytochrome P450 enzymes. | I121: low | J121: no well-documented interactions | L121: compound_level | M121: https://plants.sc.egov.usda.gov/home/search?query=Artemisia%20judaica | https://plants.sc.egov.usda.gov/home/search?query=Artemisia%20vulgaris | https://plants.sc.egov.usda.gov/home/search?query=Laurus%20nobilis | https://plants.sc.egov.usda.gov/home/search?query=Melaleuca%20alternifolia | https://plants.sc.egov.usda.gov/home/search?query=Rosmarinus%20officinalis | https://plants.sc.egov.usda.gov/home/search?query=Salvia%20officinalis | https://pubchem.ncbi.nlm.nih.gov/#query=cineole | N121: inferred_plus_trusted_gov | O121: scientific name; PubChem compound page (NIH); USDA Plants database | Q121: artemisia-judaica; artemisia-vulgaris; laurus-nobilis; melaleuca-alternifolia; rosmarinus-officinalis; salvia-officinalis | R121: 6 | S121: Yes | T121: Integrated from cleaned high-signal dataset
...

Sheet Herb Compound Map V2
A1: herbSlug | B1: herbName | C1: rawCompound | D1: canonicalCompoundId | E1: canonicalCompoundName | F1: source | G1: matchType | H1: mappingConfidence | I1: compoundPresentInMaster | J1: pathwayTargets | K1: mechanismTags
A2: ashwagandha | B2: Ashwagandha | C2: withaferin A | D2: withaferin a | E2: withaferin A | F2: herb_master_activeCompounds | G2: unmatched | H2: needs-normalization | I2: No
A3: ashwagandha | B3: Ashwagandha | C3: withanolide D | D3: withanolide d | E3: withanolide d) | F3: herb_master_activeCompounds | G3: exact | H3: confirmed-in-herb-row | I3: Yes | J3: gabaergic_modulation; inflammatory_pathway_modulation | K3: COX/NF-kB inhibition; GABAergic modulation
A4: ashwagandha | B4: Ashwagandha | C4: withanolide A | D4: withanolide a | E4: withanolide A | F4: herb_master_activeCompounds | G4: unmatched | H4: needs-normalization | I4: No
A5: ashwagandha | B5: Ashwagandha | C5: withanoside IV | D5: withanoside iv | E5: withanoside IV | F5: herb_master_activeCompounds | G5: unmatched | H5: needs-normalization | I5: No
A6: ashwagandha | B6: Ashwagandha | C6: sitoindosides | D6: sitoindosides | E6: sitoindosides | F6: herb_master_activeCompounds | G6: unmatched | H6: needs-normalization | I6: No
A7: ashwagandha | B7: Ashwagandha | C7: alkaloids | D7: alkaloids | E7: alkaloids | F7: herb_master_activeCompounds | G7: unmatched | H7: needs-normalization | I7: No
A8: black-cohosh | B8: Black Cohosh | C8: triterpene glycosides (actein, 23-epi-26-deoxyactein) | D8: triterpene glycosides actein 23-epi-26-deoxyactein | E8: triterpene glycosides (actein, 23-epi-26-deoxyactein) | F8: herb_master_activeCompounds | G8: unmatched | H8: needs-normalization | I8: No
A9: black-cohosh | B9: Black Cohosh | C9: cimifugoside | D9: cimifugoside | E9: cimifugoside | F9: herb_master_activeCompounds | G9: unmatched | H9: needs-normalization | I9: No
A10: black-cohosh | B10: Black Cohosh | C10: caffeic acid derivatives | D10: caffeic acid derivatives | E10: caffeic acid derivatives | F10: herb_master_activeCompounds | G10: unmatched | H10: needs-normalization | I10: No
A11: black-cohosh | B11: Black Cohosh | C11: fukinolic acid | D11: fukinolic acid | E11: fukinolic acid | F11: herb_master_activeCompounds | G11: unmatched | H11: needs-normalization | I11: No
A12: echinacea-purpurea | B12: Echinacea Purpurea | C12: alkamides | D12: alkamides | E12: alkamides | F12: herb_master_activeCompounds | G12: unmatched | H12: needs-normalization | I12: No
A13: echinacea-purpurea | B13: Echinacea Purpurea | C13: chicoric acid | D13: chicoric acid | E13: chicoric acid | F13: herb_master_activeCompounds | G13: unmatched | H13: needs-normalization | I13: No
A14: echinacea-purpurea | B14: Echinacea Purpurea | C14: echinacoside | D14: echinacoside | E14: echinacoside | F14: herb_master_activeCompounds | G14: unmatched | H14: needs-normalization | I14: No
